Workbook

Sheet G. Corriente
D3: Producto | E3: Precio | F3: Fecha | G3: Precio | H3: Fecha | I3: Precio | J3: Fecha | K3: Precio | L3: Fecha | M3: Precio | N3: Fecha
D4: G. Corriente | E4: 15590 | F4: 46054 | G4: 15190 | H4: 46058
B6: Día | D6: Inv Inicial | E6: Ventas | F6: Recibos | G6: Inv Teorico | H6: Inv Final | I6: Fluc Dia | J6: Fluc Acum | K6: Fluctuacion ($)
B7: 1 | C7: D | D7: 7703.17 | E7: 4423.23 | F7: =+Facturas!D4+Facturas!D5 -> 0 | G7: =+D7+F7-E7 -> 3279.94 | H7: 3306.41 | I7: =IF(E7=0,0,+H7-G7) -> 26.47 | J7: =+I7 -> 26.47 | K7: =+J7*$E$4 -> 412667.3
B8: 2 | C8: L | D8: =+H7 -> 3306.41 | E8: 2776.75 | F8: =+Facturas!D6+Facturas!D7 -> 5800 | G8: =+D8+F8-E8 -> 6329.66 | H8: 6356.311 | I8: =IF(E8=0,0,+H8-G8) -> 26.651 | J8: =+J7+I8 -> 53.121 | K8: =+J8*$E$4 -> 828156.39
B9: 3 | C9: M | D9: =+H8 -> 6356.311 | E9: 2808.95 | F9: =+Facturas!D8+Facturas!D9 -> 4000 | G9: =+D9+F9-E9 -> 7547.361 | H9: 7608.221 | I9: =IF(E9=0,0,+H9-G9) -> 60.86 | J9: =+J8+I9 -> 113.981 | K9: =+J9*$E$4 -> 1776963.8
B10: 4 | C10: M | D10: =+H9 -> 7608.221 | E10: 2858.38 | F10: =+Facturas!D10+Facturas!D11 -> 2800 | G10: =+D10+F10-E10 -> 7549.841 | H10: 7464.081 | I10: =IF(E10=0,0,+H10-G10) -> -85.76 | J10: =+J9+I10 -> 28.221 | K10: =+J10*$E$4 -> 439965.39
B11: 5 | C11: J | D11: =+H10 -> 7464.081 | E11: 1395.91 | F11: =+Facturas!D12+Facturas!D13 -> 2800 | G11: =+D11+F11-E11 -> 8868.171 | H11: 8778.85 | I11: =IF(E11=0,0,+H11-G11) -> -89.321 | J11: =+J10+I11 -> -61.1 | K11: =+J11*$G$4 -> -928109
B12: 6 | C12: V | D12: =+H11 -> 8778.85 | E12: 3847.01 | F12: =+Facturas!D14+Facturas!D15 -> 4600 | G12: =+D12+F12-E12 -> 9531.84 | H12: 9476.071 | I12: =IF(E12=0,0,+H12-G12) -> -55.769 | J12: =+J11+I12 -> -116.869 | K12: =+J12*$G$4 -> -1775240.1
B13: 7 | C13: S | D13: =+H12 -> 9476.071 | E13: 4825.95 | F13: =+Facturas!D16+Facturas!D17 -> 4600 | G13: =+D13+F13-E13 -> 9250.121 | H13: 9256.63 | I13: =IF(E13=0,0,+H13-G13) -> 6.509 | J13: =+J12+I13 -> -110.36 | K13: =+J13*$G$4 -> -1676368.4
B14: 8 | C14: D | D14: =+H13 -> 9256.63 | E14: 4423.63 | F14: =+Facturas!D18+Facturas!D19 -> 0 | G14: =+D14+F14-E14 -> 4833 | H14: 5037.03 | I14: =IF(E14=0,0,+H14-G14) -> 204.03 | J14: =+J13+I14 -> 93.67 | K14: =+J14*$G$4 -> 1422847.3
B15: 9 | C15: L | D15: =+H14 -> 5037.03 | E15: 3218.93 | F15: =+Facturas!D20+Facturas!D21 -> 4600 | G15: =+D15+F15-E15 -> 6418.1 | H15: 6356.311 | I15: =IF(E15=0,0,+H15-G15) -> -61.789 | J15: =+J14+I15 -> 31.881 | K15: =+J15*$G$4 -> 484272.39
B16: 10 | C16: M | D16: =+H15 -> 6356.311 | E16: 3206.85 | F16: =+Facturas!D22+Facturas!D23 -> 3700 | G16: =+D16+F16-E16 -> 6849.461 | H16: 6818.73 | I16: =IF(E16=0,0,+H16-G16) -> -30.731 | J16: =+J15+I16 -> 1.15 | K16: =+J16*$G$4 -> 17468.5
B17: 11 | C17: M | D17: =+H16 -> 6818.73 | E17: 3318.89 | F17: =+Facturas!D24+Facturas!D25 -> 1800 | G17: =+D17+F17-E17 -> 5299.84 | H17: 5302.771 | I17: =IF(E17=0,0,+H17-G17) -> 2.931 | J17: =+J16+I17 -> 4.081 | K17: =+J17*$G$4 -> 61990.39
B18: 12 | C18: J | D18: =+H17 -> 5302.771 | E18: 3262.23 | F18: =+Facturas!D26+Facturas!D27 -> 4000 | G18: =+D18+F18-E18 -> 6040.541 | H18: 6043.01 | I18: =IF(E18=0,0,+H18-G18) -> 2.469 | J18: =+J17+I18 -> 6.55 | K18: =+J18*$G$4 -> 99494.5
B19: 13 | C19: V | D19: =+H18 -> 6043.01 | E19: 3666.17 | F19: =+Facturas!D28+Facturas!D29 -> 4000 | G19: =+D19+F19-E19 -> 6376.84 | H19: 6804.18 | I19: =IF(E19=0,0,+H19-G19) -> 427.34 | J19: =+J18+I19 -> 433.89 | K19: =+J19*$G$4 -> 6590789.1
B20: 14 | C20: S | D20: =+H19 -> 6804.18 | E20: 5758.98 | F20: =+Facturas!D30+Facturas!D31 -> 7400 | G20: =+D20+F20-E20 -> 8445.2 | H20: 7982.13 | I20: =IF(E20=0,0,+H20-G20) -> -463.07 | J20: =+J19+I20 -> -29.18 | K20: =+J20*$G$4 -> -443244.2
B21: 15 | C21: D | D21: =+H20 -> 7982.13 | E21: 4787.87 | F21: =+Facturas!D32+Facturas!D33 -> 4600 | G21: =+D21+F21-E21 -> 7794.26 | H21: 8118.09 | I21: =IF(E21=0,0,+H21-G21) -> 323.83 | J21: =+J20+I21 -> 294.65 | K21: =+J21*$G$4 -> 4475733.5
B22: 16 | C22: L | D22: =+H21 -> 8118.09 | E22: 3117.04 | F22: =+Facturas!D34+Facturas!D35 -> 0 | G22: =+D22+F22-E22 -> 5001.05 | H22: 4771.391 | I22: =IF(E22=0,0,+H22-G22) -> -229.659 | J22: =+J21+I22 -> 64.991 | K22: =+J22*$G$4 -> 987213.29
B23: 17 | C23: M | D23: =+H22 -> 4771.391 | E23: 3498.07 | F23: =+Facturas!D36+Facturas!D37 -> 7900 | G23: =+D23+F23-E23 -> 9173.321 | H23: 5779.741 | I23: =IF(E23=0,0,+H23-G23) -> -3393.58 | J23: =+J22+I23 -> -3328.589 | K23: =+J23*$G$4 -> -50561267
B24: 18 | C24: M | D24: =+H23 -> 5779.741 | E24: 3360.64 | F24: =+Facturas!D38+Facturas!D39 -> 1800 | G24: =+D24+F24-E24 -> 4219.101 | H24: 7512.351 | I24: =IF(E24=0,0,+H24-G24) -> 3293.25 | J24: =+J23+I24 -> -35.339 | K24: =+J24*$G$4 -> -536799.41
B25: 19 | C25: J | D25: =+H24 -> 7512.351 | E25: 3465.34 | F25: =+Facturas!D40+Facturas!D41 -> 0 | G25: =+D25+F25-E25 -> 4047.011 | H25: 4084.5 | I25: =IF(E25=0,0,+H25-G25) -> 37.489 | J25: =+J24+I25 -> 2.15 | K25: =+J25*$G$4 -> 32658.5
B26: 20 | C26: V | D26: =+H25 -> 4084.5 | E26: 4211.55 | F26: =+Facturas!D42+Facturas!D43 -> 3500 | G26: =+D26+F26-E26 -> 3372.95 | H26: 3357.611 | I26: =IF(E26=0,0,+H26-G26) -> -15.339 | J26: =+J25+I26 -> -13.189 | K26: =+J26*$G$4 -> -200340.91
B27: 21 | C27: S | D27: =+H26 -> 3357.611 | E27: 5393.43 | F27: =+Facturas!D44+Facturas!D45 -> 5800 | G27: =+D27+F27-E27 -> 3764.181 | H27: 3822.94 | I27: =IF(E27=0,0,+H27-G27) -> 58.759 | J27: =+J26+I27 -> 45.57 | K27: =+J27*$G$4 -> 692208.3
B28: 22 | C28: D | D28: =+H27 -> 3822.94 | E28: 4222.01 | F28: =+Facturas!D46+Facturas!D47 -> 5800 | G28: =+D28+F28-E28 -> 5400.93 | H28: 5355.88 | I28: =IF(E28=0,0,+H28-G28) -> -45.05 | J28: =+J27+I28 -> 0.52 | K28: =+J28*$G$4 -> 7898.8
B29: 23 | C29: L | D29: =+H28 -> 5355.88 | E29: 3304.58 | F29: =+Facturas!D48+Facturas!D49 -> 3500 | G29: =+D29+F29-E29 -> 5551.3 | H29: 5568.11 | I29: =IF(E29=0,0,+H29-G29) -> 16.81 | J29: =+J28+I29 -> 17.33 | K29: =+J29*$G$4 -> 263242.7
B30: 24 | C30: M | D30: =+H29 -> 5568.11 | E30: 3183.75 | F30: =+Facturas!D50+Facturas!D51 -> 4000 | G30: =+D30+F30-E30 -> 6384.36 | H30: 6356.311 | I30: =IF(E30=0,0,+H30-G30) -> -28.049 | J30: =+J29+I30 -> -10.719 | K30: =+J30*$G$4 -> -162821.61
B31: 25 | C31: M | D31: =+H30 -> 6356.311 | E31: 3467.68 | F31: =+Facturas!D52+Facturas!D53 -> 2700 | G31: =+D31+F31-E31 -> 5588.631 | H31: 5668.701 | I31: =IF(E31=0,0,+H31-G31) -> 80.07 | J31: =+J30+I31 -> 69.351 | K31: =+J31*$G$4 -> 1053441.7
B32: 26 | C32: J | D32: =+H31 -> 5668.701 | E32: 3178.01 | F32: =+Facturas!D54+Facturas!D55 -> 2700 | G32: =+D32+F32-E32 -> 5190.691 | H32: 5090.181 | I32: =IF(E32=0,0,+H32-G32) -> -100.51 | J32: =+J31+I32 -> -31.159 | K32: =+J32*$G$4 -> -473305.21
B33: 27 | C33: V | D33: =+H32 -> 5090.181 | E33: 4230.98 | F33: =+Facturas!D56+Facturas!D57 -> 8700 | G33: =+D33+F33-E33 -> 9559.201 | H33: 6147.8 | I33: =IF(E33=0,0,+H33-G33) -> -3411.401 | J33: =+J32+I33 -> -3442.56 | K33: =+J33*$G$4 -> -52292486
B34: 28 | C34: S | D34: =+H33 -> 6147.8 | E34: 6102.09 | F34: =+Facturas!D58+Facturas!D59 -> 3500 | G34: =+D34+F34-E34 -> 3545.71 | H34: 6919.96 | I34: =IF(E34=0,0,+H34-G34) -> 3374.25 | J34: =+J33+I34 -> -68.31 | K34: =+J34*$G$4 -> -1037628.9
B35: 29 | C35: D | D35: =+H34 -> 6919.96 | F35: =+Facturas!D60+Facturas!D61 -> 0 | G35: =+D35+F35-E35 -> 6919.96 | I35: =IF(E35=0,0,+H35-G35) -> 0 | J35: =+J34+I35 -> -68.31 | K35: =+J35*$G$4 -> -1037628.9
B36: 30 | C36: L | D36: =+H35 -> 0 | F36: =+Facturas!D62+Facturas!D63 -> 0 | G36: =+D36+F36-E36 -> 0 | I36: =IF(E36=0,0,+H36-G36) -> 0 | J36: =+J35+I36 -> -68.31 | K36: =+J36*$G$4 -> -1037628.9
B37: 31 | C37: M | D37: =+H36 -> 0 | F37: =+Facturas!D64+Facturas!D65 -> 0 | G37: =+D37+F37-E37 -> 0 | I37: =IF(E37=0,0,+H37-G37) -> 0 | J37: =+J36+I37 -> -68.31 | K37: =+J37*$G$4 -> -1037628.9
E38: =SUM(E7:E37) -> 105314.9 | F38: =SUM(F7:F37) -> 104600
D39: PROM. DIA | E39: =+AVERAGEIF(E7:E37,">0",E7:E37) -> 3761.2464 | F39: =+AVERAGEIF(F7:F37,">0",F7:F37) -> 4358.3333
D40: 31 | E40: =+E39*D40 -> 116598.64 | F40: =+E40/Presupuesto!#REF! -> #REF!

Sheet Bioacem
D3: Producto | E3: Precio | F3: Fecha | G3: Precio | H3: Fecha | I3: Precio | J3: Fecha | K3: Precio | L3: Fecha
D4: Bioacem | E4: 10750 | F4: 46043
B6: Día | D6: Inv Inicial | E6: Ventas | F6: Recibos | G6: Inv Teorico | H6: Inv Final | I6: Fluc Dia | J6: Fluc Acum | K6: Venta Fluct ($)
B7: 1 | C7: =+'G. Corriente'!C7 -> D | D7: =9641.241+3010.186 -> 12651.427 | E7: 1255.44 | F7: =+Facturas!G4+Facturas!G5 -> 0 | G7: =+D7+F7-E7 -> 11395.987 | H7: =9499.8+1895.734 -> 11395.534 | I7: =IF(E7=0,0,+H7-G7) -> -0.453 | J7: =+I7 -> -0.453 | K7: =+J7*$E$4 -> -4869.75
B8: 2 | C8: =+'G. Corriente'!C8 -> L | D8: =+H7 -> 11395.534 | E8: 5294.17 | F8: =+Facturas!G6+Facturas!G7 -> 2800 | G8: =+D8+F8-E8 -> 8901.364 | H8: =6388.98+4268 -> 10656.98 | I8: =IF(E8=0,0,+H8-G8) -> 1755.616 | J8: =+J7+I8 -> 1755.163 | K8: =+J8*$E$4 -> 18868002
B9: 3 | C9: =+'G. Corriente'!C9 -> M | D9: =+H8 -> 10656.98 | E9: 5289.52 | F9: =+Facturas!G8+Facturas!G9 -> 4600 | G9: =+D9+F9-E9 -> 9967.46 | H9: 8419 | I9: =IF(E9=0,0,+H9-G9) -> -1548.46 | J9: =+J8+I9 -> 206.703 | K9: =+J9*$E$4 -> 2222057.3
B10: 4 | C10: =+'G. Corriente'!C10 -> M | D10: =+H9 -> 8419 | E10: 5582.65 | F10: =+Facturas!G10+Facturas!G11 -> 5800 | G10: =+D10+F10-E10 -> 8636.35 | H10: =5687.791+2887.646 -> 8575.437 | I10: =IF(E10=0,0,+H10-G10) -> -60.913 | J10: =+J9+I10 -> 145.79 | K10: =+J10*$E$4 -> 1567242.5
B11: 5 | C11: =+'G. Corriente'!C11 -> J | D11: =+H10 -> 8575.437 | E11: 5661.36 | F11: =+Facturas!G12+Facturas!G13 -> 3500 | G11: =+D11+F11-E11 -> 6414.077 | H11: =5951.161+457.326 -> 6408.487 | I11: =IF(E11=0,0,+H11-G11) -> -5.59 | J11: =+J10+I11 -> 140.2 | K11: =+J11*$E$4 -> 1507150
B12: 6 | C12: =+'G. Corriente'!C12 -> V | D12: =+H11 -> 6408.487 | E12: 4443.78 | F12: =+Facturas!G14+Facturas!G15 -> 8700 | G12: =+D12+F12-E12 -> 10664.707 | H12: =7082.96+3327.073 -> 10410.033 | I12: =IF(E12=0,0,+H12-G12) -> -254.674 | J12: =+J11+I12 -> -114.474 | K12: =+J12*$E$4 -> -1230595.5
B13: 7 | C13: =+'G. Corriente'!C13 -> S | D13: =+H12 -> 10410.033 | E13: 4198.96 | F13: =+Facturas!G16+Facturas!G17 -> 3500 | G13: =+D13+F13-E13 -> 9711.073 | H13: =6881.8+3190.855 -> 10072.655 | I13: =IF(E13=0,0,+H13-G13) -> 361.582 | J13: =+J12+I13 -> 247.108 | K13: =+J13*$E$4 -> 2656411
B14: 8 | C14: =+'G. Corriente'!C14 -> D | D14: =+H13 -> 10072.655 | E14: 1773.03 | F14: =+Facturas!G18+Facturas!G19 -> 0 | G14: =+D14+F14-E14 -> 8299.625 | H14: =5845.971+2665.554 -> 8511.525 | I14: =IF(E14=0,0,+H14-G14) -> 211.9 | J14: =+J13+I14 -> 459.008 | K14: =+J14*$E$4 -> 4934336
B15: 9 | C15: =+'G. Corriente'!C15 -> L | D15: =+H14 -> 8511.525 | E15: 4911.96 | F15: =+Facturas!G20+Facturas!G21 -> 4000 | G15: =+D15+F15-E15 -> 7599.565 | H15: =5793.291+1629.61 -> 7422.901 | I15: =IF(E15=0,0,+H15-G15) -> -176.664 | J15: =+J14+I15 -> 282.344 | K15: =+J15*$E$4 -> 3035198
B16: 10 | C16: =+'G. Corriente'!C16 -> M | D16: =+H15 -> 7422.901 | E16: 5231.89 | F16: =+Facturas!G22+Facturas!G23 -> 5200 | G16: =+D16+F16-E16 -> 7391.011 | H16: =5423.4+1976.789 -> 7400.189 | I16: =IF(E16=0,0,+H16-G16) -> 9.178 | J16: =+J15+I16 -> 291.522 | K16: =+J16*$E$4 -> 3133861.5
B17: 11 | C17: =+'G. Corriente'!C17 -> M | D17: =+H16 -> 7400.189 | E17: 4905.58 | F17: =+Facturas!G24+Facturas!G25 -> 6800 | G17: =+D17+F17-E17 -> 9294.609 | H17: =6368.98+2915.351 -> 9284.331 | I17: =IF(E17=0,0,+H17-G17) -> -10.278 | J17: =+J16+I17 -> 281.244 | K17: =+J17*$E$4 -> 3023373
B18: 12 | C18: =+'G. Corriente'!C18 -> J | D18: =+H17 -> 9284.331 | E18: 5109.38 | F18: =+Facturas!G26+Facturas!G27 -> 4600 | G18: =+D18+F18-E18 -> 8774.951 | H18: =5793.291+3025.937 -> 8819.228 | I18: =IF(E18=0,0,+H18-G18) -> 44.277 | J18: =+J17+I18 -> 325.521 | K18: =+J18*$E$4 -> 3499350.7
B19: 13 | C19: =+'G. Corriente'!C19 -> V | D19: =+H18 -> 8819.228 | E19: 4691.25 | F19: =+Facturas!G28+Facturas!G29 -> 4600 | G19: =+D19+F19-E19 -> 8727.978 | H19: =6212.931+2526.687 -> 8739.618 | I19: =IF(E19=0,0,+H19-G19) -> 11.64 | J19: =+J18+I19 -> 337.161 | K19: =+J19*$E$4 -> 3624480.7
B20: 14 | C20: =+'G. Corriente'!C20 -> S | D20: =+H19 -> 8739.618 | E20: 3150.09 | F20: =+Facturas!G30+Facturas!G31 -> 8000 | G20: =+D20+F20-E20 -> 13589.528 | H20: =8776.371+4739.05 -> 13515.421 | I20: =IF(E20=0,0,+H20-G20) -> -74.107 | J20: =+J19+I20 -> 263.054 | K20: =+J20*$E$4 -> 2827830.5
B21: 15 | C21: =+'G. Corriente'!C21 -> D | D21: =+H20 -> 13515.421 | E21: 1453.16 | F21: =+Facturas!G32+Facturas!G33 -> 4000 | G21: =+D21+F21-E21 -> 16062.261 | H21: =7995.71+4080.061 -> 12075.771 | I21: =IF(E21=0,0,+H21-G21) -> -3986.49 | J21: =+J20+I21 -> -3723.436 | K21: =+J21*$E$4 -> -40026937
B22: 16 | C22: =+'G. Corriente'!C22 -> L | D22: =+H21 -> 12075.771 | E22: 5991.78 | F22: =+Facturas!G34+Facturas!G35 -> 0 | G22: =+D22+F22-E22 -> 6083.991 | H22: =7032.92+3053.512 -> 10086.432 | I22: =IF(E22=0,0,+H22-G22) -> 4002.441 | J22: =+J21+I22 -> 279.005 | K22: =+J22*$E$4 -> 2999303.7
B23: 17 | C23: =+'G. Corriente'!C23 -> M | D23: =+H22 -> 10086.432 | E23: 4767.43 | F23: =+Facturas!G36+Facturas!G37 -> 7000 | G23: =+D23+F23-E23 -> 12319.002 | H23: =7379.451+1473.5 -> 8852.951 | I23: =IF(E23=0,0,+H23-G23) -> -3466.051 | J23: =+J22+I23 -> -3187.046 | K23: =+J23*$E$4 -> -34260744
B24: 18 | C24: =+'G. Corriente'!C24 -> M | D24: =+H23 -> 8852.951 | E24: 5163.7 | F24: =+Facturas!G38+Facturas!G39 -> 6800 | G24: =+D24+F24-E24 -> 10489.251 | H24: =9281.581+4787 -> 14068.581 | I24: =IF(E24=0,0,+H24-G24) -> 3579.33 | J24: =+J23+I24 -> 392.284 | K24: =+J24*$E$4 -> 4217053
B25: 19 | C25: =+'G. Corriente'!C25 -> J | D25: =+H24 -> 14068.581 | E25: 4795.83 | F25: =+Facturas!G40+Facturas!G41 -> 0 | G25: =+D25+F25-E25 -> 9272.751 | H25: =5423.4+3854.757 -> 9278.157 | I25: =IF(E25=0,0,+H25-G25) -> 5.406 | J25: =+J24+I25 -> 397.69 | K25: =+J25*$E$4 -> 4275167.5
B26: 20 | C26: =+'G. Corriente'!C26 -> V | D26: =+H25 -> 9278.157 | E26: 5219.64 | F26: =+Facturas!G42+Facturas!G43 -> 6300 | G26: =+D26+F26-E26 -> 10358.517 | H26: =6626.98+3803.535 -> 10430.515 | I26: =IF(E26=0,0,+H26-G26) -> 71.998 | J26: =+J25+I26 -> 469.688 | K26: =+J26*$E$4 -> 5049146
B27: 21 | C27: =+'G. Corriente'!C27 -> S | D27: =+H26 -> 10430.515 | E27: 2986.4 | F27: =+Facturas!G44+Facturas!G45 -> 2800 | G27: =+D27+F27-E27 -> 10244.115 | H27: =7281.371+2887.646 -> 10169.017 | I27: =IF(E27=0,0,+H27-G27) -> -75.098 | J27: =+J26+I27 -> 394.59 | K27: =+J27*$E$4 -> 4241842.5
B28: 22 | C28: =+'G. Corriente'!C28 -> D | D28: =+H27 -> 10169.017 | E28: 1422.48 | F28: =+Facturas!G46+Facturas!G47 -> 2800 | G28: =+D28+F28-E28 -> 11546.537 | H28: =9463.241+2112.907 -> 11576.148 | I28: =IF(E28=0,0,+H28-G28) -> 29.611 | J28: =+J27+I28 -> 424.201 | K28: =+J28*$E$4 -> 4560160.7
B29: 23 | C29: =+'G. Corriente'!C29 -> L | D29: =+H28 -> 11576.148 | E29: 5211.99 | F29: =+Facturas!G48+Facturas!G49 -> 2800 | G29: =+D29+F29-E29 -> 9164.158 | H29: =6212.931+2915.351 -> 9128.282 | I29: =IF(E29=0,0,+H29-G29) -> -35.876 | J29: =+J28+I29 -> 388.325 | K29: =+J29*$E$4 -> 4174493.7
B30: 24 | C30: =+'G. Corriente'!C30 -> M | D30: =+H29 -> 9128.282 | E30: 4989.73 | F30: =+Facturas!G50+Facturas!G51 -> 4600 | G30: =+D30+F30-E30 -> 8738.552 | H30: =7949.73+771.813 -> 8721.543 | I30: =IF(E30=0,0,+H30-G30) -> -17.009 | J30: =+J29+I30 -> 371.316 | K30: =+J30*$E$4 -> 3991647
B31: 25 | C31: =+'G. Corriente'!C31 -> M | D31: =+H30 -> 8721.543 | E31: 5517.01 | F31: =+Facturas!G52+Facturas!G53 -> 5800 | G31: =+D31+F31-E31 -> 9004.533 | H31: =4840.701+4272.59 -> 9113.291 | I31: =IF(E31=0,0,+H31-G31) -> 108.758 | J31: =+J30+I31 -> 480.074 | K31: =+J31*$E$4 -> 5160795.5
B32: 26 | C32: =+'G. Corriente'!C32 -> J | D32: =+H31 -> 9113.291 | E32: 4652.25 | F32: =+Facturas!G54+Facturas!G55 -> 4000 | G32: =+D32+F32-E32 -> 8461.041 | H32: =4155.88+4248.942 -> 8404.822 | I32: =IF(E32=0,0,+H32-G32) -> -56.219 | J32: =+J31+I32 -> 423.855 | K32: =+J32*$E$4 -> 4556441.2
B33: 27 | C33: =+'G. Corriente'!C33 -> V | D33: =+H32 -> 8404.822 | E33: 5105.15 | F33: =+Facturas!G56+Facturas!G57 -> 11600 | G33: =+D33+F33-E33 -> 14899.672 | H33: =5529.241+3136.036 -> 8665.277 | I33: =IF(E33=0,0,+H33-G33) -> -6234.395 | J33: =+J32+I33 -> -5810.54 | K33: =+J33*$E$4 -> -62463305
B34: 28 | C34: =+'G. Corriente'!C34 -> S | D34: =+H33 -> 8665.277 | E34: 2964.72 | F34: =+Facturas!G58+Facturas!G59 -> 2800 | G34: =+D34+F34-E34 -> 8500.557 | H34: =9886+4906 -> 14792 | I34: =IF(E34=0,0,+H34-G34) -> 6291.443 | J34: =+J33+I34 -> 480.903 | K34: =+J34*$E$4 -> 5169707.2
B35: 29 | C35: =+'G. Corriente'!C35 -> D | D35: =+H34 -> 14792 | F35: =+Facturas!G60+Facturas!G61 -> 0 | G35: =+D35+F35-E35 -> 14792 | I35: =IF(E35=0,0,+H35-G35) -> 0 | J35: =+J34+I35 -> 480.903 | K35: =+J35*$E$4 -> 5169707.2
B36: 30 | C36: =+'G. Corriente'!C36 -> L | D36: =+H35 -> 0 | F36: =+Facturas!G62+Facturas!G63 -> 0 | G36: =+D36+F36-E36 -> 0 | I36: =IF(E36=0,0,+H36-G36) -> 0 | J36: =+J35+I36 -> 480.903 | K36: =+J36*$E$4 -> 5169707.2
B37: 31 | C37: =+'G. Corriente'!C37 -> M | D37: =+H36 -> 0 | F37: =+Facturas!G64+Facturas!G65 -> 0 | G37: =+D37+F37-E37 -> 0 | I37: =IF(E37=0,0,+H37-G37) -> 0 | J37: =+J36+I37 -> 480.903 | K37: =+J37*$E$4 -> 5169707.2
E38: =SUM(E7:E37) -> 121740.33 | F38: =SUM(F7:F37) -> 123400
D39: PROM. DIA | E39: =+AVERAGEIF(E7:E37,">0",E7:E37) -> 4347.8689 | F39: =+AVERAGEIF(F7:F37,">0",F7:F37) -> 5141.6667
D40: =+'G. Corriente'!D40 -> 31 | E40: =+D40*E39 -> 134783.94 | F40: =+E40/Presupuesto!#REF! -> #REF!

Sheet G. Extra
D3: Producto | E3: Precio | F3: Fecha | G3: Precio | H3: Fecha | I3: Precio | J3: Fecha
D4: G. Extra | E4: 19770 | F4: 46023 | G4: 18070 | H4: 46060
B6: Día | D6: Inv Inicial | E6: Ventas | F6: Recibos | G6: Inv Teorico | H6: Inv Final | I6: Fluc Dia | J6: Fluc Acum | K6: Venta Total ($)
B7: 1 | C7: =+'G. Corriente'!C7 -> D | D7: 2194.99 | E7: 473.53 | F7: =+Facturas!E4+Facturas!E5 -> 0 | G7: =+D7+F7-E7 -> 1721.46 | H7: 1712.921 | I7: =IF(E7=0,0,+H7-G7) -> -8.539 | J7: =+I7 -> -8.539 | K7: =+J7*$E$4 -> -168816.03
B8: 2 | C8: =+'G. Corriente'!C8 -> L | D8: =+H7 -> 1712.921 | E8: 215.37 | F8: =+Facturas!E6+Facturas!E7 -> 0 | G8: =+D8+F8-E8 -> 1497.551 | H8: 1530 | I8: =IF(E8=0,0,+H8-G8) -> 32.449 | J8: =+I8+J7 -> 23.91 | K8: =+J8*$E$4 -> 472700.7
B9: 3 | C9: =+'G. Corriente'!C9 -> M | D9: =+H8 -> 1530 | E9: 332.29 | F9: =+Facturas!E8+Facturas!E9 -> 0 | G9: =+D9+F9-E9 -> 1197.71 | H9: 1227.75 | I9: =IF(E9=0,0,+H9-G9) -> 30.04 | J9: =+I9+J8 -> 53.95 | K9: =+J9*$E$4 -> 1066591.5
B10: 4 | C10: =+'G. Corriente'!C10 -> M | D10: =+H9 -> 1227.75 | E10: 300.41 | F10: =+Facturas!E10+Facturas!E11 -> 0 | G10: =+D10+F10-E10 -> 927.34 | H10: 844.66 | I10: =IF(E10=0,0,+H10-G10) -> -82.68 | J10: =+I10+J9 -> -28.73 | K10: =+J10*$E$4 -> -567992.1
B11: 5 | C11: =+'G. Corriente'!C11 -> J | D11: =+H10 -> 844.66 | E11: 86.21 | F11: =+Facturas!E12+Facturas!E13 -> 1800 | G11: =+D11+F11-E11 -> 2558.45 | H11: 2524.341 | I11: =IF(E11=0,0,+H11-G11) -> -34.109 | J11: =+I11+J10 -> -62.839 | K11: =+J11*$E$4 -> -1242327
B12: 6 | C12: =+'G. Corriente'!C12 -> V | D12: =+H11 -> 2524.341 | E12: 331.14 | F12: =+Facturas!E14+Facturas!E15 -> 0 | G12: =+D12+F12-E12 -> 2193.201 | H12: 2276.9 | I12: =IF(E12=0,0,+H12-G12) -> 83.699 | J12: =+I12+J11 -> 20.86 | K12: =+J12*$E$4 -> 412402.2
B13: 7 | C13: =+'G. Corriente'!C13 -> S | D13: =+H12 -> 2276.9 | E13: 658.39 | F13: =+Facturas!E16+Facturas!E17 -> 0 | G13: =+D13+F13-E13 -> 1618.51 | H13: 1608.49 | I13: =IF(E13=0,0,+H13-G13) -> -10.02 | J13: =+I13+J12 -> 10.84 | K13: =+J13*$E$4 -> 214306.8
B14: 8 | C14: =+'G. Corriente'!C14 -> D | D14: =+H13 -> 1608.49 | E14: 413.01 | F14: =+Facturas!E18+Facturas!E19 -> 0 | G14: =+D14+F14-E14 -> 1195.48 | H14: 1227.75 | I14: =IF(E14=0,0,+H14-G14) -> 32.27 | J14: =+I14+J13 -> 43.11 | K14: =+J14*$E$4 -> 852284.7
B15: 9 | C15: =+'G. Corriente'!C15 -> L | D15: =+H14 -> 1227.75 | E15: 290.11 | F15: =+Facturas!E20+Facturas!E21 -> 0 | G15: =+D15+F15-E15 -> 937.64 | H15: 961.35 | I15: =IF(E15=0,0,+H15-G15) -> 23.71 | J15: =+I15+J14 -> 66.82 | K15: =+J15*$E$4 -> 1321031.4
B16: 10 | C16: =+'G. Corriente'!C16 -> M | D16: =+H15 -> 961.35 | E16: 289.67 | F16: =+Facturas!E22+Facturas!E23 -> 1500 | G16: =+D16+F16-E16 -> 2171.68 | H16: 2113.46 | I16: =IF(E16=0,0,+H16-G16) -> -58.22 | J16: =+I16+J15 -> 8.6 | K16: =+J16*$E$4 -> 170022
B17: 11 | C17: =+'G. Corriente'!C17 -> M | D17: =+H16 -> 2113.46 | E17: 329.78 | F17: =+Facturas!E24+Facturas!E25 -> 0 | G17: =+D17+F17-E17 -> 1783.68 | H17: 1765.541 | I17: =IF(E17=0,0,+H17-G17) -> -18.139 | J17: =+I17+J16 -> -9.539 | K17: =+J17*$E$4 -> -188586.03
B18: 12 | C18: =+'G. Corriente'!C18 -> J | D18: =+H17 -> 1765.541 | E18: 303.04 | F18: =+Facturas!E26+Facturas!E27 -> 0 | G18: =+D18+F18-E18 -> 1462.501 | H18: 1505.22 | I18: =IF(E18=0,0,+H18-G18) -> 42.719 | J18: =+I18+J17 -> 33.18 | K18: =+J18*$E$4 -> 655968.6
B19: 13 | C19: =+'G. Corriente'!C19 -> V | D19: =+H18 -> 1505.22 | E19: 448.13 | F19: =+Facturas!E28+Facturas!E29 -> 0 | G19: =+D19+F19-E19 -> 1057.09 | H19: 1032.771 | I19: =IF(E19=0,0,+H19-G19) -> -24.319 | J19: =+I19+J18 -> 8.861 | K19: =+J19*$E$4 -> 175181.97
B20: 14 | C20: =+'G. Corriente'!C20 -> S | D20: =+H19 -> 1032.771 | E20: 802.91 | F20: =+Facturas!E30+Facturas!E31 -> 1800 | G20: =+D20+F20-E20 -> 2029.861 | H20: 2059.331 | I20: =IF(E20=0,0,+H20-G20) -> 29.47 | J20: =+I20+J19 -> 38.331 | K20: =+J20*$E$4 -> 757803.87
B21: 15 | C21: =+'G. Corriente'!C21 -> D | D21: =+H20 -> 2059.331 | E21: 454.83 | F21: =+Facturas!E32+Facturas!E33 -> 0 | G21: =+D21+F21-E21 -> 1604.501 | H21: 1582.57 | I21: =IF(E21=0,0,+H21-G21) -> -21.931 | J21: =+I21+J20 -> 16.4 | K21: =+J21*$E$4 -> 324228
B22: 16 | C22: =+'G. Corriente'!C22 -> L | D22: =+H21 -> 1582.57 | E22: 299.92 | F22: =+Facturas!E34+Facturas!E35 -> 0 | G22: =+D22+F22-E22 -> 1282.65 | H22: 1327.48 | I22: =IF(E22=0,0,+H22-G22) -> 44.83 | J22: =+I22+J21 -> 61.23 | K22: =+J22*$E$4 -> 1210517.1
B23: 17 | C23: =+'G. Corriente'!C23 -> M | D23: =+H22 -> 1327.48 | E23: 318.65 | F23: =+Facturas!E36+Facturas!E37 -> 1800 | G23: =+D23+F23-E23 -> 2808.83 | H23: 937.771 | I23: =IF(E23=0,0,+H23-G23) -> -1871.059 | J23: =+I23+J22 -> -1809.829 | K23: =+J23*$E$4 -> -35780319
B24: 18 | C24: =+'G. Corriente'!C24 -> M | D24: =+H23 -> 937.771 | E24: 282.54 | F24: =+Facturas!E38+Facturas!E39 -> 0 | G24: =+D24+F24-E24 -> 655.231 | H24: 2496.75 | I24: =IF(E24=0,0,+H24-G24) -> 1841.519 | J24: =+I24+J23 -> 31.69 | K24: =+J24*$E$4 -> 626511.3
B25: 19 | C25: =+'G. Corriente'!C25 -> J | D25: =+H24 -> 2496.75 | E25: 340.1 | F25: =+Facturas!E40+Facturas!E41 -> 0 | G25: =+D25+F25-E25 -> 2156.65 | H25: 2140.591 | I25: =IF(E25=0,0,+H25-G25) -> -16.059 | J25: =+I25+J24 -> 15.631 | K25: =+J25*$E$4 -> 309024.87
B26: 20 | C26: =+'G. Corriente'!C26 -> V | D26: =+H25 -> 2140.591 | E26: 452.06 | F26: =+Facturas!E42+Facturas!E43 -> 0 | G26: =+D26+F26-E26 -> 1688.531 | H26: 1765.541 | I26: =IF(E26=0,0,+H26-G26) -> 77.01 | J26: =+I26+J25 -> 92.641 | K26: =+J26*$E$4 -> 1831512.6
B27: 21 | C27: =+'G. Corriente'!C27 -> S | D27: =+H26 -> 1765.541 | E27: 754.92 | F27: =+Facturas!E44+Facturas!E45 -> 0 | G27: =+D27+F27-E27 -> 1010.621 | H27: 937.771 | I27: =IF(E27=0,0,+H27-G27) -> -72.85 | J27: =+I27+J26 -> 19.791 | K27: =+J27*$E$4 -> 391268.07
B28: 22 | C28: =+'G. Corriente'!C28 -> D | D28: =+H27 -> 937.771 | E28: 611.25 | F28: =+Facturas!E46+Facturas!E47 -> 0 | G28: =+D28+F28-E28 -> 326.521 | H28: 341.87 | I28: =IF(E28=0,0,+H28-G28) -> 15.349 | J28: =+I28+J27 -> 35.14 | K28: =+J28*$E$4 -> 694717.8
B29: 23 | C29: =+'G. Corriente'!C29 -> L | D29: =+H28 -> 341.87 | E29: 354.5 | F29: =+Facturas!E48+Facturas!E49 -> 1800 | G29: =+D29+F29-E29 -> 1787.37 | H29: 1765.541 | I29: =IF(E29=0,0,+H29-G29) -> -21.829 | J29: =+I29+J28 -> 13.311 | K29: =+J29*$E$4 -> 263158.47
B30: 24 | C30: =+'G. Corriente'!C30 -> M | D30: =+H29 -> 1765.541 | E30: 286.52 | F30: =+Facturas!E50+Facturas!E51 -> 0 | G30: =+D30+F30-E30 -> 1479.021 | H30: 1505.22 | I30: =IF(E30=0,0,+H30-G30) -> 26.199 | J30: =+I30+J29 -> 39.51 | K30: =+J30*$E$4 -> 781112.7
B31: 25 | C31: =+'G. Corriente'!C31 -> M | D31: =+H30 -> 1505.22 | E31: 338.36 | F31: =+Facturas!E52+Facturas!E53 -> 0 | G31: =+D31+F31-E31 -> 1166.86 | H31: 1129.47 | I31: =IF(E31=0,0,+H31-G31) -> -37.39 | J31: =+I31+J30 -> 2.12 | K31: =+J31*$E$4 -> 41912.4
B32: 26 | C32: =+'G. Corriente'!C32 -> J | D32: =+H31 -> 1129.47 | E32: 376.01 | F32: =+Facturas!E54+Facturas!E55 -> 1800 | G32: =+D32+F32-E32 -> 2553.46 | H32: 2551.94 | I32: =IF(E32=0,0,+H32-G32) -> -1.52 | J32: =+I32+J31 -> 0.6 | K32: =+J32*$E$4 -> 11862
B33: 27 | C33: =+'G. Corriente'!C33 -> V | D33: =+H32 -> 2551.94 | E33: 620.1 | F33: =+Facturas!E56+Facturas!E57 -> 0 | G33: =+D33+F33-E33 -> 1931.84 | H33: 1951.69 | I33: =IF(E33=0,0,+H33-G33) -> 19.85 | J33: =+I33+J32 -> 20.45 | K33: =+J33*$E$4 -> 404296.5
B34: 28 | C34: =+'G. Corriente'!C34 -> S | D34: =+H33 -> 1951.69 | E34: 892.73 | F34: =+Facturas!E58+Facturas!E59 -> 1800 | G34: =+D34+F34-E34 -> 2858.96 | H34: 2817.44 | I34: =IF(E34=0,0,+H34-G34) -> -41.52 | J34: =+I34+J33 -> -21.07 | K34: =+J34*$E$4 -> -416553.9
B35: 29 | C35: =+'G. Corriente'!C35 -> D | D35: =+H34 -> 2817.44 | F35: =+Facturas!E60+Facturas!E61 -> 0 | G35: =+D35+F35-E35 -> 2817.44 | I35: =IF(E35=0,0,+H35-G35) -> 0 | J35: =+I35+J34 -> -21.07 | K35: =+J35*$E$4 -> -416553.9
B36: 30 | C36: =+'G. Corriente'!C36 -> L | D36: =+H35 -> 0 | F36: =+Facturas!E62+Facturas!E63 -> 0 | G36: =+D36+F36-E36 -> 0 | I36: =IF(E36=0,0,+H36-G36) -> 0 | J36: =+I36+J35 -> -21.07 | K36: =+J36*$E$4 -> -416553.9
B37: 31 | C37: =+'G. Corriente'!C37 -> M | D37: =+H36 -> 0 | F37: =+Facturas!E64+Facturas!E65 -> 0 | G37: =+D37+F37-E37 -> 0 | I37: =IF(E37=0,0,+H37-G37) -> 0 | J37: =+I37+J36 -> -21.07 | K37: =+J37*$E$4 -> -416553.9
E38: =SUM(E7:E37) -> 11656.48 | F38: =SUM(F7:F37) -> 12300
D39: PROM. DIA | E39: =+AVERAGEIF(E7:E37,">0",E7:E37) -> 416.30286 | F39: =+AVERAGEIF(F7:F37,">0",F7:F37) -> 1757.1429
D40: =+'G. Corriente'!D40 -> 31 | E40: =+E39*D40 -> 12905.389 | F40: =+E40/Presupuesto!#REF! -> #REF!

Sheet Cierre
B2: Día | D2: Vta Corriente | E2: Vta Bioacem | F2: Vta Extra | G2: Vta Total | H2: Vta Gl | I2: # Clientes | J2: Efectivo | L2: Rumbo | N2: Urea Rumbo | P2: Cons Terpel | R2: Mi Emp | T2: Clien Propios | V2: App Terpel | X2: Go Pass | Z2: Datafono | AB2: QR | AD2: Ajustes | AF2: Vive Terpel | AH2: Urea | AJ2: Efectivo Real | AK2: Diferencia | AL2: Diferencia Acum | AM2: Certificacion | AN2: Diferencia | AO2: Diferencia Acum
B3: 1 | C3: =+Bioacem!C7 -> D | D3: =+'G. Corriente'!E7*'G. Corriente'!$E$4 -> 68958156 | E3: =+Bioacem!E7*Bioacem!$E$4 -> 13495980 | F3: =+'G. Extra'!E7*'G. Extra'!$E$4 -> 9361688.1 | G3: =SUM(C3:F3) -> 91815824 | H3: =+Bioacem!E7+'G. Corriente'!E7+'G. Extra'!E7 -> 6152.2 | I3: =660+500+9+15+7+11+4+1 -> 1207 | J3: =+G3-L3-P3-T3-V3-R3-X3-Z3-AB3-AD3-AF3-AH3 -> 34720329 | K3: =IF(J3=0,0,J3/G3) -> 0.37815191 | L3: =1638161-N3 -> 1560241 | M3: =IF(L3=0,0,L3/G3) -> 0.01699316 | N3: 77920 | O3: =IF(N3=0,0,N3/G3) -> 0.00084865546 | Q3: =IF(P3=0,0,P3/G3) -> 0 | R3: 2100334 | S3: =IF(R3=0,0,R3/G3) -> 0.022875512 | T3: 150156 | U3: =IF(T3=0,0,T3/G3) -> 0.0016354044 | W3: =IF(V3=0,0,V3/G3) -> 0 | X3: 237490 | Y3: =IF(X3=0,0,X3/G3) -> 0.0025865912 | Z3: =47132783+5254344 -> 52387127 | AA3: =IF(Z3=0,0,Z3/G3) -> 0.57056752 | AB3: =+'Vtas efectivo'!Z3 -> 605147 | AC3: =IF(AB3=0,0,AB3/G3) -> 0.0065908792 | AE3: =IF(AD3=0,0,AD3/G3) -> 0 | AF3: 55000 | AG3: =IF(AF3=0,0,AF3/G3) -> 0.00059902528 | AH3: =+'Vtas efectivo'!BK3 -> 0 | AI3: =IF(AH3=0,0,AH3/G3) -> 0 | AJ3: 35091000 | AK3: =+J3-AJ3 -> -370671.2 | AL3: =+AK3 -> -370671.2 | AN3: =+AM3-AJ3 -> -35091000 | AO3: =+AN3 -> -35091000
B4: 2 | C4: =+Bioacem!C8 -> L | D4: =+'G. Corriente'!E8*'G. Corriente'!$E$4 -> 43289532 | E4: =+Bioacem!E8*Bioacem!$E$4 -> 56912328 | F4: =+'G. Extra'!E8*'G. Extra'!$E$4 -> 4257864.9 | G4: =SUM(C4:F4) -> 1.0445972e+08 | H4: =+Bioacem!E8+'G. Corriente'!E8+'G. Extra'!E8 -> 8286.29 | I4: =634+429+34+54+40+15+17+2 -> 1225 | J4: =+G4-L4-P4-T4-V4-R4-X4-Z4-AB4-AD4-AF4-AH4 -> 35522187 | K4: =IF(J4=0,0,J4/G4) -> 0.34005629 | L4: =13927767-N4 -> 13845723 | M4: =IF(L4=0,0,L4/G4) -> 0.13254604 | N4: 82044 | O4: =IF(N4=0,0,N4/G4) -> 0.00078541275 | Q4: =IF(P4=0,0,P4/G4) -> 0 | R4: 7037635 | S4: =IF(R4=0,0,R4/G4) -> 0.067371755 | T4: =5365535+'Vtas efectivo'!BJ4 -> 8200671 | U4: =IF(T4=0,0,T4/G4) -> 0.078505577 | W4: =IF(V4=0,0,V4/G4) -> 0 | X4: 237037 | Y4: =IF(X4=0,0,X4/G4) -> 0.0022691712 | Z4: =37532239-253005 -> 37279234 | AA4: =IF(Z4=0,0,Z4/G4) -> 0.35687662 | AB4: =+'Vtas efectivo'!Z4 -> 2060238 | AC4: =IF(AB4=0,0,AB4/G4) -> 0.019722797 | AE4: =IF(AD4=0,0,AD4/G4) -> 0 | AF4: 277000 | AG4: =IF(AF4=0,0,AF4/G4) -> 0.0026517397 | AH4: =+'Vtas efectivo'!BK4 -> 0 | AI4: =IF(AH4=0,0,AH4/G4) -> 0 | AJ4: 35557000 | AK4: =+J4-AJ4 -> -34813.1 | AL4: =+AL3+AK4 -> -405484.3 | AN4: =+AM4-AJ4 -> -35557000 | AO4: =+AO3+AN4 -> -70648000
B5: 3 | C5: =+Bioacem!C9 -> M | D5: =+'G. Corriente'!E9*'G. Corriente'!$E$4 -> 43791530 | E5: =+Bioacem!E9*Bioacem!$E$4 -> 56862340 | F5: =+'G. Extra'!E9*'G. Extra'!$E$4 -> 6569373.3 | G5: =SUM(C5:F5) -> 1.0722324e+08 | H5: =+Bioacem!E9+'G. Corriente'!E9+'G. Extra'!E9 -> 8430.76 | I5: =690+401+41+62+27+11+9+14+1 -> 1256 | J5: =+G5-L5-P5-T5-V5-R5-X5-Z5-AB5-AD5-AF5-AH5 -> 37613323 | K5: =IF(J5=0,0,J5/G5) -> 0.35079449 | L5: =15346584-N5 -> 15020193 | M5: =IF(L5=0,0,L5/G5) -> 0.14008337 | N5: 326391 | O5: =IF(N5=0,0,N5/G5) -> 0.0030440321 | Q5: =IF(P5=0,0,P5/G5) -> 0 | R5: 6745965 | S5: =IF(R5=0,0,R5/G5) -> 0.062915136 | T5: =4511303+'Vtas efectivo'!BJ5 -> 6214052 | U5: =IF(T5=0,0,T5/G5) -> 0.057954337 | V5: 49128 | W5: =IF(V5=0,0,V5/G5) -> 0.00045818424 | X5: 1330663 | Y5: =IF(X5=0,0,X5/G5) -> 0.01241021 | Z5: =34703935+4281199 -> 38985134 | AA5: =IF(Z5=0,0,Z5/G5) -> 0.36358846 | AB5: =+'Vtas efectivo'!Z5 -> 1100786 | AC5: =IF(AB5=0,0,AB5/G5) -> 0.0102663 | AE5: =IF(AD5=0,0,AD5/G5) -> 0 | AF5: 164000 | AG5: =IF(AF5=0,0,AF5/G5) -> 0.0015295191 | AH5: =+'Vtas efectivo'!BK5 -> 0 | AI5: =IF(AH5=0,0,AH5/G5) -> 0 | AJ5: 37496000 | AK5: =+J5-AJ5 -> 117322.8 | AL5: =+AL4+AK5 -> -288161.5 | AN5: =+AM5-AJ5 -> -37496000 | AO5: =+AO4+AN5 -> -108144000
B6: 4 | C6: =+Bioacem!C10 -> M | D6: =+'G. Corriente'!E10*'G. Corriente'!$E$4 -> 44562144 | E6: =+Bioacem!E10*Bioacem!$E$4 -> 60013487 | F6: =+'G. Extra'!E10*'G. Extra'!$E$4 -> 5939105.7 | G6: =SUM(C6:F6) -> 1.1051474e+08 | H6: =+Bioacem!E10+'G. Corriente'!E10+'G. Extra'!E10 -> 8741.44 | I6: =666+390+34+61+30+15+12+5 -> 1213 | J6: =+G6-L6-P6-T6-V6-R6-X6-Z6-AB6-AD6-AF6-AH6 -> 39396453 | K6: =IF(J6=0,0,J6/G6) -> 0.35648145 | L6: =14277999-N6 -> 14208699 | M6: =IF(L6=0,0,L6/G6) -> 0.12856836 | N6: 69300 | O6: =IF(N6=0,0,N6/G6) -> 0.00062706569 | Q6: =IF(P6=0,0,P6/G6) -> 0 | R6: 5495035 | S6: =IF(R6=0,0,R6/G6) -> 0.049722192 | T6: =6148176+'Vtas efectivo'!BJ6 -> 6438662 | U6: =IF(T6=0,0,T6/G6) -> 0.058260664 | W6: =IF(V6=0,0,V6/G6) -> 0 | X6: 709302 | Y6: =IF(X6=0,0,X6/G6) -> 0.0064181666 | Z6: =40476235+2797189 -> 43273424 | AA6: =IF(Z6=0,0,Z6/G6) -> 0.39156247 | AB6: =+'Vtas efectivo'!Z6 -> 606162 | AC6: =IF(AB6=0,0,AB6/G6) -> 0.0054848974 | AE6: =IF(AD6=0,0,AD6/G6) -> 0 | AF6: 387000 | AG6: =IF(AF6=0,0,AF6/G6) -> 0.0035017954 | AH6: =+'Vtas efectivo'!BK6 -> 0 | AI6: =IF(AH6=0,0,AH6/G6) -> 0 | AJ6: 39207000 | AK6: =+J6-AJ6 -> 189453.4 | AL6: =+AL5+AK6 -> -98708.1 | AN6: =+AM6-AJ6 -> -39207000 | AO6: =+AO5+AN6 -> -147351000
B7: 5 | C7: =+Bioacem!C11 -> J | D7: =+'G. Corriente'!E11*'G. Corriente'!$G$4 -> 21203873 | E7: =+Bioacem!E11*Bioacem!$E$4 -> 60859620 | F7: =+'G. Extra'!E11*'G. Extra'!$E$4 -> 1704371.7 | G7: =SUM(C7:F7) -> 83767865 | H7: =+Bioacem!E11+'G. Corriente'!E11+'G. Extra'!E11 -> 7143.48 | I7: =416+182+22+58+44+5+3+4 -> 734 | J7: =+G7-L7-P7-T7-V7-R7-X7-Z7-AB7-AD7-AF7-AH7 -> 27053983 | K7: =IF(J7=0,0,J7/G7) -> 0.32296374 | L7: =12917658-N7 -> 12561260 | M7: =IF(L7=0,0,L7/G7) -> 0.14995321 | N7: 356398 | O7: =IF(N7=0,0,N7/G7) -> 0.004254591 | Q7: =IF(P7=0,0,P7/G7) -> 0 | R7: 9265958 | S7: =IF(R7=0,0,R7/G7) -> 0.11061471 | T7: =3947788+'Vtas efectivo'!BJ7 -> 5134058 | U7: =IF(T7=0,0,T7/G7) -> 0.061289112 | W7: =IF(V7=0,0,V7/G7) -> 0 | X7: 567228 | Y7: =IF(X7=0,0,X7/G7) -> 0.0067714272 | Z7: =26265813+2317230 -> 28583043 | AA7: =IF(Z7=0,0,Z7/G7) -> 0.34121728 | AB7: =+'Vtas efectivo'!Z7 -> 519335 | AC7: =IF(AB7=0,0,AB7/G7) -> 0.0061996925 | AE7: =IF(AD7=0,0,AD7/G7) -> 0 | AF7: 83000 | AG7: =IF(AF7=0,0,AF7/G7) -> 0.00099083342 | AH7: =+'Vtas efectivo'!BK7 -> 0 | AI7: =IF(AH7=0,0,AH7/G7) -> 0 | AJ7: 26692000 | AK7: =+J7-AJ7 -> 361982.6 | AL7: =+AL6+AK7 -> 263274.5 | AM7: 113099000 | AN7: =+AM7-AJ7 -> 86407000 | AO7: =+AO6+AN7 -> -60944000
B8: 6 | C8: =+Bioacem!C12 -> V | D8: =+'G. Corriente'!E12*'G. Corriente'!$G$4 -> 58436082 | E8: =+Bioacem!E12*Bioacem!$E$4 -> 47770635 | F8: =+'G. Extra'!E12*'G. Extra'!$E$4 -> 6546637.8 | G8: =SUM(C8:F8) -> 1.1275335e+08 | H8: =+Bioacem!E12+'G. Corriente'!E12+'G. Extra'!E12 -> 8621.93 | I8: =824+440+40+29+35+11+53+5 -> 1437 | J8: =+G8-L8-P8-T8-V8-R8-X8-Z8-AB8-AD8-AF8-AH8 -> 38929003 | K8: =IF(J8=0,0,J8/G8) -> 0.34525804 | L8: =9945579-N8 -> 9822371 | M8: =IF(L8=0,0,L8/G8) -> 0.087113781 | N8: 123208 | O8: =IF(N8=0,0,N8/G8) -> 0.0010927214 | Q8: =IF(P8=0,0,P8/G8) -> 0 | R8: 7748215 | S8: =IF(R8=0,0,R8/G8) -> 0.068718266 | T8: =3763063+'Vtas efectivo'!BJ8 -> 5705014 | U8: =IF(T8=0,0,T8/G8) -> 0.050597288 | W8: =IF(V8=0,0,V8/G8) -> 0 | X8: 590211 | Y8: =IF(X8=0,0,X8/G8) -> 0.0052345316 | Z8: =40894071+6636380 -> 47530451 | AA8: =IF(Z8=0,0,Z8/G8) -> 0.42154356 | AB8: =+'Vtas efectivo'!Z8 -> 2088640 | AC8: =IF(AB8=0,0,AB8/G8) -> 0.018523972 | AE8: =IF(AD8=0,0,AD8/G8) -> 0 | AF8: 197000 | AG8: =IF(AF8=0,0,AF8/G8) -> 0.0017471764 | AH8: =+'Vtas efectivo'!BK8 -> 142450 | AI8: =IF(AH8=0,0,AH8/G8) -> 0.001263377 | AJ8: 38799000 | AK8: =+J8-AJ8 -> 130002.7 | AL8: =+AL7+AK8 -> 393277.2 | AM8: 26740000 | AN8: =+AM8-AJ8 -> -12059000 | AO8: =+AO7+AN8 -> -73003000
B9: 7 | C9: =+Bioacem!C13 -> S | D9: =+'G. Corriente'!E13*'G. Corriente'!$G$4 -> 73306180 | E9: =+Bioacem!E13*Bioacem!$E$4 -> 45138820 | F9: =+'G. Extra'!E13*'G. Extra'!$G$4 -> 11897107 | G9: =SUM(C9:F9) -> 1.3034211e+08 | H9: =+Bioacem!E13+'G. Corriente'!E13+'G. Extra'!E13 -> 9683.3 | I9: =755+618+24+33+7+15+14+5+2 -> 1473 | J9: =+G9-L9-P9-T9-V9-R9-X9-Z9-AB9-AD9-AF9-AH9 -> 44718814 | K9: =IF(J9=0,0,J9/G9) -> 0.34308801 | L9: =10384172-N9 -> 10326722 | M9: =IF(L9=0,0,L9/G9) -> 0.079227827 | N9: 57450 | O9: =IF(N9=0,0,N9/G9) -> 0.00044076317 | Q9: =IF(P9=0,0,P9/G9) -> 0 | R9: 3999655 | S9: =IF(R9=0,0,R9/G9) -> 0.030685824 | T9: =1270408+'Vtas efectivo'!BJ9 -> 2736310 | U9: =IF(T9=0,0,T9/G9) -> 0.020993293 | V9: 343754 | W9: =IF(V9=0,0,V9/G9) -> 0.0026373212 | X9: 818085 | Y9: =IF(X9=0,0,X9/G9) -> 0.0062764445 | Z9: =64565637+839652 -> 65405289 | AA9: =IF(Z9=0,0,Z9/G9) -> 0.50179708 | AB9: =+'Vtas efectivo'!Z9 -> 1729379 | AC9: =IF(AB9=0,0,AB9/G9) -> 0.013267999 | AE9: =IF(AD9=0,0,AD9/G9) -> 0 | AF9: 241000 | AG9: =IF(AF9=0,0,AF9/G9) -> 0.0018489804 | AH9: =+'Vtas efectivo'!BK9 -> 23100 | AI9: =IF(AH9=0,0,AH9/G9) -> 0.00017722592 | AJ9: 44699000 | AK9: =+J9-AJ9 -> 19813.8 | AL9: =+AL8+AK9 -> 413091 | AN9: =+AM9-AJ9 -> -44699000 | AO9: =+AO8+AN9 -> -117702000
B10: 8 | C10: =+Bioacem!C14 -> D | D10: =+'G. Corriente'!E14*'G. Corriente'!$G$4 -> 67194940 | E10: =+Bioacem!E14*Bioacem!$E$4 -> 19060072 | F10: =+'G. Extra'!E14*'G. Extra'!$G$4 -> 7463090.7 | G10: =SUM(C10:F10) -> 93718103 | H10: =+Bioacem!E14+'G. Corriente'!E14+'G. Extra'!E14 -> 6609.67 | I10: =686+509+22+14+4+10+2+1 -> 1248 | J10: =+G10-L10-P10-T10-V10-R10-X10-Z10-AB10-AD10-AF10-AH10 -> 35956841 | K10: =IF(J10=0,0,J10/G10) -> 0.38367017 | L10: =4665267-N10 -> 4487389 | M10: =IF(L10=0,0,L10/G10) -> 0.047881774 | N10: 177878 | O10: =IF(N10=0,0,N10/G10) -> 0.0018980111 | Q10: =IF(P10=0,0,P10/G10) -> 0 | R10: 730732 | S10: =IF(R10=0,0,R10/G10) -> 0.0077971275 | T10: =590831+'Vtas efectivo'!BJ10 -> 671241 | U10: =IF(T10=0,0,T10/G10) -> 0.0071623409 | V10: 57008 | W10: =IF(V10=0,0,V10/G10) -> 0.0006082923 | Y10: =IF(X10=0,0,X10/G10) -> 0 | Z10: =45805743+4407877 -> 50213620 | AA10: =IF(Z10=0,0,Z10/G10) -> 0.53579424 | AB10: =+'Vtas efectivo'!Z10 -> 1278272 | AC10: =IF(AB10=0,0,AB10/G10) -> 0.013639542 | AE10: =IF(AD10=0,0,AD10/G10) -> 0 | AF10: 323000 | AG10: =IF(AF10=0,0,AF10/G10) -> 0.003446506 | AH10: =+'Vtas efectivo'!BK10 -> 0 | AI10: =IF(AH10=0,0,AH10/G10) -> 0 | AJ10: 35656000 | AK10: =+J10-AJ10 -> 300840.9 | AL10: =+AL9+AK10 -> 713931.9 | AN10: =+AM10-AJ10 -> -35656000 | AO10: =+AO9+AN10 -> -153358000
B11: 9 | C11: =+Bioacem!C15 -> L | D11: =+'G. Corriente'!E15*'G. Corriente'!$G$4 -> 48895547 | E11: =+Bioacem!E15*Bioacem!$E$4 -> 52803570 | F11: =+'G. Extra'!E15*'G. Extra'!$G$4 -> 5242287.7 | G11: =SUM(C11:F11) -> 1.069414e+08 | H11: =+Bioacem!E15+'G. Corriente'!E15+'G. Extra'!E15 -> 8421 | I11: =701+442+41+62+21+24+12+2 -> 1305 | J11: =+G11-L11-P11-T11-V11-R11-X11-Z11-AB11-AD11-AF11-AH11 -> 39042894 | K11: =IF(J11=0,0,J11/G11) -> 0.36508679 | L11: =10668976-N11 -> 10520959 | M11: =IF(L11=0,0,L11/G11) -> 0.098380595 | N11: 148017 | O11: =IF(N11=0,0,N11/G11) -> 0.0013840944 | Q11: =IF(P11=0,0,P11/G11) -> 0 | R11: 8099551 | S11: =IF(R11=0,0,R11/G11) -> 0.075738214 | T11: =4854763+'Vtas efectivo'!BJ11 -> 6298874 | U11: =IF(T11=0,0,T11/G11) -> 0.058900236 | W11: =IF(V11=0,0,V11/G11) -> 0 | X11: 378443 | Y11: =IF(X11=0,0,X11/G11) -> 0.0035387884 | Z11: =39165663+1133769 -> 40299432 | AA11: =IF(Z11=0,0,Z11/G11) -> 0.37683657 | AB11: =+'Vtas efectivo'!Z11 -> 2061251 | AC11: =IF(AB11=0,0,AB11/G11) -> 0.019274583 | AE11: =IF(AD11=0,0,AD11/G11) -> 0 | AF11: 240000 | AG11: =IF(AF11=0,0,AF11/G11) -> 0.0022442196 | AH11: =+'Vtas efectivo'!BK11 -> 0 | AI11: =IF(AH11=0,0,AH11/G11) -> 0 | AJ11: 39116000 | AK11: =+J11-AJ11 -> -73105.6 | AL11: =+AL10+AK11 -> 640826.3 | AM11: 126512000 | AN11: =+AM11-AJ11 -> 87396000 | AO11: =+AO10+AN11 -> -65962000
B12: 10 | C12: =+Bioacem!C16 -> M | D12: =+'G. Corriente'!E16*'G. Corriente'!$G$4 -> 48712052 | E12: =+Bioacem!E16*Bioacem!$E$4 -> 56242818 | F12: =+'G. Extra'!E16*'G. Extra'!$G$4 -> 5234336.9 | G12: =SUM(C12:F12) -> 1.1018921e+08 | H12: =+Bioacem!E16+'G. Corriente'!E16+'G. Extra'!E16 -> 8728.41 | I12: =665+477+44+32+15+11+55+1+6+1 -> 1307 | J12: =+G12-L12-P12-T12-V12-R12-X12-Z12-AB12-AD12-AF12-AH12 -> 38308780 | K12: =IF(J12=0,0,J12/G12) -> 0.34766364 | L12: =13625822-N12 -> 13333222 | M12: =IF(L12=0,0,L12/G12) -> 0.12100298 | N12: =254100+38500 -> 292600 | O12: =IF(N12=0,0,N12/G12) -> 0.0026554325 | Q12: =IF(P12=0,0,P12/G12) -> 0 | R12: 8789210 | S12: =IF(R12=0,0,R12/G12) -> 0.07976471 | T12: =4960063+'Vtas efectivo'!BJ12 -> 6522444 | U12: =IF(T12=0,0,T12/G12) -> 0.05919313 | V12: 50000 | W12: =IF(V12=0,0,V12/G12) -> 0.00045376495 | X12: 724261 | Y12: =IF(X12=0,0,X12/G12) -> 0.0065728852 | Z12: =40057432+333128 -> 40390560 | AA12: =IF(Z12=0,0,Z12/G12) -> 0.36655641 | AB12: =+'Vtas efectivo'!Z12 -> 1618779 | AC12: =IF(AB12=0,0,AB12/G12) -> 0.014690904 | AE12: =IF(AD12=0,0,AD12/G12) -> 0 | AF12: 271000 | AG12: =IF(AF12=0,0,AF12/G12) -> 0.0024594061 | AH12: =+'Vtas efectivo'!BK12 -> 180950 | AI12: =IF(AH12=0,0,AH12/G12) -> 0.0016421754 | AJ12: 38316000 | AK12: =+J12-AJ12 -> -7220.1 | AL12: =+AL11+AK12 -> 633606.2 | AN12: =+AM12-AJ12 -> -38316000 | AO12: =+AO11+AN12 -> -104278000
B13: 11 | C13: =+Bioacem!C17 -> M | D13: =+'G. Corriente'!E17*'G. Corriente'!$G$4 -> 50413939 | E13: =+Bioacem!E17*Bioacem!$E$4 -> 52734985 | F13: =+'G. Extra'!E17*'G. Extra'!$G$4 -> 5959124.6 | G13: =SUM(C13:F13) -> 1.0910805e+08 | H13: =+Bioacem!E17+'G. Corriente'!E17+'G. Extra'!E17 -> 8554.25 | I13: =761+424+32+48+27+17+5+19 -> 1333 | J13: =+G13-L13-P13-T13-V13-R13-X13-Z13-AB13-AD13-AF13-AH13 -> 41793115 | K13: =IF(J13=0,0,J13/G13) -> 0.38304337 | L13: =10737100-N13 -> 10737100 | M13: =IF(L13=0,0,L13/G13) -> 0.098407955 | O13: =IF(N13=0,0,N13/G13) -> 0 | Q13: =IF(P13=0,0,P13/G13) -> 0 | R13: 6780813 | S13: =IF(R13=0,0,R13/G13) -> 0.062147688 | T13: =4744288+'Vtas efectivo'!BJ13 -> 5913315 | U13: =IF(T13=0,0,T13/G13) -> 0.054196872 | W13: =IF(V13=0,0,V13/G13) -> 0 | X13: 639079 | Y13: =IF(X13=0,0,X13/G13) -> 0.0058573039 | Z13: =40281428+1675239 -> 41956667 | AA13: =IF(Z13=0,0,Z13/G13) -> 0.38454236 | AB13: =+'Vtas efectivo'!Z13 -> 1074960 | AC13: =IF(AB13=0,0,AB13/G13) -> 0.0098522521 | AE13: =IF(AD13=0,0,AD13/G13) -> 0 | AF13: 213000 | AG13: =IF(AF13=0,0,AF13/G13) -> 0.0019521933 | AH13: =+'Vtas efectivo'!BK13 -> 0 | AI13: =IF(AH13=0,0,AH13/G13) -> 0 | AJ13: 41696000 | AK13: =+J13-AJ13 -> 97114.7 | AL13: =+AL12+AK13 -> 730720.9 | AN13: =+AM13-AJ13 -> -41696000 | AO13: =+AO12+AN13 -> -145974000
B14: 12 | C14: =+Bioacem!C18 -> J | D14: =+'G. Corriente'!E18*'G. Corriente'!$G$4 -> 49553274 | E14: =+Bioacem!E18*Bioacem!$E$4 -> 54925835 | F14: =+'G. Extra'!E18*'G. Extra'!$G$4 -> 5475932.8 | G14: =SUM(C14:F14) -> 1.0995504e+08 | H14: =+Bioacem!E18+'G. Corriente'!E18+'G. Extra'!E18 -> 8674.65 | I14: =747+452+40+19+22+26+53+3+1 -> 1363 | J14: =+G14-L14-P14-T14-V14-R14-X14-Z14-AB14-AD14-AF14-AH14 -> 44030848 | K14: =IF(J14=0,0,J14/G14) -> 0.4004441 | L14: =16226184-N14 -> 16048391 | M14: =IF(L14=0,0,L14/G14) -> 0.14595412 | N14: 177793 | O14: =IF(N14=0,0,N14/G14) -> 0.0016169609 | Q14: =IF(P14=0,0,P14/G14) -> 0 | R14: 5490777 | S14: =IF(R14=0,0,R14/G14) -> 0.049936564 | T14: =4482331+'Vtas efectivo'!BJ14 -> 5143479 | U14: =IF(T14=0,0,T14/G14) -> 0.046778019 | V14: 30380 | W14: =IF(V14=0,0,V14/G14) -> 0.00027629474 | X14: 418636 | Y14: =IF(X14=0,0,X14/G14) -> 0.0038073379 | Z14: =38828801-1744507 -> 37084294 | AA14: =IF(Z14=0,0,Z14/G14) -> 0.33726779 | AB14: =+'Vtas efectivo'!Z14 -> 1276237 | AC14: =IF(AB14=0,0,AB14/G14) -> 0.011606898 | AE14: =IF(AD14=0,0,AD14/G14) -> 0 | AF14: 432000 | AG14: =IF(AF14=0,0,AF14/G14) -> 0.0039288785 | AH14: =+'Vtas efectivo'!BK14 -> 0 | AI14: =IF(AH14=0,0,AH14/G14) -> 0 | AJ14: 43608000 | AK14: =+J14-AJ14 -> 422847.5 | AL14: =+AL13+AK14 -> 1153568.4 | AM14: 114715000 | AN14: =+AM14-AJ14 -> 71107000 | AO14: =+AO13+AN14 -> -74867000
B15: 13 | C15: =+Bioacem!C19 -> V | D15: =+'G. Corriente'!E19*'G. Corriente'!$G$4 -> 55689122 | E15: =+Bioacem!E19*Bioacem!$E$4 -> 50430938 | F15: =+'G. Extra'!E19*'G. Extra'!$G$4 -> 8097709.1 | G15: =SUM(C15:F15) -> 1.1421777e+08 | H15: =+Bioacem!E19+'G. Corriente'!E19+'G. Extra'!E19 -> 8805.55 | I15: =716+460+30+56+38+14+6+4 -> 1324 | J15: =+G15-L15-P15-T15-V15-R15-X15-Z15-AB15-AD15-AF15-AH15 -> 36925128 | K15: =IF(J15=0,0,J15/G15) -> 0.32328707 | L15: =14060713-N15 -> 13607841 | M15: =IF(L15=0,0,L15/G15) -> 0.11913944 | N15: 452872 | O15: =IF(N15=0,0,N15/G15) -> 0.0039649873 | Q15: =IF(P15=0,0,P15/G15) -> 0 | R15: 6293578 | S15: =IF(R15=0,0,R15/G15) -> 0.055101567 | T15: =6619940+'Vtas efectivo'!BJ15 -> 7901832 | U15: =IF(T15=0,0,T15/G15) -> 0.06918216 | W15: =IF(V15=0,0,V15/G15) -> 0 | X15: 1007629 | Y15: =IF(X15=0,0,X15/G15) -> 0.0088219986 | Z15: =43735330+3567100 -> 47302430 | AA15: =IF(Z15=0,0,Z15/G15) -> 0.41414248 | AB15: =+'Vtas efectivo'!Z15 -> 957331 | AC15: =IF(AB15=0,0,AB15/G15) -> 0.0083816293 | AE15: =IF(AD15=0,0,AD15/G15) -> 0 | AF15: 222000 | AG15: =IF(AF15=0,0,AF15/G15) -> 0.0019436555 | AH15: =+'Vtas efectivo'!BK15 -> 0 | AI15: =IF(AH15=0,0,AH15/G15) -> 0 | AJ15: 36864000 | AK15: =+J15-AJ15 -> 61127.9 | AL15: =+AL14+AK15 -> 1214696.3 | AM15: 38467000 | AN15: =+AM15-AJ15 -> 1603000 | AO15: =+AO14+AN15 -> -73264000
B16: 14 | C16: =+Bioacem!C20 -> S | D16: =+'G. Corriente'!E20*'G. Corriente'!$G$4 -> 87478906 | E16: =+Bioacem!E20*Bioacem!$E$4 -> 33863468 | F16: =+'G. Extra'!E20*'G. Extra'!$G$4 -> 14508584 | G16: =SUM(C16:F16) -> 1.3585096e+08 | H16: =+Bioacem!E20+'G. Corriente'!E20+'G. Extra'!E20 -> 9711.98 | I16: =810+780+35+17+5+14+8+10 -> 1679 | J16: =+G16-L16-P16-T16-V16-R16-X16-Z16-AB16-AD16-AF16-AH16 -> 43294512 | K16: =IF(J16=0,0,J16/G16) -> 0.31869126 | L16: =11146543-N16 -> 11061843 | M16: =IF(L16=0,0,L16/G16) -> 0.081426316 | N16: 84700 | O16: =IF(N16=0,0,N16/G16) -> 0.00062347739 | Q16: =IF(P16=0,0,P16/G16) -> 0 | R16: 3571815 | S16: =IF(R16=0,0,R16/G16) -> 0.026292159 | T16: =1165343+'Vtas efectivo'!BJ16 -> 1800001 | U16: =IF(T16=0,0,T16/G16) -> 0.013249822 | W16: =IF(V16=0,0,V16/G16) -> 0 | X16: 721426 | Y16: =IF(X16=0,0,X16/G16) -> 0.0053104226 | Z16: =72644960+1228876 -> 73873836 | AA16: =IF(Z16=0,0,Z16/G16) -> 0.54378591 | AB16: =+'Vtas efectivo'!Z16 -> 1378524 | AC16: =IF(AB16=0,0,AB16/G16) -> 0.010147326 | AE16: =IF(AD16=0,0,AD16/G16) -> 0 | AF16: 149000 | AG16: =IF(AF16=0,0,AF16/G16) -> 0.0010967902 | AH16: =+'Vtas efectivo'!BK16 -> 0 | AI16: =IF(AH16=0,0,AH16/G16) -> 0 | AJ16: 42839000 | AK16: =+J16-AJ16 -> 455512.4 | AL16: =+AL15+AK16 -> 1670208.7 | AN16: =+AM16-AJ16 -> -42839000 | AO16: =+AO15+AN16 -> -116103000
B17: 15 | C17: =+Bioacem!C21 -> D | D17: =+'G. Corriente'!E21*'G. Corriente'!$G$4 -> 72727745 | E17: =+Bioacem!E21*Bioacem!$E$4 -> 15621470 | F17: =+'G. Extra'!E21*'G. Extra'!$G$4 -> 8218778.1 | G17: =SUM(C17:F17) -> 96567993 | H17: =+Bioacem!E21+'G. Corriente'!E21+'G. Extra'!E21 -> 6695.86 | I17: =708+550+19+10+8+14+1+1+1 -> 1312 | J17: =+G17-L17-P17-T17-V17-R17-X17-Z17-AB17-AD17-AF17-AH17 -> 39367127 | K17: =IF(J17=0,0,J17/G17) -> 0.40766227 | L17: 2499572 | M17: =IF(L17=0,0,L17/G17) -> 0.025884063 | O17: =IF(N17=0,0,N17/G17) -> 0 | Q17: =IF(P17=0,0,P17/G17) -> 0 | R17: 1431561 | S17: =IF(R17=0,0,R17/G17) -> 0.014824384 | T17: =1101284+'Vtas efectivo'!BJ17 -> 1355253 | U17: =IF(T17=0,0,T17/G17) -> 0.014034184 | V17: 53614 | W17: =IF(V17=0,0,V17/G17) -> 0.00055519431 | X17: 156396 | Y17: =IF(X17=0,0,X17/G17) -> 0.0016195428 | Z17: =49088860+1548153 -> 50637013 | AA17: =IF(Z17=0,0,Z17/G17) -> 0.52436642 | AB17: =+'Vtas efectivo'!Z17 -> 604457 | AC17: =IF(AB17=0,0,AB17/G17) -> 0.0062593928 | AE17: =IF(AD17=0,0,AD17/G17) -> 0 | AF17: 463000 | AG17: =IF(AF17=0,0,AF17/G17) -> 0.0047945492 | AH17: =+'Vtas efectivo'!BK17 -> 0 | AI17: =IF(AH17=0,0,AH17/G17) -> 0 | AJ17: 39299000 | AK17: =+J17-AJ17 -> 68127.4 | AL17: =+AL16+AK17 -> 1738336.1 | AN17: =+AM17-AJ17 -> -39299000 | AO17: =+AO16+AN17 -> -155402000
B18: 16 | C18: =+Bioacem!C22 -> L | D18: =+'G. Corriente'!E22*'G. Corriente'!$G$4 -> 47347838 | E18: =+Bioacem!E22*Bioacem!$E$4 -> 64411635 | F18: =+'G. Extra'!E22*'G. Extra'!$G$4 -> 5419554.4 | G18: =SUM(C18:F18) -> 117179027 | H18: =+Bioacem!E22+'G. Corriente'!E22+'G. Extra'!E22 -> 9408.74 | I18: =753+450+62+41+29+12+8+1+4 -> 1360 | J18: =+G18-L18-P18-T18-V18-R18-X18-Z18-AB18-AD18-AF18-AH18 -> 40884134 | K18: =IF(J18=0,0,J18/G18) -> 0.34890317 | L18: =18563517-N18+29950 -> 18471507 | M18: =IF(L18=0,0,L18/G18) -> 0.15763492 | N18: 121960 | O18: =IF(N18=0,0,N18/G18) -> 0.0010408006 | Q18: =IF(P18=0,0,P18/G18) -> 0 | R18: 7896585 | S18: =IF(R18=0,0,R18/G18) -> 0.067389064 | T18: =4910782+'Vtas efectivo'!BJ18 -> 6289095 | U18: =IF(T18=0,0,T18/G18) -> 0.053670825 | V18: 125667 | W18: =IF(V18=0,0,V18/G18) -> 0.0010724359 | X18: 622758 | Y18: =IF(X18=0,0,X18/G18) -> 0.0053145859 | Z18: =39298646+2239802 -> 41538448 | AA18: =IF(Z18=0,0,Z18/G18) -> 0.35448705 | AB18: =+'Vtas efectivo'!Z18 -> 1234833 | AC18: =IF(AB18=0,0,AB18/G18) -> 0.010538004 | AE18: =IF(AD18=0,0,AD18/G18) -> 0 | AF18: 116000 | AG18: =IF(AF18=0,0,AF18/G18) -> 0.00098993824 | AH18: =+'Vtas efectivo'!BK18 -> 0 | AI18: =IF(AH18=0,0,AH18/G18) -> 0 | AJ18: 40869000 | AK18: =+J18-AJ18 -> 15134 | AL18: =+AL17+AK18 -> 1753470.1 | AM18: 124978000 | AN18: =+AM18-AJ18 -> 84109000 | AO18: =+AO17+AN18 -> -71293000
B19: 17 | C19: =+Bioacem!C23 -> M | D19: =+'G. Corriente'!E23*'G. Corriente'!$G$4 -> 53135683 | E19: =+Bioacem!E23*Bioacem!$E$4 -> 51249872 | F19: =+'G. Extra'!E23*'G. Extra'!$G$4 -> 5758005.5 | G19: =SUM(C19:F19) -> 1.1014356e+08 | H19: =+Bioacem!E23+'G. Corriente'!E23+'G. Extra'!E23 -> 8584.15 | I19: =772+49+478+58+16+32+14+2+2 -> 1423 | J19: =+G19-L19-P19-T19-V19-R19-X19-Z19-AB19-AD19-AF19-AH19 -> 41584171 | K19: =IF(J19=0,0,J19/G19) -> 0.37754519 | L19: =10704802-N19 -> 10481252 | M19: =IF(L19=0,0,L19/G19) -> 0.095159916 | N19: 223550 | O19: =IF(N19=0,0,N19/G19) -> 0.0020296239 | Q19: =IF(P19=0,0,P19/G19) -> 0 | R19: 8078185 | S19: =IF(R19=0,0,R19/G19) -> 0.073342326 | T19: =5580264+'Vtas efectivo'!BJ19 -> 6695453 | U19: =IF(T19=0,0,T19/G19) -> 0.060788419 | V19: 470011 | W19: =IF(V19=0,0,V19/G19) -> 0.0042672581 | X19: 100000 | Y19: =IF(X19=0,0,X19/G19) -> 0.000907906 | Z19: =39370234+1932518 -> 41302752 | AA19: =IF(Z19=0,0,Z19/G19) -> 0.37499016 | AB19: =+'Vtas efectivo'!Z19 -> 1221737 | AC19: =IF(AB19=0,0,AB19/G19) -> 0.011092224 | AE19: =IF(AD19=0,0,AD19/G19) -> 0 | AF19: 210000 | AG19: =IF(AF19=0,0,AF19/G19) -> 0.0019066026 | AH19: =+'Vtas efectivo'!BK19 -> 0 | AI19: =IF(AH19=0,0,AH19/G19) -> 0 | AJ19: 41422000 | AK19: =+J19-AJ19 -> 162171.3 | AL19: =+AL18+AK19 -> 1915641.4 | AN19: =+AM19-AJ19 -> -41422000 | AO19: =+AO18+AN19 -> -112715000
B20: 18 | C20: =+Bioacem!C24 -> M | D20: =+'G. Corriente'!E24*'G. Corriente'!$G$4 -> 51048122 | E20: =+Bioacem!E24*Bioacem!$E$4 -> 55509775 | F20: =+'G. Extra'!E24*'G. Extra'!$G$4 -> 5105497.8 | G20: =SUM(C20:F20) -> 1.1166339e+08 | H20: =+Bioacem!E24+'G. Corriente'!E24+'G. Extra'!E24 -> 8806.88 | I20: =758+449+42+56+20+5+33+7 -> 1370 | J20: =+G20-L20-P20-T20-V20-R20-X20-Z20-AB20-AD20-AF20-AH20 -> 36961326 | K20: =IF(J20=0,0,J20/G20) -> 0.33100665 | L20: =14461260-N20 -> 14107915 | M20: =IF(L20=0,0,L20/G20) -> 0.12634324 | N20: 353345 | O20: =IF(N20=0,0,N20/G20) -> 0.0031643763 | Q20: =IF(P20=0,0,P20/G20) -> 0 | R20: 7960980 | S20: =IF(R20=0,0,R20/G20) -> 0.071294447 | T20: =6302169+'Vtas efectivo'!BJ20 -> 6888035 | U20: =IF(T20=0,0,T20/G20) -> 0.061685703 | W20: =IF(V20=0,0,V20/G20) -> 0 | X20: 931755 | Y20: =IF(X20=0,0,X20/G20) -> 0.0083443191 | Z20: =39142824+3077715 -> 42220539 | AA20: =IF(Z20=0,0,Z20/G20) -> 0.37810546 | AB20: =+'Vtas efectivo'!Z20 -> 2343044 | AC20: =IF(AB20=0,0,AB20/G20) -> 0.020983098 | AE20: =IF(AD20=0,0,AD20/G20) -> 0 | AF20: 142000 | AG20: =IF(AF20=0,0,AF20/G20) -> 0.0012716791 | AH20: =+'Vtas efectivo'!BK20 -> 107800 | AI20: =IF(AH20=0,0,AH20/G20) -> 0.00096540142 | AJ20: 36773000 | AK20: =+J20-AJ20 -> 188326.4 | AL20: =+AL19+AK20 -> 2103967.8 | AN20: =+AM20-AJ20 -> -36773000 | AO20: =+AO19+AN20 -> -149488000
B21: 19 | C21: =+Bioacem!C25 -> J | D21: =+'G. Corriente'!E25*'G. Corriente'!$G$4 -> 52638515 | E21: =+Bioacem!E25*Bioacem!$E$4 -> 51555172 | F21: =+'G. Extra'!E25*'G. Extra'!$G$4 -> 6145607 | G21: =SUM(C21:F21) -> 1.1033929e+08 | H21: =+Bioacem!E25+'G. Corriente'!E25+'G. Extra'!E25 -> 8601.27 | I21: =707+442+27+47+24+58+3+21+1 -> 1330 | J21: =+G21-L21-P21-T21-V21-R21-X21-Z21-AB21-AD21-AF21-AH21 -> 37332189 | K21: =IF(J21=0,0,J21/G21) -> 0.33833993 | L21: =14794561-N21 -> 14756723 | M21: =IF(L21=0,0,L21/G21) -> 0.13373951 | N21: 37838 | O21: =IF(N21=0,0,N21/G21) -> 0.00034292407 | Q21: =IF(P21=0,0,P21/G21) -> 0 | R21: 7376378 | S21: =IF(R21=0,0,R21/G21) -> 0.066851778 | T21: =4315529+'Vtas efectivo'!BJ21 -> 4686438 | U21: =IF(T21=0,0,T21/G21) -> 0.042472974 | V21: 159000 | W21: =IF(V21=0,0,V21/G21) -> 0.0014410098 | X21: 627249 | Y21: =IF(X21=0,0,X21/G21) -> 0.0056847291 | Z21: =41428002+2097307 -> 43525309 | AA21: =IF(Z21=0,0,Z21/G21) -> 0.39446789 | AB21: =+'Vtas efectivo'!Z21 -> 1546008 | AC21: =IF(AB21=0,0,AB21/G21) -> 0.0140114 | AE21: =IF(AD21=0,0,AD21/G21) -> 0 | AF21: 330000 | AG21: =IF(AF21=0,0,AF21/G21) -> 0.002990775 | AH21: =+'Vtas efectivo'!BK21 -> 0 | AI21: =IF(AH21=0,0,AH21/G21) -> 0 | AJ21: 37212000 | AK21: =+J21-AJ21 -> 120189.1 | AL21: =+AL20+AK21 -> 2224156.9 | AM21: 117573000 | AN21: =+AM21-AJ21 -> 80361000 | AO21: =+AO20+AN21 -> -69127000
B22: 20 | C22: =+Bioacem!C26 -> V | D22: =+'G. Corriente'!E26*'G. Corriente'!$G$4 -> 63973444 | E22: =+Bioacem!E26*Bioacem!$E$4 -> 56111130 | F22: =+'G. Extra'!E26*'G. Extra'!$G$4 -> 8168724.2 | G22: =SUM(C22:F22) -> 1.282533e+08 | H22: =+Bioacem!E26+'G. Corriente'!E26+'G. Extra'!E26 -> 9883.25 | I22: =829+500+25+39+53+27+14+4+1 -> 1492 | J22: =+G22-L22-P22-T22-V22-R22-X22-Z22-AB22-AD22-AF22-AH22 -> 47443550 | K22: =IF(J22=0,0,J22/G22) -> 0.3699207 | L22: =15020059-N22 -> 14923809 | M22: =IF(L22=0,0,L22/G22) -> 0.11636199 | N22: 96250 | O22: =IF(N22=0,0,N22/G22) -> 0.00075046803 | Q22: =IF(P22=0,0,P22/G22) -> 0 | R22: 6068321 | S22: =IF(R22=0,0,R22/G22) -> 0.047315126 | T22: =3466410+'Vtas efectivo'!BJ22 -> 5559122 | U22: =IF(T22=0,0,T22/G22) -> 0.043344866 | V22: 53362 | W22: =IF(V22=0,0,V22/G22) -> 0.00041606727 | X22: 526586 | Y22: =IF(X22=0,0,X22/G22) -> 0.0041058281 | Z22: =47609227+4017539 -> 51626766 | AA22: =IF(Z22=0,0,Z22/G22) -> 0.40253753 | AB22: =+'Vtas efectivo'!Z22 -> 1726783 | AC22: =IF(AB22=0,0,AB22/G22) -> 0.013463849 | AE22: =IF(AD22=0,0,AD22/G22) -> 0 | AF22: 325000 | AG22: =IF(AF22=0,0,AF22/G22) -> 0.0025340479 | AH22: =+'Vtas efectivo'!BK22 -> 0 | AI22: =IF(AH22=0,0,AH22/G22) -> 0 | AJ22: 47271000 | AK22: =+J22-AJ22 -> 172549.7 | AL22: =+AL21+AK22 -> 2396706.6 | AM22: 33496000 | AN22: =+AM22-AJ22 -> -13775000 | AO22: =+AO21+AN22 -> -82902000
B23: 21 | C23: =+Bioacem!C27 -> S | D23: =+'G. Corriente'!E27*'G. Corriente'!$G$4 -> 81926202 | E23: =+Bioacem!E27*Bioacem!$E$4 -> 32103800 | F23: =+'G. Extra'!E27*'G. Extra'!$G$4 -> 13641404 | G23: =SUM(C23:F23) -> 1.2767141e+08 | H23: =+Bioacem!E27+'G. Corriente'!E27+'G. Extra'!E27 -> 9134.75 | I23: =875+707+13+25+10+18+2+3+13+3 -> 1669 | J23: =+G23-L23-P23-T23-V23-R23-X23-Z23-AB23-AD23-AF23-AH23 -> 46151452 | K23: =IF(J23=0,0,J23/G23) -> 0.36148621 | L23: =7217375-N23 -> 7155775 | M23: =IF(L23=0,0,L23/G23) -> 0.056048376 | N23: 61600 | O23: =IF(N23=0,0,N23/G23) -> 0.00048248862 | Q23: =IF(P23=0,0,P23/G23) -> 0 | R23: 2826430 | S23: =IF(R23=0,0,R23/G23) -> 0.022138317 | T23: =1872042+'Vtas efectivo'!BJ23 -> 2256236 | U23: =IF(T23=0,0,T23/G23) -> 0.017672211 | V23: 339759 | W23: =IF(V23=0,0,V23/G23) -> 0.0026611989 | X23: 472261 | Y23: =IF(X23=0,0,X23/G23) -> 0.003699035 | Z23: =63528381+3735732 -> 67264113 | AA23: =IF(Z23=0,0,Z23/G23) -> 0.52685339 | AB23: =+'Vtas efectivo'!Z23 -> 830380 | AC23: =IF(AB23=0,0,AB23/G23) -> 0.0065040405 | AE23: =IF(AD23=0,0,AD23/G23) -> 0 | AF23: 375000 | AG23: =IF(AF23=0,0,AF23/G23) -> 0.0029372278 | AH23: =+'Vtas efectivo'!BK23 -> 0 | AI23: =IF(AH23=0,0,AH23/G23) -> 0 | AJ23: 46067000 | AK23: =+J23-AJ23 -> 84452.1 | AL23: =+AL22+AK23 -> 2481158.7 | AN23: =+AM23-AJ23 -> -46067000 | AO23: =+AO22+AN23 -> -128969000
B24: 22 | C24: =+Bioacem!C28 -> D | D24: =+'G. Corriente'!E28*'G. Corriente'!$G$4 -> 64132332 | E24: =+Bioacem!E28*Bioacem!$E$4 -> 15291660 | F24: =+'G. Extra'!E28*'G. Extra'!$G$4 -> 11045288 | G24: =SUM(C24:F24) -> 90469279 | H24: =+Bioacem!E28+'G. Corriente'!E28+'G. Extra'!E28 -> 6255.74 | I24: =678+516+8+20+2+12+10+1 -> 1247 | J24: =+G24-L24-P24-T24-V24-R24-X24-Z24-AB24-AD24-AF24-AH24 -> 35478399 | K24: =IF(J24=0,0,J24/G24) -> 0.39215963 | L24: =2803839-N24 -> 2767329 | M24: =IF(L24=0,0,L24/G24) -> 0.030588604 | N24: 36510 | O24: =IF(N24=0,0,N24/G24) -> 0.00040356241 | Q24: =IF(P24=0,0,P24/G24) -> 0 | R24: 3197049 | S24: =IF(R24=0,0,R24/G24) -> 0.035338504 | T24: =+'Vtas efectivo'!BJ24 -> 166331 | U24: =IF(T24=0,0,T24/G24) -> 0.0018385357 | V24: 184676 | W24: =IF(V24=0,0,V24/G24) -> 0.0020413117 | Y24: =IF(X24=0,0,X24/G24) -> 0 | Z24: =45437466+2555752 -> 47993218 | AA24: =IF(Z24=0,0,Z24/G24) -> 0.53049188 | AB24: =+'Vtas efectivo'!Z24 -> 346277 | AC24: =IF(AB24=0,0,AB24/G24) -> 0.0038275645 | AE24: =IF(AD24=0,0,AD24/G24) -> 0 | AF24: 336000 | AG24: =IF(AF24=0,0,AF24/G24) -> 0.0037139679 | AH24: =+'Vtas efectivo'!BK24 -> 0 | AI24: =IF(AH24=0,0,AH24/G24) -> 0 | AJ24: 35499000 | AK24: =+J24-AJ24 -> -20600.6 | AL24: =+AL23+AK24 -> 2460558.1 | AN24: =+AM24-AJ24 -> -35499000 | AO24: =+AO23+AN24 -> -164468000
B25: 23 | C25: =+Bioacem!C29 -> L | D25: =+'G. Corriente'!E29*'G. Corriente'!$G$4 -> 50196570 | E25: =+Bioacem!E29*Bioacem!$E$4 -> 56028892 | F25: =+'G. Extra'!E29*'G. Extra'!$G$4 -> 6405815 | G25: =SUM(C25:F25) -> 1.1263128e+08 | H25: =+Bioacem!E29+'G. Corriente'!E29+'G. Extra'!E29 -> 8871.07 | I25: =756+433+44+30+62+8+4+12+2+1 -> 1352 | J25: =+G25-L25-P25-T25-V25-R25-X25-Z25-AB25-AD25-AF25-AH25 -> 45243550 | K25: =IF(J25=0,0,J25/G25) -> 0.40169614 | L25: =12857685+N25 -> 12857685 | M25: =IF(L25=0,0,L25/G25) -> 0.11415732 | O25: =IF(N25=0,0,N25/G25) -> 0 | Q25: =IF(P25=0,0,P25/G25) -> 0 | R25: =7134610+79003 -> 7213613 | S25: =IF(R25=0,0,R25/G25) -> 0.064046268 | T25: =5546456+'Vtas efectivo'!BJ25 -> 5817861 | U25: =IF(T25=0,0,T25/G25) -> 0.051654044 | W25: =IF(V25=0,0,V25/G25) -> 0 | X25: 532290 | Y25: =IF(X25=0,0,X25/G25) -> 0.0047259519 | Z25: =39556343-769035 -> 38787308 | AA25: =IF(Z25=0,0,Z25/G25) -> 0.34437422 | AB25: =+'Vtas efectivo'!Z25 -> 1975971 | AC25: =IF(AB25=0,0,AB25/G25) -> 0.017543715 | AE25: =IF(AD25=0,0,AD25/G25) -> 0 | AF25: 203000 | AG25: =IF(AF25=0,0,AF25/G25) -> 0.0018023413 | AH25: =+'Vtas efectivo'!BK25 -> 0 | AI25: =IF(AH25=0,0,AH25/G25) -> 0 | AJ25: 45153000 | AK25: =+J25-AJ25 -> 90549.7 | AL25: =+AL24+AK25 -> 2551107.8 | AM25: 121884000 | AN25: =+AM25-AJ25 -> 76731000 | AO25: =+AO24+AN25 -> -87737000
B26: 24 | C26: =+Bioacem!C30 -> M | D26: =+'G. Corriente'!E30*'G. Corriente'!$G$4 -> 48361162 | E26: =+Bioacem!E30*Bioacem!$E$4 -> 53639597 | F26: =+'G. Extra'!E30*'G. Extra'!$G$4 -> 5177416.4 | G26: =SUM(C26:F26) -> 1.0717818e+08 | H26: =+Bioacem!E30+'G. Corriente'!E30+'G. Extra'!E30 -> 8460 | I26: =747+427+50+48+19+24+8+1+2+3 -> 1329 | J26: =+G26-L26-P26-T26-V26-R26-X26-Z26-AB26-AD26-AF26-AH26 -> 37823715 | K26: =IF(J26=0,0,J26/G26) -> 0.35290501 | L26: =12991088-N26 -> 12666575 | M26: =IF(L26=0,0,L26/G26) -> 0.11818241 | N26: 324513 | O26: =IF(N26=0,0,N26/G26) -> 0.0030277899 | Q26: =IF(P26=0,0,P26/G26) -> 0 | R26: 9730177 | S26: =IF(R26=0,0,R26/G26) -> 0.090785058 | T26: =4747126+'Vtas efectivo'!BJ26 -> 6188609 | U26: =IF(T26=0,0,T26/G26) -> 0.057741316 | V26: 337733 | W26: =IF(V26=0,0,V26/G26) -> 0.0031511359 | X26: 375181 | Y26: =IF(X26=0,0,X26/G26) -> 0.0035005354 | Z26: =37238998+702186 -> 37941184 | AA26: =IF(Z26=0,0,Z26/G26) -> 0.35400102 | AB26: =+'Vtas efectivo'!Z26 -> 1993002 | AC26: =IF(AB26=0,0,AB26/G26) -> 0.018595222 | AE26: =IF(AD26=0,0,AD26/G26) -> 0 | AF26: 122000 | AG26: =IF(AF26=0,0,AF26/G26) -> 0.0011382914 | AH26: =+'Vtas efectivo'!BK26 -> 0 | AI26: =IF(AH26=0,0,AH26/G26) -> 0 | AJ26: 37748000 | AK26: =+J26-AJ26 -> 75715.4 | AL26: =+AL25+AK26 -> 2626823.2 | AN26: =+AM26-AJ26 -> -37748000 | AO26: =+AO25+AN26 -> -125485000
B27: 25 | C27: =+Bioacem!C31 -> M | D27: =+'G. Corriente'!E31*'G. Corriente'!$G$4 -> 52674059 | E27: =+Bioacem!E31*Bioacem!$E$4 -> 59307858 | F27: =+'G. Extra'!E31*'G. Extra'!$G$4 -> 6114165.2 | G27: =SUM(C27:F27) -> 1.1809608e+08 | H27: =+Bioacem!E31+'G. Corriente'!E31+'G. Extra'!E31 -> 9323.05 | I27: =811+504+39+31+57+15+2+14+1 -> 1474 | J27: =+G27-L27-P27-T27-V27-R27-X27-Z27-AB27-AD27-AF27-AH27 -> 43240453 | K27: =IF(J27=0,0,J27/G27) -> 0.36614638 | L27: =14231794-N27 -> 14181744 | M27: =IF(L27=0,0,L27/G27) -> 0.12008649 | N27: 50050 | O27: =IF(N27=0,0,N27/G27) -> 0.00042380746 | Q27: =IF(P27=0,0,P27/G27) -> 0 | R27: 7290298 | S27: =IF(R27=0,0,R27/G27) -> 0.061731921 | T27: =6122993+'Vtas efectivo'!BJ27 -> 6512756 | U27: =IF(T27=0,0,T27/G27) -> 0.055147943 | W27: =IF(V27=0,0,V27/G27) -> 0 | X27: 307686 | Y27: =IF(X27=0,0,X27/G27) -> 0.002605387 | Z27: =44171403+1514885 -> 45686288 | AA27: =IF(Z27=0,0,Z27/G27) -> 0.38685693 | AB27: =+'Vtas efectivo'!Z27 -> 460557 | AC27: =IF(AB27=0,0,AB27/G27) -> 0.00389985 | AE27: =IF(AD27=0,0,AD27/G27) -> 0 | AF27: 347000 | AG27: =IF(AF27=0,0,AF27/G27) -> 0.0029382855 | AH27: =+'Vtas efectivo'!BK27 -> 69300 | AI27: =IF(AH27=0,0,AH27/G27) -> 0.00058681032 | AJ27: 42899000 | AK27: =+J27-AJ27 -> 341452.9 | AL27: =+AL26+AK27 -> 2968276.1 | AN27: =+AM27-AJ27 -> -42899000 | AO27: =+AO26+AN27 -> -168384000
B28: 26 | C28: =+Bioacem!C32 -> J | D28: =+'G. Corriente'!E32*'G. Corriente'!$G$4 -> 48273972 | E28: =+Bioacem!E32*Bioacem!$E$4 -> 50011688 | F28: =+'G. Extra'!E32*'G. Extra'!$G$4 -> 6794500.7 | G28: =SUM(C28:F28) -> 1.0508016e+08 | H28: =+Bioacem!E32+'G. Corriente'!E32+'G. Extra'!E32 -> 8206.27 | I28: =677+494+42+46+2+23+20+8+12 -> 1324 | J28: =+G28-L28-P28-T28-V28-R28-X28-Z28-AB28-AD28-AF28-AH28 -> 33530636 | K28: =IF(J28=0,0,J28/G28) -> 0.31909578 | L28: =9850684-N28 -> 9850684 | M28: =IF(L28=0,0,L28/G28) -> 0.093744471 | O28: =IF(N28=0,0,N28/G28) -> 0 | Q28: =IF(P28=0,0,P28/G28) -> 0 | R28: 7071587 | S28: =IF(R28=0,0,R28/G28) -> 0.067297071 | T28: =3700866+'Vtas efectivo'!BJ28 -> 5104371 | U28: =IF(T28=0,0,T28/G28) -> 0.048575973 | V28: 277324 | W28: =IF(V28=0,0,V28/G28) -> 0.0026391661 | X28: 1175172 | Y28: =IF(X28=0,0,X28/G28) -> 0.011183576 | Z28: =44979538+1338169 -> 46317707 | AA28: =IF(Z28=0,0,Z28/G28) -> 0.44078451 | AB28: =+'Vtas efectivo'!Z28 -> 1667679 | AC28: =IF(AB28=0,0,AB28/G28) -> 0.015870541 | AE28: =IF(AD28=0,0,AD28/G28) -> 0 | AF28: 85000 | AG28: =IF(AF28=0,0,AF28/G28) -> 0.00080890627 | AH28: =+'Vtas efectivo'!BK28 -> 0 | AI28: =IF(AH28=0,0,AH28/G28) -> 0 | AJ28: 33322000 | AK28: =+J28-AJ28 -> 208636.1 | AL28: =+AL27+AK28 -> 3176912.2 | AN28: =+AM28-AJ28 -> -33322000 | AO28: =+AO27+AN28 -> -201706000
B29: 27 | C29: =+Bioacem!C33 -> V | D29: =+'G. Corriente'!E33*'G. Corriente'!$G$4 -> 64268586 | E29: =+Bioacem!E33*Bioacem!$E$4 -> 54880362 | F29: =+'G. Extra'!E33*'G. Extra'!$G$4 -> 11205207 | G29: =SUM(C29:F29) -> 1.3035416e+08 | H29: =+Bioacem!E33+'G. Corriente'!E33+'G. Extra'!E33 -> 9956.23 | I29: =748+594+22+37+55+29+1+7+14+1 -> 1508 | J29: =+G29-L29-P29-T29-V29-R29-X29-Z29-AB29-AD29-AF29-AH29 -> 44993835 | K29: =IF(J29=0,0,J29/G29) -> 0.34516609 | L29: =13327811-N29 -> 13296911 | M29: =IF(L29=0,0,L29/G29) -> 0.10200604 | N29: 30900 | O29: =IF(N29=0,0,N29/G29) -> 0.00023704653 | Q29: =IF(P29=0,0,P29/G29) -> 0 | R29: =4611284+93905 -> 4705189 | S29: =IF(R29=0,0,R29/G29) -> 0.036095428 | T29: =5649454+'Vtas efectivo'!BJ29 -> 6903659 | U29: =IF(T29=0,0,T29/G29) -> 0.052960789 | V29: 119196 | W29: =IF(V29=0,0,V29/G29) -> 0.00091440123 | X29: 975565 | Y29: =IF(X29=0,0,X29/G29) -> 0.0074839578 | Z29: =55975866+449591 -> 56425457 | AA29: =IF(Z29=0,0,Z29/G29) -> 0.43286274 | AB29: =+'Vtas efectivo'!Z29 -> 2792344 | AC29: =IF(AB29=0,0,AB29/G29) -> 0.021421212 | AE29: =IF(AD29=0,0,AD29/G29) -> 0 | AF29: 142000 | AG29: =IF(AF29=0,0,AF29/G29) -> 0.00108934 | AH29: =+'Vtas efectivo'!BK29 -> 0 | AI29: =IF(AH29=0,0,AH29/G29) -> 0 | AJ29: 44988000 | AK29: =+J29-AJ29 -> 5834.7 | AL29: =+AL28+AK29 -> 3182746.9 | AM29: 167521000 | AN29: =+AM29-AJ29 -> 122533000 | AO29: =+AO28+AN29 -> -79173000
B30: 28 | C30: =+Bioacem!C34 -> S | D30: =+'G. Corriente'!E34*'G. Corriente'!$G$4 -> 92690747 | E30: =+Bioacem!E34*Bioacem!$E$4 -> 31870740 | F30: =+'G. Extra'!E34*'G. Extra'!$G$4 -> 16131631 | G30: =SUM(C30:F30) -> 1.4069312e+08 | H30: =+Bioacem!E34+'G. Corriente'!E34+'G. Extra'!E34 -> 9959.54 | I30: =970+696+11+23+25+9+9+5+1 -> 1749 | J30: =+G30-L30-P30-T30-V30-R30-X30-Z30-AB30-AD30-AF30-AH30 -> 51441504 | K30: =IF(J30=0,0,J30/G30) -> 0.36562914 | L30: =4285702-N30 -> 4140014 | M30: =IF(L30=0,0,L30/G30) -> 0.029425846 | N30: 145688 | O30: =IF(N30=0,0,N30/G30) -> 0.001035502 | P30: 124634 | Q30: =IF(P30=0,0,P30/G30) -> 0.00088585712 | R30: 4767081 | S30: =IF(R30=0,0,R30/G30) -> 0.03388283 | T30: =1624745+'Vtas efectivo'!BJ30 -> 2039770 | U30: =IF(T30=0,0,T30/G30) -> 0.014498008 | W30: =IF(V30=0,0,V30/G30) -> 0 | X30: 659056 | Y30: =IF(X30=0,0,X30/G30) -> 0.0046843514 | Z30: =65763091+10845568 -> 76608659 | AA30: =IF(Z30=0,0,Z30/G30) -> 0.54450893 | AB30: =+'Vtas efectivo'!Z30 -> 619150 | AC30: =IF(AB30=0,0,AB30/G30) -> 0.0044007128 | AE30: =IF(AD30=0,0,AD30/G30) -> 0 | AF30: 197000 | AG30: =IF(AF30=0,0,AF30/G30) -> 0.0014002106 | AH30: =+'Vtas efectivo'!BK30 -> 96250 | AI30: =IF(AH30=0,0,AH30/G30) -> 0.00068411306 | AJ30: 51295000 | AK30: =+J30-AJ30 -> 146504.2 | AL30: =+AL29+AK30 -> 3329251.1 | AN30: =+AM30-AJ30 -> -51295000 | AO30: =+AO29+AN30 -> -130468000
B31: 29 | C31: =+Bioacem!C35 -> D | D31: =+'G. Corriente'!E35*'G. Corriente'!$G$4 -> 0 | E31: =+Bioacem!E35*Bioacem!$E$4 -> 0 | F31: =+'G. Extra'!E35*'G. Extra'!$G$4 -> 0 | G31: =SUM(C31:F31) -> 0 | H31: =+Bioacem!E35+'G. Corriente'!E35+'G. Extra'!E35 -> 0 | J31: =+G31-L31-P31-T31-V31-R31-X31-Z31-AB31-AD31-AF31-AH31 -> 0 | K31: =IF(J31=0,0,J31/G31) -> 0 | M31: =IF(L31=0,0,L31/G31) -> 0 | O31: =IF(N31=0,0,N31/G31) -> 0 | Q31: =IF(P31=0,0,P31/G31) -> 0 | S31: =IF(R31=0,0,R31/G31) -> 0 | U31: =IF(T31=0,0,T31/G31) -> 0 | W31: =IF(V31=0,0,V31/G31) -> 0 | Y31: =IF(X31=0,0,X31/G31) -> 0 | AA31: =IF(Z31=0,0,Z31/G31) -> 0 | AB31: =+'Vtas efectivo'!Z31 -> 0 | AC31: =IF(AB31=0,0,AB31/G31) -> 0 | AE31: =IF(AD31=0,0,AD31/G31) -> 0 | AG31: =IF(AF31=0,0,AF31/G31) -> 0 | AH31: =+'Vtas efectivo'!BK31 -> 0 | AI31: =IF(AH31=0,0,AH31/G31) -> 0 | AK31: =+J31-AJ31 -> 0 | AL31: =+AL30+AK31 -> 3329251.1 | AN31: =+AM31-AJ31 -> 0 | AO31: =+AO30+AN31 -> -130468000
B32: 30 | C32: =+Bioacem!C36 -> L | D32: =+'G. Corriente'!E36*'G. Corriente'!$G$4 -> 0 | E32: =+Bioacem!E36*Bioacem!$E$4 -> 0 | F32: =+'G. Extra'!E36*'G. Extra'!$G$4 -> 0 | G32: =SUM(C32:F32) -> 0 | H32: =+Bioacem!E36+'G. Corriente'!E36+'G. Extra'!E36 -> 0 | J32: =+G32-L32-P32-T32-V32-R32-X32-Z32-AB32-AD32-AF32-AH32 -> 0 | K32: =IF(J32=0,0,J32/G32) -> 0 | M32: =IF(L32=0,0,L32/G32) -> 0 | O32: =IF(N32=0,0,N32/G32) -> 0 | Q32: =IF(P32=0,0,P32/G32) -> 0 | S32: =IF(R32=0,0,R32/G32) -> 0 | U32: =IF(T32=0,0,T32/G32) -> 0 | W32: =IF(V32=0,0,V32/G32) -> 0 | Y32: =IF(X32=0,0,X32/G32) -> 0 | AA32: =IF(Z32=0,0,Z32/G32) -> 0 | AB32: =+'Vtas efectivo'!Z32 -> 0 | AC32: =IF(AB32=0,0,AB32/G32) -> 0 | AE32: =IF(AD32=0,0,AD32/G32) -> 0 | AG32: =IF(AF32=0,0,AF32/G32) -> 0 | AH32: =+'Vtas efectivo'!BK32 -> 0 | AI32: =IF(AH32=0,0,AH32/G32) -> 0 | AK32: =+J32-AJ32 -> 0 | AL32: =+AL31+AK32 -> 3329251.1 | AN32: =+AM32-AJ32 -> 0 | AO32: =+AO31+AN32 -> -130468000
B33: 31 | C33: =+Bioacem!C37 -> M | D33: =+'G. Corriente'!E37*'G. Corriente'!$G$4 -> 0 | E33: =+Bioacem!E37*Bioacem!$E$4 -> 0 | F33: =+'G. Extra'!E37*'G. Extra'!$G$4 -> 0 | G33: =SUM(C33:F33) -> 0 | H33: =+Bioacem!E37+'G. Corriente'!E37+'G. Extra'!E37 -> 0 | J33: =+G33-L33-P33-T33-V33-R33-X33-Z33-AB33-AD33-AF33-AH33 -> 0 | K33: =IF(J33=0,0,J33/G33) -> 0 | M33: =IF(L33=0,0,L33/G33) -> 0 | O33: =IF(N33=0,0,N33/G33) -> 0 | Q33: =IF(P33=0,0,P33/G33) -> 0 | S33: =IF(R33=0,0,R33/G33) -> 0 | U33: =IF(T33=0,0,T33/G33) -> 0 | W33: =IF(V33=0,0,V33/G33) -> 0 | Y33: =IF(X33=0,0,X33/G33) -> 0 | AA33: =IF(Z33=0,0,Z33/G33) -> 0 | AB33: =+'Vtas efectivo'!Z33 -> 0 | AC33: =IF(AB33=0,0,AB33/G33) -> 0 | AE33: =IF(AD33=0,0,AD33/G33) -> 0 | AG33: =IF(AF33=0,0,AF33/G33) -> 0 | AH33: =+'Vtas efectivo'!BK33 -> 0 | AI33: =IF(AH33=0,0,AH33/G33) -> 0 | AK33: =+J33-AJ33 -> 0 | AL33: =+AL32+AK33 -> 3329251.1 | AN33: =+AM33-AJ33 -> 0 | AO33: =+AO32+AN33 -> -130468000
D34: =SUM(D3:D33) -> 1604880255 | E34: =SUM(E3:E33) -> 1.3087085e+09 | F34: =SUM(F3:F33) -> 2.1358881e+08 | G34: =SUM(G3:G33) -> 3.1271776e+09 | H34: =SUM(H3:H33) -> 238711.71 | I34: =SUM(I3:I33) -> 38043 | J34: =SUM(J3:J33) -> 1.1187823e+09 | K34: =IF(J34=0,0,J34/$G$34) -> 0.35776102 | L34: =SUM(L3:L33) -> 309299449 | M34: =IF(L34=0,0,L34/$G$34) -> 0.098906902 | N34: =SUM(N3:N33) -> 3908775 | O34: =IF(N34=0,0,N34/$G$34) -> 0.001249937 | P34: =SUM(P3:P33) -> 124634 | Q34: =IF(P34=0,0,P34/$G$34) -> 3.9855108e-05 | R34: =SUM(R3:R33) -> 167762707 | S34: =IF(R34=0,0,R34/$G$34) -> 0.053646683 | T34: =SUM(T3:T33) -> 135293098 | U34: =IF(T34=0,0,T34/$G$34) -> 0.043263644 | V34: =SUM(V3:V33) -> 2650612 | W34: =IF(V34=0,0,V34/$G$34) -> 0.0008476052 | X34: =SUM(X3:X33) -> 15841445 | Y34: =IF(X34=0,0,X34/$G$34) -> 0.0050657324 | Z34: =SUM(Z3:Z33) -> 1332439302 | AA34: =IF(Z34=0,0,Z34/$G$34) -> 0.42608367 | AB34: =SUM(AB3:AB33) -> 37717263 | AC34: =IF(AB34=0,0,AB34/$G$34) -> 0.01206112 | AD34: =SUM(AD3:AD33) -> 0 | AE34: =IF(AD34=0,0,AD34/$G$34) -> 0 | AF34: =SUM(AF3:AF33) -> 6647000 | AG34: =IF(AF34=0,0,AF34/$G$34) -> 0.0021255588 | AH34: =SUM(AH3:AH33) -> 619850 | AI34: =IF(AH34=0,0,AH34/$G$34) -> 0.00019821388 | AJ34: =SUM(AJ3:AJ33) -> 1115453000 | AM34: =SUM(AM3:AM33) -> 984985000
D35: =+D34/$G$34 -> 0.51320406 | E35: =+E34/$G$34 -> 0.41849511 | F35: =+F34/$G$34 -> 0.068300824 | J35: =+K34*$H$34 -> 85401.745 | L35: =+M34*$H$34 -> 23610.236 | N35: =+O34*$H$34 -> 298.3746 | P35: =+Q34*$H$34 -> 9.5138809 | R35: =+S34*$H$34 -> 12806.092 | T35: =+U34*$H$34 -> 10327.538 | X35: =+Y34*$H$34 -> 1209.2496 | Z35: =+AA34*$H$34 -> 101711.16 | AB35: =+AC34*$H$34 -> 2879.1305 | AD35: =+AE34*$H$34 -> 0 | AF35: =+AG34*$H$34 -> 507.39578 | AH35: =+AI34*$H$34 -> 47.315974
P36: =+L35+R35+N35 -> 36714.702
D37: % MIX DIARIO | G37: CLIENTES | J37: TIQUETE PROMEDIO
B38: Día | D38: Vta Corriente | E38: Vta Bioacem | F38: Vta Extra | G38: Vta Corriente | H38: Vta Bioacem | I38: Vta Extra | J38: Vta Corriente | K38: Vta Acpm | L38: Vta Extra
B39: 1 | C39: =+C3 -> D | D39: =IF(D3=0,0,'G. Corriente'!E7/$H3) -> 0.7189672 | E39: =IF(E3=0,0, Bioacem!E7/$H3) -> 0.20406359 | F39: =IF(F3=0,0,'G. Extra'!E7/$H3) -> 0.076969214
B40: 2 | C40: =+C4 -> L | D40: =IF(D4=0,0,'G. Corriente'!E8/$H4) -> 0.33510172 | E40: =IF(E4=0,0, Bioacem!E8/$H4) -> 0.63890716 | F40: =IF(F4=0,0,'G. Extra'!E8/$H4) -> 0.025991125
B41: 3 | C41: =+C5 -> M | D41: =IF(D5=0,0,'G. Corriente'!E9/$H5) -> 0.33317874 | E41: =IF(E5=0,0, Bioacem!E9/$H5) -> 0.62740726 | F41: =IF(F5=0,0,'G. Extra'!E9/$H5) -> 0.039414003
B42: 4 | C42: =+C6 -> M | D42: =IF(D6=0,0,'G. Corriente'!E10/$H6) -> 0.32699189 | E42: =IF(E6=0,0, Bioacem!E10/$H6) -> 0.63864192 | F42: =IF(F6=0,0,'G. Extra'!E10/$H6) -> 0.034366191
B43: 5 | C43: =+C7 -> J | D43: =IF(D7=0,0,'G. Corriente'!E11/$H7) -> 0.19541036 | E43: =IF(E7=0,0, Bioacem!E11/$H7) -> 0.79252129 | F43: =IF(F7=0,0,'G. Extra'!E11/$H7) -> 0.012068348
B44: 6 | C44: =+C8 -> V | D44: =IF(D8=0,0,'G. Corriente'!E12/$H8) -> 0.44618896 | E44: =IF(E8=0,0, Bioacem!E12/$H8) -> 0.51540432 | F44: =IF(F8=0,0,'G. Extra'!E12/$H8) -> 0.038406714
B45: 7 | C45: =+C9 -> S | D45: =IF(D9=0,0,'G. Corriente'!E13/$H9) -> 0.49837865 | E45: =IF(E9=0,0, Bioacem!E13/$H9) -> 0.43362903 | F45: =IF(F9=0,0,'G. Extra'!E13/$H9) -> 0.067992317
B46: 8 | C46: =+C10 -> D | D46: =IF(D10=0,0,'G. Corriente'!E14/$H10) -> 0.66926639 | E46: =IF(E10=0,0, Bioacem!E14/$H10) -> 0.26824789 | F46: =IF(F10=0,0,'G. Extra'!E14/$H10) -> 0.062485722
B47: 9 | C47: =+C11 -> L | D47: =IF(D11=0,0,'G. Corriente'!E15/$H11) -> 0.38225033 | E47: =IF(E11=0,0, Bioacem!E15/$H11) -> 0.5832989 | F47: =IF(F11=0,0,'G. Extra'!E15/$H11) -> 0.034450778
B48: 10 | C48: =+C12 -> M | D48: =IF(D12=0,0,'G. Corriente'!E16/$H12) -> 0.36740369 | E48: =IF(E12=0,0, Bioacem!E16/$H12) -> 0.59940929 | F48: =IF(F12=0,0,'G. Extra'!E16/$H12) -> 0.033187029
B49: 11 | C49: =+C13 -> M | D49: =IF(D13=0,0,'G. Corriente'!E17/$H13) -> 0.38798141 | E49: =IF(E13=0,0, Bioacem!E17/$H13) -> 0.57346699 | F49: =IF(F13=0,0,'G. Extra'!E17/$H13) -> 0.038551597
B50: 12 | C50: =+C14 -> J | D50: =IF(D14=0,0,'G. Corriente'!E18/$H14) -> 0.37606474 | E50: =IF(E14=0,0, Bioacem!E18/$H14) -> 0.58900129 | F50: =IF(F14=0,0,'G. Extra'!E18/$H14) -> 0.034933974
... B69: 31 | C69: =+C33 -> M | D69: =IF(D33=0,0,'G. Corriente'!E37/$H33) -> 0 | E69: =IF(E33=0,0, Bioacem!E37/$H33) -> 0 | F69: =IF(F33=0,0,'G. Extra'!E37/$H33) -> 0
B70: TOTAL | D70: =+AVERAGE(D39:D69) -> 0.40393534 | E70: =+AVERAGE(E39:E69) -> 0.45493948 | F70: =+AVERAGE(F39:F69) -> 0.044350991

Sheet Vtas efectivo
B2: Día | D2: CRC | E2: CRC UREA | F2: EASY CEM | G2: UT NUTRIENDO | H2: MAURICIO C | I2: COLEG NUEVA INGLATERRA | J2: COLEG NUEVA INGLATERRA UREA | K2: LA COLINA BRANDS | L2: LAB BRANDS | M2: CAPITAL USPEC | N2: CAPITAL USPEC UREA | O2: OCMIA | P2: AQUA | Q2: BAM | R2: BAM UREA | S2: INSMEVET | T2: INSMEVET UREA | U2: INTEXCO | V2: AVSA | W2: DACT CHEMICAL | X2: VERPACKEN | Y2: SANTILLANA | Z2: QR | AA2: QR UREA | AB2: DISPAPELES | AC2: DASA HIGH | AD2: PETMAX | AE2: IMPRESISTEM | AF2: JANETH TELLEZ | AG2: PROVEFABRICA | AH2: PROVEFABRICA UREA | AI2: PARAISO | AJ2: FM INGENIERIA | AK2: WILLIAM JIMENEZ | AL2: EDS JAP | AM2: SEBASTIAN RAMIREZ | AN2: PARQUE ROSALINDA | AO2: FIGUCENTRO | AP2: FIGUCENTER UREA | AQ2: INTERPHARMA | AR2: SERVICIO PREMIERE | AS2: DICOLTEXCO | AT2: VARIOS | AU2: JOSE LUIS | AV2: SILVINO | AW2: ANDREA ZARATE | AX2: OFFICE SUPPLY | AY2: GESTOAGRO | AZ2: TRANSP LA RUTA | BA2: TRANSP LA RUTA UREA | BB2: POMAR | BC2: LEXMANA | BD2: LEXMANA UREA | BE2: ETRICOL | BF2: GRAFICAS JAIBER | BG2: GRAFICAS JAIBER LUB | BH2: UNION SERVIR | BI2: UNION SERVIR UREA | BJ2: TOTAL COMBUSTIBLE | BK2: TOTAL UREA | BL2: TOTAL LUB
B3: 1 | C3: =+Bioacem!C7 -> D | Z3: =20000+20000+130000+17078+10000+100000+26020+110019+25350+20000+21140+12000+93540 -> 605147 | BJ3: =+D3+F3+G3+H3+I3+K3+L3+M3+P3+Q3+S3+U3+W3+X3+Y3+AB3+AC3+AD3+AE3+AF3+AG3+AI3+AJ3+AK3+AL3+AT3+AM3+AN3+AQ3+AO3+AS3+AU3+O3+AV3+AX3+AR3+AW3+AY3+AZ3+BB3+BE3+BC3+BF3+BH3 -> 0 | BK3: =+R3+N3+J3+E3+AP3+AH3+BA3+BD3+T3+AA3+BI3 -> 0 | BL3: =+BG3 -> 0 | BM3: =+BJ3+BK3+BL3 -> 0
B4: 2 | C4: =+Bioacem!C8 -> L | O4: 380002 | Z4: =50000+30000+200000+38300+200000+350000+25000+64038+67000+18000+33000+25000+40000+288150+250000+22000+30000+129750+20000+150000+30000 -> 2060238 | AT4: 223912 | AW4: 579769 | AZ4: =301000+176463+273276+281650+192597+100000+190286+136181 -> 1651453 | BJ4: =+D4+F4+G4+H4+I4+K4+L4+M4+P4+Q4+S4+U4+W4+X4+Y4+AB4+AC4+AD4+AE4+AF4+AG4+AI4+AJ4+AK4+AL4+AT4+AM4+AN4+AQ4+AO4+AS4+AU4+O4+AV4+AX4+AR4+AW4+AY4+AZ4+BB4+BE4+BC4+BF4+BH4 -> 2835136 | BK4: =+R4+N4+J4+E4+AP4+AH4+BA4+BD4+T4+AA4+BI4 -> 0 | BL4: =+BG4 -> 0 | BM4: =+BJ4+BK4+BL4 -> 2835136
B5: 3 | C5: =+Bioacem!C9 -> M | Z5: =10000+150833+25000+50000+100000+25000+50000+77950+14000+220053+77950+30000+230000+40000 -> 1100786 | AY5: 163757 | AZ5: =120604+135214+301172+450178 -> 1007168 | BH5: 531824 | BJ5: =+D5+F5+G5+H5+I5+K5+L5+M5+P5+Q5+S5+U5+W5+X5+Y5+AB5+AC5+AD5+AE5+AF5+AG5+AI5+AJ5+AK5+AL5+AT5+AM5+AN5+AQ5+AO5+AS5+AU5+O5+AV5+AX5+AR5+AW5+AY5+AZ5+BB5+BE5+BC5+BF5+BH5 -> 1702749 | BK5: =+R5+N5+J5+E5+AP5+AH5+BA5+BD5+T5+AA5+BI5 -> 0 | BL5: =+BG5 -> 0 | BM5: =+BJ5+BK5+BL5 -> 1702749
B6: 4 | C6: =+Bioacem!C10 -> M | Z6: =30000+25000+20000+74003+15000+27000+158434+48641+50000+23073+65011+40000+20000+10000 -> 606162 | AZ6: =198552+91934 -> 290486 | BJ6: =+D6+F6+G6+H6+I6+K6+L6+M6+P6+Q6+S6+U6+W6+X6+Y6+AB6+AC6+AD6+AE6+AF6+AG6+AI6+AJ6+AK6+AL6+AT6+AM6+AN6+AQ6+AO6+AS6+AU6+O6+AV6+AX6+AR6+AW6+AY6+AZ6+BB6+BE6+BC6+BF6+BH6 -> 290486 | BK6: =+R6+N6+J6+E6+AP6+AH6+BA6+BD6+T6+AA6+BI6 -> 0 | BL6: =+BG6 -> 0 | BM6: =+BJ6+BK6+BL6 -> 290486
B7: 5 | C7: =+Bioacem!C11 -> J | D7: 297033 | Z7: =20000+80000+100000+20000+149335+15000+135000 -> 519335 | AZ7: =151016+333658+240101+164462 -> 889237 | BJ7: =+D7+F7+G7+H7+I7+K7+L7+M7+P7+Q7+S7+U7+W7+X7+Y7+AB7+AC7+AD7+AE7+AF7+AG7+AI7+AJ7+AK7+AL7+AT7+AM7+AN7+AQ7+AO7+AS7+AU7+O7+AV7+AX7+AR7+AW7+AY7+AZ7+BB7+BE7+BC7+BF7+BH7 -> 1186270 | BK7: =+R7+N7+J7+E7+AP7+AH7+BA7+BD7+T7+AA7+BI7 -> 0 | BL7: =+BG7 -> 0 | BM7: =+BJ7+BK7+BL7 -> 1186270
B8: 6 | C8: =+Bioacem!C12 -> V | J8: 57750 | Q8: 270685 | R8: 84700 | Z8: =68000+46451+30000+20000+15000+10000+50000+169194+50000+54008+35000+30000+33000+50000+50000+146644+35013+50000+50000+45570+900000+50000+40000+60760 -> 2088640 | AE8: 78626 | AZ8: =351342+135848+362759 -> 849949 | BE8: 211749 | BH8: 530942 | BJ8: =+D8+F8+G8+H8+I8+K8+L8+M8+P8+Q8+S8+U8+W8+X8+Y8+AB8+AC8+AD8+AE8+AF8+AG8+AI8+AJ8+AK8+AL8+AT8+AM8+AN8+AQ8+AO8+AS8+AU8+O8+AV8+AX8+AR8+AW8+AY8+AZ8+BB8+BE8+BC8+BF8+BH8 -> 1941951 | BK8: =+R8+N8+J8+E8+AP8+AH8+BA8+BD8+T8+AA8+BI8 -> 142450 | BL8: =+BG8 -> 0 | BM8: =+BJ8+BK8+BL8 -> 2084401
B9: 7 | C9: =+Bioacem!C13 -> S | Z9: =30000+132381+172012+50000+50000+40370+34500+15000+150000+251948+20000+20000+50000+140000+70000+66338+171638+40000+225192 -> 1729379 | AT9: 217010 | AZ9: =114627+369005+100061+379819+150371+135009 -> 1248892 | BA9: 23100 | BJ9: =+D9+F9+G9+H9+I9+K9+L9+M9+P9+Q9+S9+U9+W9+X9+Y9+AB9+AC9+AD9+AE9+AF9+AG9+AI9+AJ9+AK9+AL9+AT9+AM9+AN9+AQ9+AO9+AS9+AU9+O9+AV9+AX9+AR9+AW9+AY9+AZ9+BB9+BE9+BC9+BF9+BH9 -> 1465902 | BK9: =+R9+N9+J9+E9+AP9+AH9+BA9+BD9+T9+AA9+BI9 -> 23100 | BL9: =+BG9 -> 0 | BM9: =+BJ9+BK9+BL9 -> 1489002
B10: 8 | C10: =+Bioacem!C14 -> D | Z10: =477214+26000+50000+200000+120000+121034+50000+20000+46024+20000+18000+120000+10000 -> 1278272 | AZ10: =39141+41269 -> 80410 | BJ10: =+D10+F10+G10+H10+I10+K10+L10+M10+P10+Q10+S10+U10+W10+X10+Y10+AB10+AC10+AD10+AE10+AF10+AG10+AI10+AJ10+AK10+AL10+AT10+AM10+AN10+AQ10+AO10+AS10+AU10+O10+AV10+AX10+AR10+AW10+AY10+AZ10+BB10+BE10+BC10+BF10+BH10 -> 80410 | BK10: =+R10+N10+J10+E10+AP10+AH10+BA10+BD10+T10+AA10+BI10 -> 0 | BL10: =+BG10 -> 0 | BM10: =+BJ10+BK10+BL10 -> 80410
B11: 9 | C11: =+Bioacem!C15 -> L | Z11: =206500+140000+50000+10000+12000+32000+150000+50000+80000+100000+168463+20000+65005+233436+43097+34650+333100+301000+32000 -> 2061251 | AG11: 91824 | AZ11: =341592+130011+226675+280468+373541 -> 1352287 | BJ11: =+D11+F11+G11+H11+I11+K11+L11+M11+P11+Q11+S11+U11+W11+X11+Y11+AB11+AC11+AD11+AE11+AF11+AG11+AI11+AJ11+AK11+AL11+AT11+AM11+AN11+AQ11+AO11+AS11+AU11+O11+AV11+AX11+AR11+AW11+AY11+AZ11+BB11+BE11+BC11+BF11+BH11 -> 1444111 | BK11: =+R11+N11+J11+E11+AP11+AH11+BA11+BD11+T11+AA11+BI11 -> 0 | BL11: =+BG11 -> 0 | BM11: =+BJ11+BK11+BL11 -> 1444111
B12: 10 | C12: =+Bioacem!C16 -> M | Z12: =356000+50000+100000+50000+108489+110000+52383+135826+138032+200000+45000+10700+36760+45570+30000+140019+10000 -> 1618779 | AZ12: =348687+466034+180600+421099+145961 -> 1562381 | BA12: 180950 | BJ12: =+D12+F12+G12+H12+I12+K12+L12+M12+P12+Q12+S12+U12+W12+X12+Y12+AB12+AC12+AD12+AE12+AF12+AG12+AI12+AJ12+AK12+AL12+AT12+AM12+AN12+AQ12+AO12+AS12+AU12+O12+AV12+AX12+AR12+AW12+AY12+AZ12+BB12+BE12+BC12+BF12+BH12 -> 1562381 | BK12: =+R12+N12+J12+E12+AP12+AH12+BA12+BD12+T12+AA12+BI12 -> 180950 | BL12: =+BG12 -> 0 | BM12: =+BJ12+BK12+BL12 -> 1743331
B13: 11 | C13: =+Bioacem!C17 -> M | Z13: =100000+63000+120000+75000+20000+25000+50000+33000+13000+20000+75980+23043+50000+100000+40000+69037+30000+47900+15000+30000+20000+35000+20000 -> 1074960 | AZ13: =291196+106006+50005+378045+240134 -> 1065386 | BE13: 103641 | BJ13: =+D13+F13+G13+H13+I13+K13+L13+M13+P13+Q13+S13+U13+W13+X13+Y13+AB13+AC13+AD13+AE13+AF13+AG13+AI13+AJ13+AK13+AL13+AT13+AM13+AN13+AQ13+AO13+AS13+AU13+O13+AV13+AX13+AR13+AW13+AY13+AZ13+BB13+BE13+BC13+BF13+BH13 -> 1169027 | BK13: =+R13+N13+J13+E13+AP13+AH13+BA13+BD13+T13+AA13+BI13 -> 0 | BL13: =+BG13 -> 0 | BM13: =+BJ13+BK13+BL13 -> 1169027
B14: 12 | C14: =+Bioacem!C18 -> J | Q14: =150000+267181 -> 417181 | Z14: =35000+120000+20000+40000+39000+191092+75023+30000+30000+16000+32000+50000+100000+20000+61502+100000+181414+15190+110016+10000 -> 1276237 | AZ14: 120047 | BE14: 123920 | BJ14: =+D14+F14+G14+H14+I14+K14+L14+M14+P14+Q14+S14+U14+W14+X14+Y14+AB14+AC14+AD14+AE14+AF14+AG14+AI14+AJ14+AK14+AL14+AT14+AM14+AN14+AQ14+AO14+AS14+AU14+O14+AV14+AX14+AR14+AW14+AY14+AZ14+BB14+BE14+BC14+BF14+BH14 -> 661148 | BK14: =+R14+N14+J14+E14+AP14+AH14+BA14+BD14+T14+AA14+BI14 -> 0 | BL14: =+BG14 -> 0 | BM14: =+BJ14+BK14+BL14 -> 661148
B15: 13 | C15: =+Bioacem!C19 -> V | Q15: 150000 | Z15: =60000+72000+15800+50000+20000+46021+350000+133010+100000+20000+50000+20500+20000 -> 957331 | AY15: 156092 | AZ15: =226116+239790+181030+208066 -> 855002 | BE15: 120798 | BJ15: =+D15+F15+G15+H15+I15+K15+L15+M15+P15+Q15+S15+U15+W15+X15+Y15+AB15+AC15+AD15+AE15+AF15+AG15+AI15+AJ15+AK15+AL15+AT15+AM15+AN15+AQ15+AO15+AS15+AU15+O15+AV15+AX15+AR15+AW15+AY15+AZ15+BB15+BE15+BC15+BF15+BH15 -> 1281892 | BK15: =+R15+N15+J15+E15+AP15+AH15+BA15+BD15+T15+AA15+BI15 -> 0 | BL15: =+BG15 -> 0 | BM15: =+BJ15+BK15+BL15 -> 1281892
B16: 14 | C16: =+Bioacem!C20 -> S | Z16: =30000+450000+100000+200000+15000+10000+30000+26400+20000+11000+19000+20000+125850+100000+13580+70000+34642+18052+85000 -> 1378524 | AZ16: =365145+269513 -> 634658 | BJ16: =+D16+F16+G16+H16+I16+K16+L16+M16+P16+Q16+S16+U16+W16+X16+Y16+AB16+AC16+AD16+AE16+AF16+AG16+AI16+AJ16+AK16+AL16+AT16+AM16+AN16+AQ16+AO16+AS16+AU16+O16+AV16+AX16+AR16+AW16+AY16+AZ16+BB16+BE16+BC16+BF16+BH16 -> 634658 | BK16: =+R16+N16+J16+E16+AP16+AH16+BA16+BD16+T16+AA16+BI16 -> 0 | BL16: =+BG16 -> 0 | BM16: =+BJ16+BK16+BL16 -> 634658
B17: 15 | C17: =+Bioacem!C21 -> D | Z17: =20000+200000+6618+40000+20000+50000+37839+65000+30000+100000+15000+20000 -> 604457 | AZ17: 253969 | BJ17: =+D17+F17+G17+H17+I17+K17+L17+M17+P17+Q17+S17+U17+W17+X17+Y17+AB17+AC17+AD17+AE17+AF17+AG17+AI17+AJ17+AK17+AL17+AT17+AM17+AN17+AQ17+AO17+AS17+AU17+O17+AV17+AX17+AR17+AW17+AY17+AZ17+BB17+BE17+BC17+BF17+BH17 -> 253969 | BK17: =+R17+N17+J17+E17+AP17+AH17+BA17+BD17+T17+AA17+BI17 -> 0 | BL17: =+BG17 -> 0 | BM17: =+BJ17+BK17+BL17 -> 253969
B18: 16 | C18: =+Bioacem!C22 -> L | Z18: =150000+100000+20000+35000+50000+100000+10000+177590+23043+100000+200000+20000+189200+60000 -> 1234833 | AZ18: =317620+120077+134010+100406+374573+331627 -> 1378313 | BJ18: =+D18+F18+G18+H18+I18+K18+L18+M18+P18+Q18+S18+U18+W18+X18+Y18+AB18+AC18+AD18+AE18+AF18+AG18+AI18+AJ18+AK18+AL18+AT18+AM18+AN18+AQ18+AO18+AS18+AU18+O18+AV18+AX18+AR18+AW18+AY18+AZ18+BB18+BE18+BC18+BF18+BH18 -> 1378313 | BK18: =+R18+N18+J18+E18+AP18+AH18+BA18+BD18+T18+AA18+BI18 -> 0 | BL18: =+BG18 -> 0 | BM18: =+BJ18+BK18+BL18 -> 1378313
B19: 17 | C19: =+Bioacem!C23 -> M | Q19: 150000 | Z19: =25000+50000+200000+40000+200000+40000+64027+60000+147899+70000+40000+28600+50000+15190+173021+18000 -> 1221737 | AZ19: =217924+133988+6687 -> 358599 | BH19: 606590 | BJ19: =+D19+F19+G19+H19+I19+K19+L19+M19+P19+Q19+S19+U19+W19+X19+Y19+AB19+AC19+AD19+AE19+AF19+AG19+AI19+AJ19+AK19+AL19+AT19+AM19+AN19+AQ19+AO19+AS19+AU19+O19+AV19+AX19+AR19+AW19+AY19+AZ19+BB19+BE19+BC19+BF19+BH19 -> 1115189 | BK19: =+R19+N19+J19+E19+AP19+AH19+BA19+BD19+T19+AA19+BI19 -> 0 | BL19: =+BG19 -> 0 | BM19: =+BJ19+BK19+BL19 -> 1115189
B20: 18 | C20: =+Bioacem!C24 -> M | R20: 92400 | Z20: =300000+41616+30000+50000+75950+50100+271000+100000+70000+100000+350000+90000+50000+10000+100000+124378+30000+80000+30000+100000+290000 -> 2343044 | AM20: 68381 | AZ20: =185008+255270+77207 -> 517485 | BA20: 15400 | BJ20: =+D20+F20+G20+H20+I20+K20+L20+M20+P20+Q20+S20+U20+W20+X20+Y20+AB20+AC20+AD20+AE20+AF20+AG20+AI20+AJ20+AK20+AL20+AT20+AM20+AN20+AQ20+AO20+AS20+AU20+O20+AV20+AX20+AR20+AW20+AY20+AZ20+BB20+BE20+BC20+BF20+BH20 -> 585866 | BK20: =+R20+N20+J20+E20+AP20+AH20+BA20+BD20+T20+AA20+BI20 -> 107800 | BL20: =+BG20 -> 0 | BM20: =+BJ20+BK20+BL20 -> 693666
B21: 19 | C21: =+Bioacem!C25 -> J | Z21: =50000+20000+20000+15000+25000+40000+30000+100000+15000+100000+188813+150000+145000+59071+34952+26461+40000+121520+20000+10000+40000+70000+125191+100000 -> 1546008 | AZ21: =110477+160892 -> 271369 | BE21: 99540 | BJ21: =+D21+F21+G21+H21+I21+K21+L21+M21+P21+Q21+S21+U21+W21+X21+Y21+AB21+AC21+AD21+AE21+AF21+AG21+AI21+AJ21+AK21+AL21+AT21+AM21+AN21+AQ21+AO21+AS21+AU21+O21+AV21+AX21+AR21+AW21+AY21+AZ21+BB21+BE21+BC21+BF21+BH21 -> 370909 | BK21: =+R21+N21+J21+E21+AP21+AH21+BA21+BD21+T21+AA21+BI21 -> 0 | BL21: =+BG21 -> 0 | BM21: =+BJ21+BK21+BL21 -> 370909
B22: 20 | C22: =+Bioacem!C26 -> V | Z22: =978250+5500+50000+15190+30000+250000+18836+30000+31747+247260+30000+40000 -> 1726783 | AL22: 211055 | AZ22: =387634+281091+172505+124281+377658+213784+193694+131010 -> 1881657 | BJ22: =+D22+F22+G22+H22+I22+K22+L22+M22+P22+Q22+S22+U22+W22+X22+Y22+AB22+AC22+AD22+AE22+AF22+AG22+AI22+AJ22+AK22+AL22+AT22+AM22+AN22+AQ22+AO22+AS22+AU22+O22+AV22+AX22+AR22+AW22+AY22+AZ22+BB22+BE22+BC22+BF22+BH22 -> 2092712 | BK22: =+R22+N22+J22+E22+AP22+AH22+BA22+BD22+T22+AA22+BI22 -> 0 | BL22: =+BG22 -> 0 | BM22: =+BJ22+BK22+BL22 -> 2092712
B23: 21 | C23: =+Bioacem!C27 -> S | Z23: =30380+30000+100000+100000+50000+10000+50000+30000+30000+20000+100000+150000+50000+43000+20000+17000 -> 830380 | AZ23: =79679+304515 -> 384194 | BJ23: =+D23+F23+G23+H23+I23+K23+L23+M23+P23+Q23+S23+U23+W23+X23+Y23+AB23+AC23+AD23+AE23+AF23+AG23+AI23+AJ23+AK23+AL23+AT23+AM23+AN23+AQ23+AO23+AS23+AU23+O23+AV23+AX23+AR23+AW23+AY23+AZ23+BB23+BE23+BC23+BF23+BH23 -> 384194 | BK23: =+R23+N23+J23+E23+AP23+AH23+BA23+BD23+T23+AA23+BI23 -> 0 | BL23: =+BG23 -> 0 | BM23: =+BJ23+BK23+BL23 -> 384194
B24: 22 | C24: =+Bioacem!C28 -> D | Z24: =11350+40000+14300+60000+10000+10000+40000+30577+100000+30050 -> 346277 | BE24: 166331 | BJ24: =+D24+F24+G24+H24+I24+K24+L24+M24+P24+Q24+S24+U24+W24+X24+Y24+AB24+AC24+AD24+AE24+AF24+AG24+AI24+AJ24+AK24+AL24+AT24+AM24+AN24+AQ24+AO24+AS24+AU24+O24+AV24+AX24+AR24+AW24+AY24+AZ24+BB24+BE24+BC24+BF24+BH24 -> 166331 | BK24: =+R24+N24+J24+E24+AP24+AH24+BA24+BD24+T24+AA24+BI24 -> 0 | BL24: =+BG24 -> 0 | BM24: =+BJ24+BK24+BL24 -> 166331
B25: 23 | C25: =+Bioacem!C29 -> L | Z25: =100000+200000+81066+50000+164120+560000+50000+37785+50000+20000+10000+50000+30000+100000+20000+320000+40000+18000+75000 -> 1975971 | AZ25: 271405 | BJ25: =+D25+F25+G25+H25+I25+K25+L25+M25+P25+Q25+S25+U25+W25+X25+Y25+AB25+AC25+AD25+AE25+AF25+AG25+AI25+AJ25+AK25+AL25+AT25+AM25+AN25+AQ25+AO25+AS25+AU25+O25+AV25+AX25+AR25+AW25+AY25+AZ25+BB25+BE25+BC25+BF25+BH25 -> 271405 | BK25: =+R25+N25+J25+E25+AP25+AH25+BA25+BD25+T25+AA25+BI25 -> 0 | BL25: =+BG25 -> 0 | BM25: =+BJ25+BK25+BL25 -> 271405
B26: 24 | C26: =+Bioacem!C30 -> M | Z26: =35000+100000+20000+20000+26100+38000+189300+38446+20000+30000+38051+350100+100000+33069+151900+20000+7656+30380+25000+220000+50000+450000 -> 1993002 | AQ26: 220483 | AY26: 110158 | AZ26: =132268+193627+90092+110037 -> 526024 | BE26: 104067 | BH26: 480751 | BJ26: =+D26+F26+G26+H26+I26+K26+L26+M26+P26+Q26+S26+U26+W26+X26+Y26+AB26+AC26+AD26+AE26+AF26+AG26+AI26+AJ26+AK26+AL26+AT26+AM26+AN26+AQ26+AO26+AS26+AU26+O26+AV26+AX26+AR26+AW26+AY26+AZ26+BB26+BE26+BC26+BF26+BH26 -> 1441483 | BK26: =+R26+N26+J26+E26+AP26+AH26+BA26+BD26+T26+AA26+BI26 -> 0 | BL26: =+BG26 -> 0 | BM26: =+BJ26+BK26+BL26 -> 1441483
B27: 25 | C27: =+Bioacem!C31 -> M | Z27: =50000+34056+30000+24500+20000+25000+12000+50000+20000+29300+27950+35000+20000+26051+20000+36700 -> 460557 | AZ27: =191382+198381 -> 389763 | BA27: =38500+30800 -> 69300 | BJ27: =+D27+F27+G27+H27+I27+K27+L27+M27+P27+Q27+S27+U27+W27+X27+Y27+AB27+AC27+AD27+AE27+AF27+AG27+AI27+AJ27+AK27+AL27+AT27+AM27+AN27+AQ27+AO27+AS27+AU27+O27+AV27+AX27+AR27+AW27+AY27+AZ27+BB27+BE27+BC27+BF27+BH27 -> 389763 | BK27: =+R27+N27+J27+E27+AP27+AH27+BA27+BD27+T27+AA27+BI27 -> 69300 | BL27: =+BG27 -> 0 | BM27: =+BJ27+BK27+BL27 -> 459063
B28: 26 | C28: =+Bioacem!C32 -> J | Q28: 300000 | Z28: =200000+12000+10000+50000+10830+190000+70000+100000+27813+60750+26111+200000+500000+20000+80000+25000+45175+30000+10000 -> 1667679 | AZ28: =368123+318404+262891+154087 -> 1103505 | BJ28: =+D28+F28+G28+H28+I28+K28+L28+M28+P28+Q28+S28+U28+W28+X28+Y28+AB28+AC28+AD28+AE28+AF28+AG28+AI28+AJ28+AK28+AL28+AT28+AM28+AN28+AQ28+AO28+AS28+AU28+O28+AV28+AX28+AR28+AW28+AY28+AZ28+BB28+BE28+BC28+BF28+BH28 -> 1403505 | BK28: =+R28+N28+J28+E28+AP28+AH28+BA28+BD28+T28+AA28+BI28 -> 0 | BL28: =+BG28 -> 0 | BM28: =+BJ28+BK28+BL28 -> 1403505
B29: 27 | C29: =+Bioacem!C33 -> V | Q29: 325929 | Z29: =47000+37307+1000000+20000+30000+368026+400000+43065+20000+47900+100000+25000+15000+100000+297700+30836+16694+46816+30000+5000+100000+12000 -> 2792344 | AZ29: =433021+80674+137202+168603 -> 819500 | BE29: 108776 | BJ29: =+D29+F29+G29+H29+I29+K29+L29+M29+P29+Q29+S29+U29+W29+X29+Y29+AB29+AC29+AD29+AE29+AF29+AG29+AI29+AJ29+AK29+AL29+AT29+AM29+AN29+AQ29+AO29+AS29+AU29+O29+AV29+AX29+AR29+AW29+AY29+AZ29+BB29+BE29+BC29+BF29+BH29 -> 1254205 | BK29: =+R29+N29+J29+E29+AP29+AH29+BA29+BD29+T29+AA29+BI29 -> 0 | BL29: =+BG29 -> 0 | BM29: =+BJ29+BK29+BL29 -> 1254205
B30: 28 | C30: =+Bioacem!C34 -> S | E30: 50050 | Z30: =80000+20000+27400+11450+52656+15000+50000+20000+30000+122644+50000+100000+40000 -> 619150 | AZ30: =133934+204282+76809 -> 415025 | BA30: 46200 | BJ30: =+D30+F30+G30+H30+I30+K30+L30+M30+P30+Q30+S30+U30+W30+X30+Y30+AB30+AC30+AD30+AE30+AF30+AG30+AI30+AJ30+AK30+AL30+AT30+AM30+AN30+AQ30+AO30+AS30+AU30+O30+AV30+AX30+AR30+AW30+AY30+AZ30+BB30+BE30+BC30+BF30+BH30 -> 415025 | BK30: =+R30+N30+J30+E30+AP30+AH30+BA30+BD30+T30+AA30+BI30 -> 96250 | BL30: =+BG30 -> 0 | BM30: =+BJ30+BK30+BL30 -> 511275
B31: 29 | C31: =+Bioacem!C35 -> D | BJ31: =+D31+F31+G31+H31+I31+K31+L31+M31+P31+Q31+S31+U31+W31+X31+Y31+AB31+AC31+AD31+AE31+AF31+AG31+AI31+AJ31+AK31+AL31+AT31+AM31+AN31+AQ31+AO31+AS31+AU31+O31+AV31+AX31+AR31+AW31+AY31+AZ31+BB31+BE31+BC31+BF31+BH31 -> 0 | BK31: =+R31+N31+J31+E31+AP31+AH31+BA31+BD31+T31+AA31+BI31 -> 0 | BL31: =+BG31 -> 0 | BM31: =+BJ31+BK31+BL31 -> 0
B32: 30 | C32: =+Bioacem!C36 -> L | BJ32: =+D32+F32+G32+H32+I32+K32+L32+M32+P32+Q32+S32+U32+W32+X32+Y32+AB32+AC32+AD32+AE32+AF32+AG32+AI32+AJ32+AK32+AL32+AT32+AM32+AN32+AQ32+AO32+AS32+AU32+O32+AV32+AX32+AR32+AW32+AY32+AZ32+BB32+BE32+BC32+BF32+BH32 -> 0 | BK32: =+R32+N32+J32+E32+AP32+AH32+BA32+BD32+T32+AA32+BI32 -> 0 | BL32: =+BG32 -> 0 | BM32: =+BJ32+BK32+BL32 -> 0
B33: 31 | C33: =+Bioacem!C37 -> M | BJ33: =+D33+F33+G33+H33+I33+K33+L33+M33+P33+Q33+S33+U33+W33+X33+Y33+AB33+AC33+AD33+AE33+AF33+AG33+AI33+AJ33+AK33+AL33+AT33+AM33+AN33+AQ33+AO33+AS33+AU33+O33+AV33+AX33+AR33+AW33+AY33+AZ33+BB33+BE33+BC33+BF33+BH33 -> 0 | BK33: =+R33+N33+J33+E33+AP33+AH33+BA33+BD33+T33+AA33+BI33 -> 0 | BL33: =+BG33 -> 0 | BM33: =+BJ33+BK33+BL33 -> 0
BJ34: =SUM(BJ3:BJ33) -> 27778990

Sheet Urea
B2: Día | D2: II | E2: IF | F2: DIF. | G2: RUMBO | H2: C PROP | I2: VALOR | J2: VALOR RUMBO | K2: VALOR PROPIOS | L2: TOTAL | M2: INVENTARIO | N2: RECIBO | Q2: VALOR | R2: 3850
B3: 31 | E3: 73281.2 | M3: 1236.1 | Q3: COSTO | R3: 2950 | S3: =+R2-R3 -> 900 | T3: =+S3/R2 -> 0.23376623
B4: 1 | C4: =+'G. Corriente'!C7 -> D | D4: =+E3 -> 73281.2 | E4: 73307.2 | F4: =+E4-D4 -> 26 | G4: =+Cierre!N3/$R$2 -> 20.238961 | H4: =+Cierre!AH3/$R$2 -> 0 | I4: =+(F4-G4-H4)*$R$2 -> 22180 | J4: =+G4*$R$2 -> 77920 | K4: =+H4*$R$2 -> 0 | L4: =+I4+J4+K4 -> 100100 | M4: =+M3+N3-F4 -> 1210.1 | O4: 22400 | P4: =+O4 -> 22400 | R4: =+P4+[1]Urea!$P$34 -> 1122900
B5: 2 | C5: =+'G. Corriente'!C8 -> L | D5: =+E4 -> 73307.2 | E5: 73429.3 | F5: =+E5-D5 -> 122.1 | G5: =+Cierre!N4/$R$2 -> 21.31013 | H5: =+Cierre!AH4/$R$2 -> 0 | I5: =+(F5-G5-H5)*$R$2 -> 388041 | J5: =+G5*$R$2 -> 82044 | K5: =+H5*$R$2 -> 0 | L5: =+I5+J5+K5 -> 470085 | M5: =+M4+N4-F5 -> 1088 | O5: 388300
B6: 3 | C6: =+'G. Corriente'!C9 -> M | D6: =+E5 -> 73429.3 | E6: 73579.4 | F6: =+E6-D6 -> 150.1 | G6: =+Cierre!N5/$R$2 -> 84.776883 | H6: =+Cierre!AH5/$R$2 -> 0 | I6: =+(F6-G6-H6)*$R$2 -> 251494 | J6: =+G6*$R$2 -> 326391 | K6: =+H6*$R$2 -> 0 | L6: =+I6+J6+K6 -> 577885 | M6: =+M5+N5-F6 -> 937.9 | O6: 251600
B7: 4 | C7: =+'G. Corriente'!C10 -> M | D7: =+E6 -> 73579.4 | E7: 73702.3 | F7: =+E7-D7 -> 122.9 | G7: =+Cierre!N6/$R$2 -> 18 | H7: =+Cierre!AH6/$R$2 -> 0 | I7: =+(F7-G7-H7)*$R$2 -> 403865 | J7: =+G7*$R$2 -> 69300 | K7: =+H7*$R$2 -> 0 | L7: =+I7+J7+K7 -> 473165 | M7: =+M6+N6-F7 -> 815 | O7: 403950
B8: 5 | C8: =+'G. Corriente'!C11 -> J | D8: =+E7 -> 73702.3 | E8: 73842.9 | F8: =+E8-D8 -> 140.6 | G8: =+Cierre!N7/$R$2 -> 92.570909 | H8: =+Cierre!AH7/$R$2 -> 0 | I8: =+(F8-G8-H8)*$R$2 -> 184912 | J8: =+G8*$R$2 -> 356398 | K8: =+H8*$R$2 -> 0 | L8: =+I8+J8+K8 -> 541310 | M8: =+M7+N7-F8 -> 674.4 | O8: 188600
B9: 6 | C9: =+'G. Corriente'!C12 -> V | D9: =+E8 -> 73842.9 | E9: 74006.1 | F9: =+E9-D9 -> 163.2 | G9: =+Cierre!N8/$R$2 -> 32.002078 | H9: =+Cierre!AH8/$R$2 -> 37 | I9: =+(F9-G9-H9)*$R$2 -> 362662 | J9: =+G9*$R$2 -> 123208 | K9: =+H9*$R$2 -> 142450 | L9: =+I9+J9+K9 -> 628320 | M9: =+M8+N8-F9 -> 511.2 | N9: 1000 | O9: 505600
B10: 7 | C10: =+'G. Corriente'!C13 -> S | D10: =+E9 -> 74006.1 | E10: 74107.4 | F10: =+E10-D10 -> 101.3 | G10: =+Cierre!N9/$R$2 -> 14.922078 | H10: =+Cierre!AH9/$R$2 -> 6 | I10: =+(F10-G10-H10)*$R$2 -> 309455 | J10: =+G10*$R$2 -> 57450 | K10: =+H10*$R$2 -> 23100 | L10: =+I10+J10+K10 -> 390005 | M10: =+M9+N9-F10 -> 1409.9 | O10: 332850
B11: 8 | C11: =+'G. Corriente'!C14 -> D | D11: =+E10 -> 74107.4 | E11: 74210.9 | F11: =+E11-D11 -> 103.5 | G11: =+Cierre!N10/$R$2 -> 46.202078 | H11: =+Cierre!AH10/$R$2 -> 0 | I11: =+(F11-G11-H11)*$R$2 -> 220597 | J11: =+G11*$R$2 -> 177878 | K11: =+H11*$R$2 -> 0 | L11: =+I11+J11+K11 -> 398475 | M11: =+M10+N10-F11 -> 1306.4 | O11: 220900
B12: 9 | C12: =+'G. Corriente'!C15 -> L | D12: =+E11 -> 74210.9 | E12: 74289.7 | F12: =+E12-D12 -> 78.8 | G12: =+Cierre!N11/$R$2 -> 38.445974 | H12: =+Cierre!AH11/$R$2 -> 0 | I12: =+(F12-G12-H12)*$R$2 -> 155363 | J12: =+G12*$R$2 -> 148017 | K12: =+H12*$R$2 -> 0 | L12: =+I12+J12+K12 -> 303380 | M12: =+M11+N11-F12 -> 1227.6 | O12: 156300
B13: 10 | C13: =+'G. Corriente'!C16 -> M | D13: =+E12 -> 74289.7 | E13: 74471.1 | F13: =+E13-D13 -> 181.4 | G13: =+Cierre!N12/$R$2 -> 76 | H13: =+Cierre!AH12/$R$2 -> 47 | I13: =+(F13-G13-H13)*$R$2 -> 224840 | J13: =+G13*$R$2 -> 292600 | K13: =+H13*$R$2 -> 180950 | L13: =+I13+J13+K13 -> 698390 | M13: =+M12+N12-F13 -> 1046.2 | O13: 245600 | P13: =+O5+O6+O7+O8+O9+O10+O11+O12+O13 -> 2693700 | Q13: FALTANTE UREA | R13: 160250 | S13: DIF UREA RUMBO
B14: 11 | C14: =+'G. Corriente'!C17 -> M | D14: =+E13 -> 74471.1 | E14: 74504.2 | F14: =+E14-D14 -> 33.1 | G14: =+Cierre!N13/$R$2 -> 0 | H14: =+Cierre!AH13/$R$2 -> 0 | I14: =+(F14-G14-H14)*$R$2 -> 127435 | J14: =+G14*$R$2 -> 0 | K14: =+H14*$R$2 -> 0 | L14: =+I14+J14+K14 -> 127435 | M14: =+M13+N13-F14 -> 1013.1 | O14: 128800
B15: 12 | C15: =+'G. Corriente'!C18 -> J | D15: =+E14 -> 74504.2 | E15: 74606.6 | F15: =+E15-D15 -> 102.4 | G15: =+Cierre!N14/$R$2 -> 46.18 | H15: =+Cierre!AH14/$R$2 -> 0 | I15: =+(F15-G15-H15)*$R$2 -> 216447 | J15: =+G15*$R$2 -> 177793 | K15: =+H15*$R$2 -> 0 | L15: =+I15+J15+K15 -> 394240 | M15: =+M14+N14-F15 -> 910.7 | O15: 217600
B16: 13 | C16: =+'G. Corriente'!C19 -> V | D16: =+E15 -> 74606.6 | E16: 74780.7 | F16: =+E16-D16 -> 174.1 | G16: =+Cierre!N15/$R$2 -> 117.62909 | H16: =+Cierre!AH15/$R$2 -> 0 | I16: =+(F16-G16-H16)*$R$2 -> 217413 | J16: =+G16*$R$2 -> 452872 | K16: =+H16*$R$2 -> 0 | L16: =+I16+J16+K16 -> 670285 | M16: =+M15+N15-F16 -> 736.6 | O16: 221000
B17: 14 | C17: =+'G. Corriente'!C20 -> S | D17: =+E16 -> 74780.7 | E17: 74825.8 | F17: =+E17-D17 -> 45.1 | G17: =+Cierre!N16/$R$2 -> 22 | H17: =+Cierre!AH16/$R$2 -> 0 | I17: =+(F17-G17-H17)*$R$2 -> 88935 | J17: =+G17*$R$2 -> 84700 | K17: =+H17*$R$2 -> 0 | L17: =+I17+J17+K17 -> 173635 | M17: =+M16+N16-F17 -> 691.5 | O17: 88950
B18: 15 | C18: =+'G. Corriente'!C21 -> D | D18: =+E17 -> 74825.8 | E18: 74858 | F18: =+E18-D18 -> 32.2 | G18: =+Cierre!N17/$R$2 -> 0 | H18: =+Cierre!AH17/$R$2 -> 0 | I18: =+(F18-G18-H18)*$R$2 -> 123970 | J18: =+G18*$R$2 -> 0 | K18: =+H18*$R$2 -> 0 | L18: =+I18+J18+K18 -> 123970 | M18: =+M17+N17-F18 -> 659.3 | O18: 124000
B19: 16 | C19: =+'G. Corriente'!C22 -> L | D19: =+E18 -> 74858 | E19: 74946.2 | F19: =+E19-D19 -> 88.2 | G19: =+Cierre!N18/$R$2 -> 31.677922 | H19: =+Cierre!AH18/$R$2 -> 0 | I19: =+(F19-G19-H19)*$R$2 -> 217610 | J19: =+G19*$R$2 -> 121960 | K19: =+H19*$R$2 -> 0 | L19: =+I19+J19+K19 -> 339570 | M19: =+M18+N18-F19 -> 571.1 | O19: 219300
B20: 17 | C20: =+'G. Corriente'!C23 -> M | D20: =+E19 -> 74946.2 | E20: 75186.9 | F20: =+E20-D20 -> 240.7 | G20: =+Cierre!N19/$R$2 -> 58.064935 | H20: =+Cierre!AH19/$R$2 -> 0 | I20: =+(F20-G20-H20)*$R$2 -> 703145 | J20: =+G20*$R$2 -> 223550 | K20: =+H20*$R$2 -> 0 | L20: =+I20+J20+K20 -> 926695 | M20: =+M19+N19-F20 -> 330.4 | O20: 703900
B21: 18 | C21: =+'G. Corriente'!C24 -> M | D21: =+E20 -> 75186.9 | E21: 75384 | F21: =+E21-D21 -> 197.1 | G21: =+Cierre!N20/$R$2 -> 91.777922 | H21: =+Cierre!AH20/$R$2 -> 28 | I21: =+(F21-G21-H21)*$R$2 -> 297690 | J21: =+G21*$R$2 -> 353345 | K21: =+H21*$R$2 -> 107800 | L21: =+I21+J21+K21 -> 758835 | M21: =+M20+N20-F21 -> 133.3 | N21: 1900 | O21: 405350 | P21: =+O21+O20+O19+O18+O17+O16+O15+O14 -> 2108900
B22: 19 | C22: =+'G. Corriente'!C25 -> J | D22: =+E21 -> 75384 | E22: 75496.7 | F22: =+E22-D22 -> 112.7 | G22: =+Cierre!N21/$R$2 -> 9.8280519 | H22: =+Cierre!AH21/$R$2 -> 0 | I22: =+(F22-G22-H22)*$R$2 -> 396057 | J22: =+G22*$R$2 -> 37838 | K22: =+H22*$R$2 -> 0 | L22: =+I22+J22+K22 -> 433895 | M22: =+M21+N21-F22 -> 1920.6 | O22: 396150
B23: 20 | C23: =+'G. Corriente'!C26 -> V | D23: =+E22 -> 75496.7 | E23: 75625 | F23: =+E23-D23 -> 128.3 | G23: =+Cierre!N22/$R$2 -> 25 | H23: =+Cierre!AH22/$R$2 -> 0 | I23: =+(F23-G23-H23)*$R$2 -> 397705 | J23: =+G23*$R$2 -> 96250 | K23: =+H23*$R$2 -> 0 | L23: =+I23+J23+K23 -> 493955 | M23: =+M22+N22-F23 -> 1792.3 | O23: 397850
B24: 21 | C24: =+'G. Corriente'!C27 -> S | D24: =+E23 -> 75625 | E24: 75685.4 | F24: =+E24-D24 -> 60.4 | G24: =+Cierre!N23/$R$2 -> 16 | H24: =+Cierre!AH23/$R$2 -> 0 | I24: =+(F24-G24-H24)*$R$2 -> 170940 | J24: =+G24*$R$2 -> 61600 | K24: =+H24*$R$2 -> 0 | L24: =+I24+J24+K24 -> 232540 | M24: =+M23+N23-F24 -> 1731.9 | O24: 171000
B25: 22 | C25: =+'G. Corriente'!C28 -> D | D25: =+E24 -> 75685.4 | E25: 75765.1 | F25: =+E25-D25 -> 79.7 | G25: =+Cierre!N24/$R$2 -> 9.4831169 | H25: =+Cierre!AH24/$R$2 -> 0 | I25: =+(F25-G25-H25)*$R$2 -> 270335 | J25: =+G25*$R$2 -> 36510 | K25: =+H25*$R$2 -> 0 | L25: =+I25+J25+K25 -> 306845 | M25: =+M24+N24-F25 -> 1652.2 | O25: 270350
B26: 23 | C26: =+'G. Corriente'!C29 -> L | D26: =+E25 -> 75765.1 | E26: 75867.2 | F26: =+E26-D26 -> 102.1 | G26: =+Cierre!N25/$R$2 -> 0 | H26: =+Cierre!AH25/$R$2 -> 0 | I26: =+(F26-G26-H26)*$R$2 -> 393085 | J26: =+G26*$R$2 -> 0 | K26: =+H26*$R$2 -> 0 | L26: =+I26+J26+K26 -> 393085 | M26: =+M25+N25-F26 -> 1550.1 | O26: 393450
B27: 24 | C27: =+'G. Corriente'!C30 -> M | D27: =+E26 -> 75867.2 | E27: 76049.6 | F27: =+E27-D27 -> 182.4 | G27: =+Cierre!N26/$R$2 -> 84.289091 | H27: =+Cierre!AH26/$R$2 -> 0 | I27: =+(F27-G27-H27)*$R$2 -> 377727 | J27: =+G27*$R$2 -> 324513 | K27: =+H27*$R$2 -> 0 | L27: =+I27+J27+K27 -> 702240 | M27: =+M26+N26-F27 -> 1367.7 | O27: 378300
B28: 25 | C28: =+'G. Corriente'!C31 -> M | D28: =+E27 -> 76049.6 | E28: 76203.5 | F28: =+E28-D28 -> 153.9 | G28: =+Cierre!N27/$R$2 -> 13 | H28: =+Cierre!AH27/$R$2 -> 18 | I28: =+(F28-G28-H28)*$R$2 -> 473165 | J28: =+G28*$R$2 -> 50050 | K28: =+H28*$R$2 -> 69300 | L28: =+I28+J28+K28 -> 592515 | M28: =+M27+N27-F28 -> 1213.8 | O28: 542600
B29: 26 | C29: =+'G. Corriente'!C32 -> J | D29: =+E28 -> 76203.5 | E29: 76239.3 | F29: =+E29-D29 -> 35.8 | G29: =+Cierre!N28/$R$2 -> 0 | H29: =+Cierre!AH28/$R$2 -> 0 | I29: =+(F29-G29-H29)*$R$2 -> 137830 | J29: =+G29*$R$2 -> 0 | K29: =+H29*$R$2 -> 0 | L29: =+I29+J29+K29 -> 137830 | M29: =+M28+N28-F29 -> 1178 | O29: 137850
B30: 27 | C30: =+'G. Corriente'!C33 -> V | D30: =+E29 -> 76239.3 | E30: 76322.1 | F30: =+E30-D30 -> 82.8 | G30: =+Cierre!N29/$R$2 -> 8.025974 | H30: =+Cierre!AH29/$R$2 -> 0 | I30: =+(F30-G30-H30)*$R$2 -> 287880 | J30: =+G30*$R$2 -> 30900 | K30: =+H30*$R$2 -> 0 | L30: =+I30+J30+K30 -> 318780 | M30: =+M29+N29-F30 -> 1095.2 | O30: 288600
B31: 28 | C31: =+'G. Corriente'!C34 -> S | D31: =+E30 -> 76322.1 | E31: 76449.1 | F31: =+E31-D31 -> 127 | G31: =+Cierre!N30/$R$2 -> 37.841039 | H31: =+Cierre!AH30/$R$2 -> 25 | I31: =+(F31-G31-H31)*$R$2 -> 247012 | J31: =+G31*$R$2 -> 145688 | K31: =+H31*$R$2 -> 96250 | L31: =+I31+J31+K31 -> 488950 | M31: =+M30+N30-F31 -> 968.2 | O31: 343300 | P31: =+O31+O30+O29+O28+O27+O26+O25+O24+O23+O22 -> 3319450
B32: 29 | C32: =+'G. Corriente'!C35 -> D | D32: =+E31 -> 76449.1 | F32: =+E32-D32 -> -76449.1 | G32: =+Cierre!N31/$R$2 -> 0 | H32: =+Cierre!AH31/$R$2 -> 0 | I32: =+(F32-G32-H32)*$R$2 -> -294329035 | J32: =+G32*$R$2 -> 0 | K32: =+H32*$R$2 -> 0 | L32: =+I32+J32+K32 -> -294329035 | M32: =+M31+N31-F32 -> 77417.3
B33: 30 | C33: =+'G. Corriente'!C36 -> L | D33: =+E32 -> 0 | F33: =+E33-D33 -> 0 | G33: =+Cierre!N32/$R$2 -> 0 | H33: =+Cierre!AH32/$R$2 -> 0 | I33: =+(F33-G33-H33)*$R$2 -> 0 | J33: =+G33*$R$2 -> 0 | K33: =+H33*$R$2 -> 0 | L33: =+I33+J33+K33 -> 0 | M33: =+M32+N32-F33 -> 77417.3
B34: 31 | C34: =+'G. Corriente'!C37 -> M | D34: =+E33 -> 0 | F34: =+E34-D34 -> 0 | G34: =+Cierre!N33/$R$2 -> 0 | H34: =+Cierre!AH33/$R$2 -> 0 | I34: =+(F34-G34-H34)*$R$2 -> 0 | J34: =+G34*$R$2 -> 0 | K34: =+H34*$R$2 -> 0 | L34: =+I34+J34+K34 -> 0 | M34: =+M33+N33-F34 -> 77417.3

Sheet Facturas
B2: FECHA | C2: FACTURA | D2: CANTIDAD COMBUSTIBLE
D3: CTE | E3: EXTRA | F3: SUMA | G3: BIOACEM | H3: TOTAL
B4: 45689 | F4: =+D4+E4 -> 0 | H4: =+D4+E4+G4 -> 0
B5: 45689 | F5: =+D5+E5 -> 0 | H5: =+D5+E5+G5 -> 0
B6: 45690 | C6: 867020135 | D6: 5800 | F6: =+D6+E6 -> 5800 | G6: 2800 | H6: =+D6+E6+G6 -> 8600
B7: 45690 | F7: =+D7+E7 -> 0 | H7: =+D7+E7+G7 -> 0
B8: 45691 | C8: 867029358 | D8: 4000 | F8: =+D8+E8 -> 4000 | G8: 4600 | H8: =+D8+E8+G8 -> 8600
B9: 45691 | F9: =+D9+E9 -> 0 | H9: =+D9+E9+G9 -> 0
B10: 45692 | C10: 867029175 | D10: 2800 | F10: =+D10+E10 -> 2800 | G10: 5800 | H10: =+D10+E10+G10 -> 8600
B11: 45692 | F11: =+D11+E11 -> 0 | H11: =+D11+E11+G11 -> 0
B12: 45693 | C12: 867031351 | D12: 2800 | E12: 1800 | F12: =+D12+E12 -> 4600 | G12: 3500 | H12: =+D12+E12+G12 -> 8100
B13: 45693 | F13: =+D13+E13 -> 0 | H13: =+D13+E13+G13 -> 0
B14: 45694 | C14: 867034431 | F14: =+D14+E14 -> 0 | G14: 5200 | H14: =+D14+E14+G14 -> 5200
B15: 45694 | C15: 867033982 | D15: 4600 | F15: =+D15+E15 -> 4600 | G15: 3500 | H15: =+D15+E15+G15 -> 8100
B16: 45695 | C16: 867040093 | D16: 4600 | F16: =+D16+E16 -> 4600 | G16: 3500 | H16: =+D16+E16+G16 -> 8100
B17: 45695 | F17: =+D17+E17 -> 0 | H17: =+D17+E17+G17 -> 0
B18: 45696 | F18: =+D18+E18 -> 0 | H18: =+D18+E18+G18 -> 0
B19: 45696 | F19: =+D19+E19 -> 0 | H19: =+D19+E19+G19 -> 0
B20: 45697 | C20: 867045369 | D20: 4600 | F20: =+D20+E20 -> 4600 | G20: 4000 | H20: =+D20+E20+G20 -> 8600
B21: 45697 | F21: =+D21+E21 -> 0 | H21: =+D21+E21+G21 -> 0
B22: 45698 | C22: 867053993 | D22: 3700 | E22: 1500 | F22: =+D22+E22 -> 5200 | H22: =+D22+E22+G22 -> 5200
B23: 45698 | C23: 867051899 | F23: =+D23+E23 -> 0 | G23: 5200 | H23: =+D23+E23+G23 -> 5200
B24: 45699 | C24: 867062026 | D24: 1800 | F24: =+D24+E24 -> 1800 | G24: 6800 | H24: =+D24+E24+G24 -> 8600
B25: 45699 | F25: =+D25+E25 -> 0 | H25: =+D25+E25+G25 -> 0
B26: 45700 | C26: 867060096 | D26: 4000 | F26: =+D26+E26 -> 4000 | G26: 4600 | H26: =+D26+E26+G26 -> 8600
B27: 45700 | F27: =+D27+E27 -> 0 | H27: =+D27+E27+G27 -> 0
B28: 45701 | C28: 867063566 | D28: 4000 | F28: =+D28+E28 -> 4000 | G28: 4600 | H28: =+D28+E28+G28 -> 8600
B29: 45701 | F29: =+D29+E29 -> 0 | H29: =+D29+E29+G29 -> 0
B30: 45702 | C30: 867069675 | D30: 4600 | F30: =+D30+E30 -> 4600 | G30: 4000 | H30: =+D30+E30+G30 -> 8600
B31: 45702 | C31: 867069226 | D31: 2800 | E31: 1800 | F31: =+D31+E31 -> 4600 | G31: 4000 | H31: =+D31+E31+G31 -> 8600
B32: 45703 | C32: 867075510 | D32: 4600 | F32: =+D32+E32 -> 4600 | G32: 4000 | H32: =+D32+E32+G32 -> 8600
B33: 45703 | F33: =+D33+E33 -> 0 | H33: =+D33+E33+G33 -> 0
B34: 45704 | F34: =+D34+E34 -> 0 | H34: =+D34+E34+G34 -> 0
B35: 45704 | F35: =+D35+E35 -> 0 | H35: =+D35+E35+G35 -> 0
B36: 45705 | C36: 867083937 | D36: 3300 | E36: 1800 | F36: =+D36+E36 -> 5100 | G36: 3500 | H36: =+D36+E36+G36 -> 8600
B37: 45705 | C37: 867083434 | D37: 4600 | F37: =+D37+E37 -> 4600 | G37: 3500 | H37: =+D37+E37+G37 -> 8100
B38: 45706 | C38: 867084103 | D38: 1800 | F38: =+D38+E38 -> 1800 | G38: 6800 | H38: =+D38+E38+G38 -> 8600
B39: 45706 | F39: =+D39+E39 -> 0 | H39: =+D39+E39+G39 -> 0
B40: 45707 | F40: =+D40+E40 -> 0 | H40: =+D40+E40+G40 -> 0
B41: 45707 | F41: =+D41+E41 -> 0 | H41: =+D41+E41+G41 -> 0
B42: 45708 | C42: 867094878 | D42: 3500 | F42: =+D42+E42 -> 3500 | G42: 6300 | H42: =+D42+E42+G42 -> 9800
B43: 45708 | F43: =+D43+E43 -> 0 | H43: =+D43+E43+G43 -> 0
B44: 45709 | C44: 867099527 | D44: 5800 | F44: =+D44+E44 -> 5800 | G44: 2800 | H44: =+D44+E44+G44 -> 8600
B45: 45709 | F45: =+D45+E45 -> 0 | H45: =+D45+E45+G45 -> 0
B46: 45710 | C46: 867101512 | D46: 5800 | F46: =+D46+E46 -> 5800 | G46: 2800 | H46: =+D46+E46+G46 -> 8600
B47: 45710 | F47: =+D47+E47 -> 0 | H47: =+D47+E47+G47 -> 0
B48: 45711 | C48: 867099706 | D48: 3500 | E48: 1800 | F48: =+D48+E48 -> 5300 | G48: 2800 | H48: =+D48+E48+G48 -> 8100
B49: 45711 | F49: =+D49+E49 -> 0 | H49: =+D49+E49+G49 -> 0
B50: 45712 | C50: 9410634788 | D50: 4000 | F50: =+D50+E50 -> 4000 | G50: 4600 | H50: =+D50+E50+G50 -> 8600
B51: 45712 | F51: =+D51+E51 -> 0 | H51: =+D51+E51+G51 -> 0
B52: 45713 | C52: 867109496 | D52: 2700 | F52: =+D52+E52 -> 2700 | G52: 5800 | H52: =+D52+E52+G52 -> 8500
B53: 45713 | F53: =+D53+E53 -> 0 | H53: =+D53+E53+G53 -> 0
B54: 45714 | C54: 867112976 | D54: 2700 | E54: 1800 | F54: =+D54+E54 -> 4500 | G54: 4000 | H54: =+D54+E54+G54 -> 8500
B55: 45714 | F55: =+D55+E55 -> 0 | H55: =+D55+E55+G55 -> 0
B56: 45715 | C56: 867122879 | D56: 5200 | F56: =+D56+E56 -> 5200 | G56: 5300 | H56: =+D56+E56+G56 -> 10500
B57: 45715 | C57: 867127535 | D57: 3500 | F57: =+D57+E57 -> 3500 | G57: 6300 | H57: =+D57+E57+G57 -> 9800
B58: 45716 | C58: 867128321 | D58: 3500 | E58: 1800 | F58: =+D58+E58 -> 5300 | G58: 2800 | H58: =+D58+E58+G58 -> 8100
B59: 45716 | F59: =+D59+E59 -> 0 | H59: =+D59+E59+G59 -> 0
F60: =+D60+E60 -> 0 | H60: =+D60+E60+G60 -> 0
F61: =+D61+E61 -> 0 | H61: =+D61+E61+G61 -> 0
F62: =+D62+E62 -> 0 | H62: =+D62+E62+G62 -> 0
F63: =+D63+E63 -> 0 | H63: =+D63+E63+G63 -> 0
F64: =+D64+E64 -> 0 | H64: =+D64+E64+G64 -> 0
F65: =+D65+E65 -> 0 | H65: =+D65+E65+G65 -> 0
B66: TOTAL | D66: =SUM(D4:D65) -> 104600 | E66: =SUM(E4:E65) -> 12300 | F66: =SUM(F4:F65) -> 116900 | G66: =SUM(G4:G65) -> 123400
B67: ANULACIONES
B68: TOTAL CON ANULACIONES | D68: =+D66-D67 -> 104600 | E68: =+E66-E67 -> 12300 | F68: =+F66-F67 -> 116900 | G68: =+G66-G67 -> 123400
F69: =+F68+G68 -> 240300

Sheet Fluctuaciones
D2: FLUCTUACION | S2: DESCARGUE
B3: Día | D3: Dia | E3: Acumulado | F3: % Dia | G3: % Acum | H3: Color | I3: Dia | J3: Acumulado | K3: % Dia | L3: % Acum | M3: Color | N3: Dia | O3: Acumulado | P3: % Dia | Q3: % Acum | R3: Color | S3: Cte | T3: Bioacem | U3: Extra | V3: Placa | W3: Planta | X3: Concepto
B4: 1 | C4: S | D4: =+'G. Corriente'!I7 -> 26.47 | E4: =+'G. Corriente'!J7 -> 26.47 | F4: =IF(D4=0,0,D4/'G. Corriente'!E7) -> 0.0059843146 | G4: =+E4/'G. Corriente'!$E$38 -> 0.00025134145 | I4: =+Bioacem!I7 -> -0.453 | J4: =+Bioacem!J7 -> -0.453 | K4: =IF(I4=0,0,I4/Bioacem!E7) -> -0.00036082967 | L4: =J4/Bioacem!$E$38 -> -3.7210348e-06 | N4: =+'G. Extra'!I7 -> -8.539 | O4: =+'G. Extra'!J7 -> -8.539 | P4: =IF(N4=0,0,N4/'G. Extra'!E7) -> -0.018032648 | Q4: =+O4/'G. Extra'!$E$38 -> -0.00073255391 | S4: =+'G. Corriente'!F7 -> 0 | T4: =+Bioacem!F7 -> 0 | U4: =+'G. Extra'!F7 -> 0
B5: 2 | C5: D | D5: =+'G. Corriente'!I8 -> 26.651 | E5: =+'G. Corriente'!J8 -> 53.121 | F5: =IF(D5=0,0,D5/'G. Corriente'!E8) -> 0.0095979112 | G5: =+E5/'G. Corriente'!$E$38 -> 0.00050440156 | I5: =+Bioacem!I8 -> 1755.616 | J5: =+Bioacem!J8 -> 1755.163 | K5: =IF(I5=0,0,I5/Bioacem!E8) -> 0.33161308 | L5: =J5/Bioacem!$E$38 -> 0.014417268 | N5: =+'G. Extra'!I8 -> 32.449 | O5: =+'G. Extra'!J8 -> 23.91 | P5: =IF(N5=0,0,N5/'G. Extra'!E8) -> 0.1506663 | Q5: =+O5/'G. Extra'!$E$38 -> 0.0020512196 | S5: =+'G. Corriente'!F8 -> 5800 | T5: =+Bioacem!F8 -> 2800 | U5: =+'G. Extra'!F8 -> 0
B6: 3 | C6: L | D6: =+'G. Corriente'!I9 -> 60.86 | E6: =+'G. Corriente'!J9 -> 113.981 | F6: =IF(D6=0,0,D6/'G. Corriente'!E9) -> 0.021666459 | G6: =+E6/'G. Corriente'!$E$38 -> 0.0010822875 | I6: =+Bioacem!I9 -> -1548.46 | J6: =+Bioacem!J9 -> 206.703 | K6: =IF(I6=0,0,I6/Bioacem!E9) -> -0.29274112 | L6: =J6/Bioacem!$E$38 -> 0.0016979008 | N6: =+'G. Extra'!I9 -> 30.04 | O6: =+'G. Extra'!J9 -> 53.95 | P6: =IF(N6=0,0,N6/'G. Extra'!E9) -> 0.090402961 | Q6: =+O6/'G. Extra'!$E$38 -> 0.0046283269 | S6: =+'G. Corriente'!F9 -> 4000 | T6: =+Bioacem!F9 -> 4600 | U6: =+'G. Extra'!F9 -> 0
B7: 4 | C7: M | D7: =+'G. Corriente'!I10 -> -85.76 | E7: =+'G. Corriente'!J10 -> 28.221 | F7: =IF(D7=0,0,D7/'G. Corriente'!E10) -> -0.030003009 | G7: =+E7/'G. Corriente'!$E$38 -> 0.00026796778 | I7: =+Bioacem!I10 -> -60.913 | J7: =+Bioacem!J10 -> 145.79 | K7: =IF(I7=0,0,I7/Bioacem!E10) -> -0.010911126 | L7: =J7/Bioacem!$E$38 -> 0.0011975489 | N7: =+'G. Extra'!I10 -> -82.68 | O7: =+'G. Extra'!J10 -> -28.73 | P7: =IF(N7=0,0,N7/'G. Extra'!E10) -> -0.27522386 | Q7: =+O7/'G. Extra'!$E$38 -> -0.0024647235 | S7: =+'G. Corriente'!F10 -> 2800 | T7: =+Bioacem!F10 -> 5800 | U7: =+'G. Extra'!F10 -> 0
B8: 5 | C8: M | D8: =+'G. Corriente'!I11 -> -89.321 | E8: =+'G. Corriente'!J11 -> -61.1 | F8: =IF(D8=0,0,D8/'G. Corriente'!E11) -> -0.06398765 | G8: =+E8/'G. Corriente'!$E$38 -> -0.00058016482 | I8: =+Bioacem!I11 -> -5.59 | J8: =+Bioacem!J11 -> 140.2 | K8: =IF(I8=0,0,I8/Bioacem!E11) -> -0.00098739525 | L8: =J8/Bioacem!$E$38 -> 0.0011516315 | N8: =+'G. Extra'!I11 -> -34.109 | O8: =+'G. Extra'!J11 -> -62.839 | P8: =IF(N8=0,0,N8/'G. Extra'!E11) -> -0.39565016 | Q8: =+O8/'G. Extra'!$E$38 -> -0.005390907 | S8: =+'G. Corriente'!F11 -> 2800 | T8: =+Bioacem!F11 -> 3500 | U8: =+'G. Extra'!F11 -> 1800
B9: 6 | C9: J | D9: =+'G. Corriente'!I12 -> -55.769 | E9: =+'G. Corriente'!J12 -> -116.869 | F9: =IF(D9=0,0,D9/'G. Corriente'!E12) -> -0.014496713 | G9: =+E9/'G. Corriente'!$E$38 -> -0.00110971 | I9: =+Bioacem!I12 -> -254.674 | J9: =+Bioacem!J12 -> -114.474 | K9: =IF(I9=0,0,I9/Bioacem!E12) -> -0.057310218 | L9: =J9/Bioacem!$E$38 -> -0.00094031288 | N9: =+'G. Extra'!I12 -> 83.699 | O9: =+'G. Extra'!J12 -> 20.86 | P9: =IF(N9=0,0,N9/'G. Extra'!E12) -> 0.25276016 | Q9: =+O9/'G. Extra'!$E$38 -> 0.0017895625 | S9: =+'G. Corriente'!F12 -> 4600 | T9: =+Bioacem!F12 -> 8700 | U9: =+'G. Extra'!F12 -> 0
B10: 7 | C10: V | D10: =+'G. Corriente'!I13 -> 6.509 | E10: =+'G. Corriente'!J13 -> -110.36 | F10: =IF(D10=0,0,D10/'G. Corriente'!E13) -> 0.00134875 | G10: =+E10/'G. Corriente'!$E$38 -> -0.0010479049 | I10: =+Bioacem!I13 -> 361.582 | J10: =+Bioacem!J13 -> 247.108 | K10: =IF(I10=0,0,I10/Bioacem!E13) -> 0.086112275 | L10: =J10/Bioacem!$E$38 -> 0.0020297957 | N10: =+'G. Extra'!I13 -> -10.02 | O10: =+'G. Extra'!J13 -> 10.84 | P10: =IF(N10=0,0,N10/'G. Extra'!E13) -> -0.015218943 | Q10: =+O10/'G. Extra'!$E$38 -> 0.00092995484 | S10: =+'G. Corriente'!F13 -> 4600 | T10: =+Bioacem!F13 -> 3500 | U10: =+'G. Extra'!F13 -> 0
B11: 8 | C11: S | D11: =+'G. Corriente'!I14 -> 204.03 | E11: =+'G. Corriente'!J14 -> 93.67 | F11: =IF(D11=0,0,D11/'G. Corriente'!E14) -> 0.046122754 | G11: =+E11/'G. Corriente'!$E$38 -> 0.0008894278 | I11: =+Bioacem!I14 -> 211.9 | J11: =+Bioacem!J14 -> 459.008 | K11: =IF(I11=0,0,I11/Bioacem!E14) -> 0.11951292 | L11: =J11/Bioacem!$E$38 -> 0.0037703857 | N11: =+'G. Extra'!I14 -> 32.27 | O11: =+'G. Extra'!J14 -> 43.11 | P11: =IF(N11=0,0,N11/'G. Extra'!E14) -> 0.078133701 | Q11: =+O11/'G. Extra'!$E$38 -> 0.0036983721 | S11: =+'G. Corriente'!F14 -> 0 | T11: =+Bioacem!F14 -> 0 | U11: =+'G. Extra'!F14 -> 0
B12: 9 | C12: D | D12: =+'G. Corriente'!I15 -> -61.789 | E12: =+'G. Corriente'!J15 -> 31.881 | F12: =IF(D12=0,0,D12/'G. Corriente'!E15) -> -0.019195509 | G12: =+E12/'G. Corriente'!$E$38 -> 0.0003027207 | I12: =+Bioacem!I15 -> -176.664 | J12: =+Bioacem!J15 -> 282.344 | K12: =IF(I12=0,0,I12/Bioacem!E15) -> -0.035966091 | L12: =J12/Bioacem!$E$38 -> 0.0023192314 | N12: =+'G. Extra'!I15 -> 23.71 | O12: =+'G. Extra'!J15 -> 66.82 | P12: =IF(N12=0,0,N12/'G. Extra'!E15) -> 0.081727621 | Q12: =+O12/'G. Extra'!$E$38 -> 0.0057324338 | S12: =+'G. Corriente'!F15 -> 4600 | T12: =+Bioacem!F15 -> 4000 | U12: =+'G. Extra'!F15 -> 0
B13: 10 | C13: L | D13: =+'G. Corriente'!I16 -> -30.731 | E13: =+'G. Corriente'!J16 -> 1.15 | F13: =IF(D13=0,0,D13/'G. Corriente'!E16) -> -0.0095829241 | G13: =+E13/'G. Corriente'!$E$38 -> 1.0919632e-05 | I13: =+Bioacem!I16 -> 9.178 | J13: =+Bioacem!J16 -> 291.522 | K13: =IF(I13=0,0,I13/Bioacem!E16) -> 0.0017542418 | L13: =J13/Bioacem!$E$38 -> 0.0023946214 | N13: =+'G. Extra'!I16 -> -58.22 | O13: =+'G. Extra'!J16 -> 8.6 | P13: =IF(N13=0,0,N13/'G. Extra'!E16) -> -0.20098733 | Q13: =+O13/'G. Extra'!$E$38 -> 0.00073778705 | S13: =+'G. Corriente'!F16 -> 3700 | T13: =+Bioacem!F16 -> 5200 | U13: =+'G. Extra'!F16 -> 1500
B14: 11 | C14: M | D14: =+'G. Corriente'!I17 -> 2.931 | E14: =+'G. Corriente'!J17 -> 4.081 | F14: =IF(D14=0,0,D14/'G. Corriente'!E17) -> 0.00088312659 | G14: =+E14/'G. Corriente'!$E$38 -> 3.8750452e-05 | I14: =+Bioacem!I17 -> -10.278 | J14: =+Bioacem!J17 -> 281.244 | K14: =IF(I14=0,0,I14/Bioacem!E17) -> -0.0020951651 | L14: =J14/Bioacem!$E$38 -> 0.0023101958 | N14: =+'G. Extra'!I17 -> -18.139 | O14: =+'G. Extra'!J17 -> -9.539 | P14: =IF(N14=0,0,N14/'G. Extra'!E17) -> -0.055003336 | Q14: =+O14/'G. Extra'!$E$38 -> -0.0008183431 | S14: =+'G. Corriente'!F17 -> 1800 | T14: =+Bioacem!F17 -> 6800 | U14: =+'G. Extra'!F17 -> 0
B15: 12 | C15: M | D15: =+'G. Corriente'!I18 -> 2.469 | E15: =+'G. Corriente'!J18 -> 6.55 | F15: =IF(D15=0,0,D15/'G. Corriente'!E18) -> 0.00075684424 | G15: =+E15/'G. Corriente'!$E$38 -> 6.2194428e-05 | I15: =+Bioacem!I18 -> 44.277 | J15: =+Bioacem!J18 -> 325.521 | K15: =IF(I15=0,0,I15/Bioacem!E18) -> 0.0086658264 | L15: =J15/Bioacem!$E$38 -> 0.0026738962 | N15: =+'G. Extra'!I18 -> 42.719 | O15: =+'G. Extra'!J18 -> 33.18 | P15: =IF(N15=0,0,N15/'G. Extra'!E18) -> 0.14096819 | Q15: =+O15/'G. Extra'!$E$38 -> 0.0028464854 | S15: =+'G. Corriente'!F18 -> 4000 | T15: =+Bioacem!F18 -> 4600 | U15: =+'G. Extra'!F18 -> 0
... B34: 31 | C34: L | D34: =+'G. Corriente'!I37 -> 0 | E34: =+'G. Corriente'!J37 -> -68.31 | F34: =IF(D34=0,0,D34/'G. Corriente'!E37) -> 0 | G34: =+E34/'G. Corriente'!$E$38 -> -0.00064862617 | I34: =+Bioacem!I37 -> 0 | J34: =+Bioacem!J37 -> 480.903 | K34: =IF(I34=0,0,I34/Bioacem!E37) -> 0 | L34: =J34/Bioacem!$E$38 -> 0.0039502357 | N34: =+'G. Extra'!I37 -> 0 | O34: =+'G. Extra'!J37 -> -21.07 | P34: =IF(N34=0,0,N34/'G. Extra'!E37) -> 0 | Q34: =+O34/'G. Extra'!$E$38 -> -0.0018075783 | S34: =+'G. Corriente'!F37 -> 0 | T34: =+Bioacem!F37 -> 0 | U34: =+'G. Extra'!F37 -> 0
S35: =SUM(S4:S34) -> 104600 | T35: =SUM(T4:T34) -> 123400 | U35: =SUM(U4:U34) -> 12300
S36: =+S35+T35+U35 -> 240300
E39: ENE | F39: FEB | G39: MAR | H39: ABR | I39: MAY | J39: JUN | K39: JUL | L39: AGO | M39: SEP | N39: OCT | O39: NOV | P39: DIC
C40: CORRIENTE | E40: -439.38 | F40: -636.51 | G40: -383.48 | H40: -450.94 | I40: -152.58 | J40: -245.67 | K40: 133.1
C41: BIOACEM | E41: 403.84 | F41: -3.72 | G41: 114.7 | H41: 64.99 | I41: 179.03 | J41: 173.61 | K41: 364.6
C42: EXTRA | E42: 12.36 | F42: 9.83 | G42: -14.91 | H42: 143.99 | I42: 3.05 | J42: 14.22 | K42: -67.62

Sheet Promotor
B1: TERPEL
B2: EDS LA FLORIDA
B3: Ventas y Fidelización
D6: SAMUEL MORENO/SANTIAGO LEON | J6: YEISON FLOREZ | P6: JHONATAN PADILLA | V6: MARIA CAROLINA MEJIA | AB6: SANDRA YEPEZ | AH6: LEONARDO SERPA | AN6: YADIRA CRUZ | AT6: MARIBEL GAMEZ | AZ6: ANGELA HERREÑO | BF6: LIZETH ORJUELA | BL6: ANGIE RUIZ/CAMILO SANCHEZ | BR6: JOSE DUARTE | BX6: VALENTINA COSSIO /DANIEL ARGEL
D7: T1 | E7: T2 | F7: T3 | G7: T4 | H7: No VEH | I7: ISLA | J7: T1 | K7: T2 | L7: T3 | M7: T4 | N7: No VEH | O7: ISLA | P7: T1 | Q7: T2 | R7: T3 | S7: T4 | T7: No VEH | U7: ISLA | V7: T1 | W7: T2 | X7: T3 | Y7: T4 | Z7: No VEH | AA7: ISLA | AB7: T1 | AC7: T2 | AD7: T3 | AE7: T4 | AF7: No VEH | AG7: ISLA | AH7: T1 | AI7: T2 | AJ7: T3 | AK7: T4 | AL7: No VEH | AM7: ISLA | AN7: T1 | AO7: T2 | AP7: T3 | AQ7: T4 | AR7: No VEH | AS7: ISLA | AT7: T1 | AU7: T2 | AV7: T3 | AW7: T4 | AX7: No VEH | AY7: ISLA | AZ7: T1 | BA7: T2 | BB7: T3 | BC7: T4 | BD7: No VEH | BE7: ISLA | BF7: T1 | BG7: T2 | BH7: T3 | BI7: T4 | BJ7: No VEH | BK7: ISLA | BL7: T1 | BM7: T2 | BN7: T3 | BO7: T4 | BP7: No VEH | BQ7: ISLA | BR7: T1 | BS7: T2 | BT7: T3 | BU7: T4 | BV7: No VEH | BW7: ISLA | BX7: T1 | BY7: T2 | BZ7: T3 | CA7: T4 | CB7: No VEH | CC7: ISLA | CD7: TURNO 1 | CE7: TURNO 2 | CF7: TURNO 3 | CG7: VTAS X PROM | CH7: VTAS | CI7: # CLIENTES
B8: 1 | C8: =+Bioacem!C7 -> D | E8: 664.069 | H8: =89+33+3+2+2 -> 129 | I8: 2 | L8: 396.908 | N8: =52+24+2+1+1 -> 80 | O8: 2 Y 3 | P8: 1041.044 | T8: =117+107+2 -> 226 | U8: 4 | W8: 631.484 | Z8: =76+47+6+1 -> 130 | AA8: 2 | AC8: 583.764 | AF8: =50+34+4+1+1+2 -> 92 | AG8: 3 | AK8: 229.988 | AL8: =27+19+1 -> 47 | AM8: 4 | AP8: 542.997 | AR8: =65+30+1+1+1 -> 98 | AS8: 1 | AZ8: 543.904 | BD8: =46+39+1+3 -> 89 | BE8: 3 | BL8: 254.137 | BP8: =32+23+1+1 -> 57 | BQ8: 3 | BT8: 263.479 | BV8: =33+14+2 -> 49 | BW8: 1 | BX8: 1000.418 | CB8: =101+102+2+2+1+1+1 -> 210 | CC8: 2 | CD8: =+BR8+BL8+BF8+AZ8+AT8+AN8+AH8+AB8+V8+P8+J8+D8+BX8 -> 2839.503 | CE8: =+BS8+BM8+BG8+BA8+AU8+AO8+AI8+AC8+W8+Q8+K8+E8+BY8 -> 1879.317 | CF8: =+BT8+BN8+BH8+BB8+AV8+AP8+AJ8+AD8+X8+R8+L8+F8+BZ8 -> 1203.384 | CG8: =+D8+F8+J8+L8+P8+R8+V8+X8+AB8+AD8+AH8+AJ8+AN8+AP8+AT8+AV8+AZ8+BB8+BF8+BH8+BR8+BT8+BN8+BL8+E8+K8+Q8+W8+AC8+AI8+AO8+AU8+BA8+BG8+BM8+BS8+G8+M8+S8+Y8+AE8+AK8+AQ8+AW8+BC8+BI8+BO8+BU8+BX8+BY8+BZ8+CA8 -> 6152.192 | CH8: =+Cierre!H3 -> 6152.2 | CI8: =+H8+N8+T8+Z8+AF8+AL8+AR8+AX8+BD8+BJ8+BV8+BP8+CB8 -> 1207 | CJ8: =+Cierre!I3 -> 1207
B9: 2 | C9: =+Bioacem!C8 -> L | F9: 587.444 | H9: =26+13+4+1 -> 44 | I9: 2 Y 3 | L9: 365.149 | N9: =36+19+2+1+1+1 -> 60 | O9: 1 | Q9: 364.805 | T9: =15+19+2+2+1 -> 39 | U9: 3 | AC9: 635.822 | AF9: =62+55+5+4+4+2 -> 132 | AG9: 2 | AH9: 718.713 | AL9: =32+38+11+3+1+1 -> 86 | AM9: 3 | AN9: 969.362 | AR9: =36+12+8+5+5+1 -> 67 | AS9: 3 | AU9: 1150.12 | AX9: =85+74+3+9+6+3+2 -> 182 | AY9: 1 | AZ9: 810.433 | BD9: =107+67+5+4+3+3+2 -> 191 | BE9: 3 | BL9: 1089.413 | BP9: =115+82+6+5+4+2+2 -> 216 | BQ9: 1 | BT9: 906.052 | BV9: =49+81+3+3+2+4 -> 142 | BW9: 1 | CA9: 688.941 | CB9: =29+8+11+4+2+11+1 -> 66 | CC9: 4 | CD9: =+BR9+BL9+BF9+AZ9+AT9+AN9+AH9+AB9+V9+P9+J9+D9+BX9 -> 3587.921 | CE9: =+BS9+BM9+BG9+BA9+AU9+AO9+AI9+AC9+W9+Q9+K9+E9+BY9 -> 2150.747 | CF9: =+BT9+BN9+BH9+BB9+AV9+AP9+AJ9+AD9+X9+R9+L9+F9+BZ9 -> 1858.645 | CG9: =+D9+F9+J9+L9+P9+R9+V9+X9+AB9+AD9+AH9+AJ9+AN9+AP9+AT9+AV9+AZ9+BB9+BF9+BH9+BR9+BT9+BN9+BL9+E9+K9+Q9+W9+AC9+AI9+AO9+AU9+BA9+BG9+BM9+BS9+G9+M9+S9+Y9+AE9+AK9+AQ9+AW9+BC9+BI9+BO9+BU9+BX9+BY9+BZ9+CA9 -> 8286.254 | CH9: =+Cierre!H4 -> 8286.29 | CI9: =+H9+N9+T9+Z9+AF9+AL9+AR9+AX9+BD9+BJ9+BV9+BP9+CB9 -> 1225 | CJ9: =+Cierre!I4 -> 1225
B10: 3 | C10: =+Bioacem!C9 -> M | F10: 951.285 | H10: =89+14+1+6+2+3 -> 115 | I10: 1 | J10: 997.882 | N10: =28+12+45+2+7+2+1+1 -> 98 | O10: 1 | P10: 125.179 | T10: =6+10+2+1+1 -> 20 | U10: 4 | W10: 757.185 | Z10: =64+61+3+1+1+1+1+1+1 -> 134 | AA10: 3 | AH10: 973.694 | AL10: =137+89+4+4+4+3+1+1 -> 243 | AM10: 2 | AN10: 1187.34 | AR10: =40+28+19+7+4+2+1 -> 101 | AS10: 3 | BA10: 837.843 | BD10: =81+53+5+5+3+2+1+1 -> 151 | BE10: 2 | BI10: 232.556 | BJ10: =20+12+1+1+1 -> 35 | BK10: 4 | BN10: 653.358 | BP10: =24+18+7+2+1 -> 52 | BQ10: 2 Y 3 | BT10: 575.564 | BV10: =55+22+3+2+3+2 -> 87 | BW10: 1 | BX10: 1138.875 | CB10: =128+67+10+5+4+3+2+1 -> 220 | CC10: 1 | CD10: =+BR10+BL10+BF10+AZ10+AT10+AN10+AH10+AB10+V10+P10+J10+D10+BX10 -> 4422.97 | CE10: =+BS10+BM10+BG10+BA10+AU10+AO10+AI10+AC10+W10+Q10+K10+E10+BY10 -> 1595.028 | CF10: =+BT10+BN10+BH10+BB10+AV10+AP10+AJ10+AD10+X10+R10+L10+F10+BZ10 -> 2180.207 | CG10: =+D10+F10+J10+L10+P10+R10+V10+X10+AB10+AD10+AH10+AJ10+AN10+AP10+AT10+AV10+AZ10+BB10+BF10+BH10+BR10+BT10+BN10+BL10+E10+K10+Q10+W10+AC10+AI10+AO10+AU10+BA10+BG10+BM10+BS10+G10+M10+S10+Y10+AE10+AK10+AQ10+AW10+BC10+BI10+BO10+BU10+BX10+BY10+BZ10+CA10 -> 8430.761 | CH10: =+Cierre!H5 -> 8430.76 | CI10: =+H10+N10+T10+Z10+AF10+AL10+AR10+AX10+BD10+BJ10+BV10+BP10+CB10 -> 1256 | CJ10: =+Cierre!I5 -> 1256
B11: 4 | C11: =+Bioacem!C10 -> M | F11: 506.957 | H11: =80+1+4+1 -> 86 | I11: 1 | J11: 1532.495 | N11: =67+40+4+8+4+23+6 -> 152 | O11: 3 | R11: 548.348 | T11: =43+26+2 -> 71 | U11: 2 Y 3 | V11: 1139.173 | Z11: =105+82+8+6+4+3+2+1 -> 211 | AA11: 1 | AI11: 1001.202 | AL11: =24+30+10+6+4 -> 74 | AM11: 3 | BA11: 956.563 | BD11: =78+57+6+4+3+3+1 -> 152 | BE11: 1 | BI11: 102.999 | BJ11: =12+5+1+1 -> 19 | BK11: 4 | BN11: 785.312 | BP11: =45+24+3+1+5 -> 78 | BQ11: 2 Y 3 | BS11: 979.38 | BV11: =88+64+7+3+2+2+1 -> 167 | BW11: 2 | BX11: 1189.022 | CB11: =3+118+64+6+5+4+2+1 -> 203 | CC11: 2 | CD11: =+BR11+BL11+BF11+AZ11+AT11+AN11+AH11+AB11+V11+P11+J11+D11+BX11 -> 3860.69 | CE11: =+BS11+BM11+BG11+BA11+AU11+AO11+AI11+AC11+W11+Q11+K11+E11+BY11 -> 2937.145 | CF11: =+BT11+BN11+BH11+BB11+AV11+AP11+AJ11+AD11+X11+R11+L11+F11+BZ11 -> 1840.617 | CG11: =+D11+F11+J11+L11+P11+R11+V11+X11+AB11+AD11+AH11+AJ11+AN11+AP11+AT11+AV11+AZ11+BB11+BF11+BH11+BR11+BT11+BN11+BL11+E11+K11+Q11+W11+AC11+AI11+AO11+AU11+BA11+BG11+BM11+BS11+G11+M11+S11+Y11+AE11+AK11+AQ11+AW11+BC11+BI11+BO11+BU11+BX11+BY11+BZ11+CA11 -> 8741.451 | CH11: =+Cierre!H6 -> 8741.44 | CI11: =+H11+N11+T11+Z11+AF11+AL11+AR11+AX11+BD11+BJ11+BV11+BP11+CB11 -> 1213 | CJ11: =+Cierre!I6 -> 1213
B12: 5 | C12: =+Bioacem!C11 -> J | F12: 646.38 | H12: =88+3+3+2+2 -> 98 | I12: 1 | J12: 966.464 | N12: =70+37+7+8+4+1+2 -> 129 | O12: 1 | R12: 1279.422 | T12: =57+38+5+4+1+7+1 -> 113 | U12: 2 | V12: 1469.508 | Z12: =40+19+9+21+5 -> 94 | AA12: 3 | AB12: 426.128 | AF12: =11+32+3+2+4 -> 52 | AG12: 2 | AO12: 626.279 | AR12: =33+27+4+4+2+1 -> 71 | AS12: 2 | BB12: 575.862 | BD12: =13+6+8+5+1 -> 33 | BE12: 3 | BI12: 9.875 | BJ12: 1 | BK12: 4 | BS12: 911.298 | BV12: =66+28+9+4+2+1+1+1 -> 112 | BW12: 1 | BZ12: 232.269 | CB12: =11+2+16+1+1 -> 31 | CC12: 2 Y 3 | CD12: =+BR12+BL12+BF12+AZ12+AT12+AN12+AH12+AB12+V12+P12+J12+D12+BX12 -> 2862.1 | CE12: =+BS12+BM12+BG12+BA12+AU12+AO12+AI12+AC12+W12+Q12+K12+E12+BY12 -> 1537.577 | CF12: =+BT12+BN12+BH12+BB12+AV12+AP12+AJ12+AD12+X12+R12+L12+F12+BZ12 -> 2733.933 | CG12: =+D12+F12+J12+L12+P12+R12+V12+X12+AB12+AD12+AH12+AJ12+AN12+AP12+AT12+AV12+AZ12+BB12+BF12+BH12+BR12+BT12+BN12+BL12+E12+K12+Q12+W12+AC12+AI12+AO12+AU12+BA12+BG12+BM12+BS12+G12+M12+S12+Y12+AE12+AK12+AQ12+AW12+BC12+BI12+BO12+BU12+BX12+BY12+BZ12+CA12 -> 7143.485 | CH12: =+Cierre!H7 -> 7143.48 | CI12: =+H12+N12+T12+Z12+AF12+AL12+AR12+AX12+BD12+BJ12+BV12+BP12+CB12 -> 734 | CJ12: =+Cierre!I7 -> 734
B13: 6 | C13: =+Bioacem!C12 -> V | E13: 977.56 | H13: =201+6+6+2+2+1+1 -> 219 | I13: 2 | L13: 610.176 | N13: =45+44+2+4+1 -> 96 | O13: 2 Y 3 | R13: 464.238 | T13: =38+18+3+1+1 -> 61 | U13: 1 | V13: 1087.67 | Z13: =1+124+83+4+6+3+2+2 -> 225 | AA13: 2 | AC13: 1031.64 | AF13: =92+76+18+4+3+1+1 -> 195 | AG13: 3 | AH13: 1239.403 | AL13: =130+78+8+5+4+3+3+1 -> 232 | AM13: 1 | BC13: 111.634 | BD13: =14+8+1+1 -> 24 | BE13: 4 | BO13: 1020.487 | BP13: =51+38+7+9+6+1 -> 112 | BQ13: 4 | BR13: 1441.223 | BV13: =55+45+25+10+5+2 -> 142 | BW13: 3 | BZ13: 637.867 | CB13: =74+44+2+2+1+2+5+1 -> 131 | CC13: 1 | CD13: =+BR13+BL13+BF13+AZ13+AT13+AN13+AH13+AB13+V13+P13+J13+D13+BX13 -> 3768.296 | CE13: =+BS13+BM13+BG13+BA13+AU13+AO13+AI13+AC13+W13+Q13+K13+E13+BY13 -> 2009.2 | CF13: =+BT13+BN13+BH13+BB13+AV13+AP13+AJ13+AD13+X13+R13+L13+F13+BZ13 -> 1712.281 | CG13: =+D13+F13+J13+L13+P13+R13+V13+X13+AB13+AD13+AH13+AJ13+AN13+AP13+AT13+AV13+AZ13+BB13+BF13+BH13+BR13+BT13+BN13+BL13+E13+K13+Q13+W13+AC13+AI13+AO13+AU13+BA13+BG13+BM13+BS13+G13+M13+S13+Y13+AE13+AK13+AQ13+AW13+BC13+BI13+BO13+BU13+BX13+BY13+BZ13+CA13 -> 8621.898 | CH13: =+Cierre!H8 -> 8621.93 | CI13: =+H13+N13+T13+Z13+AF13+AL13+AR13+AX13+BD13+BJ13+BV13+BP13+CB13 -> 1437 | CJ13: =+Cierre!I8 -> 1437
B14: 7 | C14: =+Bioacem!C13 -> S | D14: 564.576 | H14: =27+19+1+1+1 -> 49 | I14: 3 | L14: 1237.08 | N14: =83+54+1+2+1+3+1 -> 145 | O14: 2 Y 3 | Q14: 915.194 | T14: =75+94+9+1+1 -> 180 | U14: 2 | W14: 763.461 | Z14: =36+27+1+3+1+5+1 -> 74 | AA14: 3 | AB14: 1376.027 | AF14: =149+122+3+3+2+1+1 -> 281 | AG14: 2 | AI14: 925.242 | AL14: =92+80+3+1+1+1 -> 178 | AM14: 1 | AU14: 653.427 | AX14: =26+23+1+9 -> 59 | AY14: 3 | AZ14: 1405.595 | BD14: =131+124+2+2+2+1 -> 262 | BE14: 1 | BI14: 143.705 | BJ14: =12+6+2 -> 20 | BK14: 4 | BN14: 262.274 | BP14: =28+16+7 -> 51 | BQ14: 1 | BR14: 916.823 | BV14: =34+38+7+4+3+3+1 -> 90 | BW14: 3 | BZ14: 519.842 | CB14: =50+27+3+2+1+1 -> 84 | CC14: 1 | CD14: =+BR14+BL14+BF14+AZ14+AT14+AN14+AH14+AB14+V14+P14+J14+D14+BX14 -> 4263.021 | CE14: =+BS14+BM14+BG14+BA14+AU14+AO14+AI14+AC14+W14+Q14+K14+E14+BY14 -> 3257.324 | CF14: =+BT14+BN14+BH14+BB14+AV14+AP14+AJ14+AD14+X14+R14+L14+F14+BZ14 -> 2019.196 | CG14: =+D14+F14+J14+L14+P14+R14+V14+X14+AB14+AD14+AH14+AJ14+AN14+AP14+AT14+AV14+AZ14+BB14+BF14+BH14+BR14+BT14+BN14+BL14+E14+K14+Q14+W14+AC14+AI14+AO14+AU14+BA14+BG14+BM14+BS14+G14+M14+S14+Y14+AE14+AK14+AQ14+AW14+BC14+BI14+BO14+BU14+BX14+BY14+BZ14+CA14 -> 9683.246 | CH14: =+Cierre!H9 -> 9683.3 | CI14: =+H14+N14+T14+Z14+AF14+AL14+AR14+AX14+BD14+BJ14+BV14+BP14+CB14 -> 1473 | CJ14: =+Cierre!I9 -> 1473
B15: 8 | C15: =+Bioacem!C14 -> D | D15: 1026.799 | H15: =195+33+2 -> 230 | I15: 1 | L15: 335.183 | N15: =24+6+1+1+1 -> 33 | O15: 2 Y 3 | Q15: 742.279 | T15: =91+58+4 -> 153 | U15: 1 | W15: 893.774 | Z15: =104+93+3+3+1 -> 204 | AA15: 2 | AH15: 1222.77 | AL15: =124+98+11+4+1+1 -> 239 | AM15: 2 | AU15: 321.268 | AX15: =29+20+2+1+1 -> 53 | AY15: 3 | BN15: 541.094 | BP15: =61+42+1+1 -> 105 | BQ15: 1 | BT15: 469.014 | BV15: =26+22+2+1+3 -> 54 | BW15: 2 Y 3 | BX15: 1057.452 | CB15: =89+80+3+1+1+3 -> 177 | CC15: 3 | CD15: =+BR15+BL15+BF15+AZ15+AT15+AN15+AH15+AB15+V15+P15+J15+D15+BX15 -> 3307.021 | CE15: =+BS15+BM15+BG15+BA15+AU15+AO15+AI15+AC15+W15+Q15+K15+E15+BY15 -> 1957.321 | CF15: =+BT15+BN15+BH15+BB15+AV15+AP15+AJ15+AD15+X15+R15+L15+F15+BZ15 -> 1345.291 | CG15: =+D15+F15+J15+L15+P15+R15+V15+X15+AB15+AD15+AH15+AJ15+AN15+AP15+AT15+AV15+AZ15+BB15+BF15+BH15+BR15+BT15+BN15+BL15+E15+K15+Q15+W15+AC15+AI15+AO15+AU15+BA15+BG15+BM15+BS15+G15+M15+S15+Y15+AE15+AK15+AQ15+AW15+BC15+BI15+BO15+BU15+BX15+BY15+BZ15+CA15 -> 6609.633 | CH15: =+Cierre!H10 -> 6609.67 | CI15: =+H15+N15+T15+Z15+AF15+AL15+AR15+AX15+BD15+BJ15+BV15+BP15+CB15 -> 1248 | CJ15: =+Cierre!I10 -> 1248
B16: 9 | C16: =+Bioacem!C15 -> L | K16: 798.948 | N16: =88+63+6+1+2+6+4+3 -> 173 | O16: 2 | Q16: 985.291 | T16: =50+39+3+7+4+2 -> 105 | U16: 3 | V16: 1617.666 | Z16: =49+42+25+6+6+1 -> 129 | AA16: 3 | AC16: 678.833 | AF16: =74+54+5+5+2+2 -> 142 | AG16: 2 | AH16: 1307.791 | AL16: =151+79+7+5+3+3+2 -> 250 | AM16: 1 | AV16: 363.174 | AX16: =30+18+2+1+1 -> 52 | AY16: 2 Y 3 | AZ16: 1043.501 | BD16: =122+74+9+7+6+2 -> 220 | BE16: 2 | BI16: 241.035 | BJ16: =32+5+1+1+1 -> 40 | BK16: 4 | BN16: 538.685 | BP16: =45+23+2+1+1 -> 72 | BQ16: 1 | BT16: 846.036 | BV16: =60+45+4+4+4+1+4 -> 122 | BW16: 1 | CD16: =+BR16+BL16+BF16+AZ16+AT16+AN16+AH16+AB16+V16+P16+J16+D16+BX16 -> 3968.958 | CE16: =+BS16+BM16+BG16+BA16+AU16+AO16+AI16+AC16+W16+Q16+K16+E16+BY16 -> 2463.072 | CF16: =+BT16+BN16+BH16+BB16+AV16+AP16+AJ16+AD16+X16+R16+L16+F16+BZ16 -> 1747.895 | CG16: =+D16+F16+J16+L16+P16+R16+V16+X16+AB16+AD16+AH16+AJ16+AN16+AP16+AT16+AV16+AZ16+BB16+BF16+BH16+BR16+BT16+BN16+BL16+E16+K16+Q16+W16+AC16+AI16+AO16+AU16+BA16+BG16+BM16+BS16+G16+M16+S16+Y16+AE16+AK16+AQ16+AW16+BC16+BI16+BO16+BU16+BX16+BY16+BZ16+CA16 -> 8420.96 | CH16: =+Cierre!H11 -> 8421 | CI16: =+H16+N16+T16+Z16+AF16+AL16+AR16+AX16+BD16+BJ16+BV16+BP16+CB16 -> 1305 | CJ16: =+Cierre!I11 -> 1305
B17: 10 | C17: =+Bioacem!C16 -> M | D17: 1327.782 | H17: =43+31+21+5+5+1+1+1+1 -> 109 | I17: 3 | P17: 1331.272 | T17: =143+93+8+6+5+3+2+2 -> 262 | U17: 2 | V17: 1264.846 | Z17: =125+85+10+8+2+1+1+1 -> 233 | AA17: 1 | AC17: 795.125 | AF17: =87+62+5+4+3+2+2 -> 165 | AG17: 2 | AJ17: 358.603 | AL17: =18+24+3+2+1+1 -> 49 | AM17: 2 Y 3 | AV17: 906.012 | AX17: =46+79+2+2+4 -> 133 | AY17: 1 | BC17: 85.634 | BD17: =9+10+2 -> 21 | BE17: 4 | BM17: 1177.29 | BP17: =42+26+7+13+2+2+1 -> 93 | BQ17: 3 | BT17: 568.234 | BV17: =44+21+3+3+1+1 -> 73 | BW17: 1 | BY17: 913.563 | CB17: =79+75+4+3+3+3+1+1 -> 169 | CC17: 1 | CD17: =+BR17+BL17+BF17+AZ17+AT17+AN17+AH17+AB17+V17+P17+J17+D17+BX17 -> 3923.9 | CE17: =+BS17+BM17+BG17+BA17+AU17+AO17+AI17+AC17+W17+Q17+K17+E17+BY17 -> 2885.978 | CF17: =+BT17+BN17+BH17+BB17+AV17+AP17+AJ17+AD17+X17+R17+L17+F17+BZ17 -> 1832.849 | CG17: =+D17+F17+J17+L17+P17+R17+V17+X17+AB17+AD17+AH17+AJ17+AN17+AP17+AT17+AV17+AZ17+BB17+BF17+BH17+BR17+BT17+BN17+BL17+E17+K17+Q17+W17+AC17+AI17+AO17+AU17+BA17+BG17+BM17+BS17+G17+M17+S17+Y17+AE17+AK17+AQ17+AW17+BC17+BI17+BO17+BU17+BX17+BY17+BZ17+CA17 -> 8728.361 | CH17: =+Cierre!H12 -> 8728.41 | CI17: =+H17+N17+T17+Z17+AF17+AL17+AR17+AX17+BD17+BJ17+BV17+BP17+CB17 -> 1307 | CJ17: =+Cierre!I12 -> 1307
B18: 11 | C18: =+Bioacem!C17 -> M | D18: 1107.197 | H18: =160+48+3+3+2+1 -> 217 | I18: 1 | M18: 210.392 | N18: =25+19+2+1 -> 47 | O18: 4 | P18: 673.074 | T18: =48+19+11+5+3+2+1 -> 89 | U18: 3 | V18: 1227.698 | Z18: =137+82+3+5+4+2+2+1 -> 236 | AA18: 2 | AD18: 175.494 | AF18: =20+17+1 -> 38 | AG18: 2 Y 3 | AJ18: 810.515 | AL18: =47+82+4+3+1+3+1 -> 141 | AM18: 2 Y 3 | AO18: 1039.207 | AR18: =34+30+1+11+2+1 -> 79 | AS18: 3 | AT18: 727.739 | AX18: =53+17+5+2+2 -> 79 | AY18: 3 | BC18: 240.157 | BD18: =10+3+3+1 -> 17 | BE18: 4 | BL18: 557.807 | BP18: =18+9+7+5+3 -> 42 | BQ18: 3 | BS18: 1029.753 | BV18: =98+75+5+5+2+3+1+2 -> 191 | BW18: 1 | BY18: 755.18 | CB18: =76+58+8+5+3+4+3 -> 157 | CC18: 2 | CD18: =+BR18+BL18+BF18+AZ18+AT18+AN18+AH18+AB18+V18+P18+J18+D18+BX18 -> 4293.515 | CE18: =+BS18+BM18+BG18+BA18+AU18+AO18+AI18+AC18+W18+Q18+K18+E18+BY18 -> 2824.14 | CF18: =+BT18+BN18+BH18+BB18+AV18+AP18+AJ18+AD18+X18+R18+L18+F18+BZ18 -> 986.009 | CG18: =+D18+F18+J18+L18+P18+R18+V18+X18+AB18+AD18+AH18+AJ18+AN18+AP18+AT18+AV18+AZ18+BB18+BF18+BH18+BR18+BT18+BN18+BL18+E18+K18+Q18+W18+AC18+AI18+AO18+AU18+BA18+BG18+BM18+BS18+G18+M18+S18+Y18+AE18+AK18+AQ18+AW18+BC18+BI18+BO18+BU18+BX18+BY18+BZ18+CA18 -> 8554.213 | CH18: =+Cierre!H13 -> 8554.25 | CI18: =+H18+N18+T18+Z18+AF18+AL18+AR18+AX18+BD18+BJ18+BV18+BP18+CB18 -> 1333 | CJ18: =+Cierre!I13 -> 1333
B19: 12 | C19: =+Bioacem!C18 -> J | D19: 600.88 | H19: =29+16+4+2+1+1 -> 53 | I19: 3 | J19: 604.442 | N19: =60+55+5+3+3+1+1 -> 128 | O19: 2 | S19: 231.871 | T19: =21+16+2+2+1 -> 42 | U19: 4 | V19: 790.834 | Z19: =26+15+5+15+6+4+1 -> 72 | AA19: 3 | AD19: 869.172 | AF19: =70+42+4+2+1+4+7 -> 130 | AG19: 1 | AJ19: 832.632 | AL19: =86+38+3+3 -> 130 | AM19: 2 Y 3 | AN19: 1203.309 | AR19: =75+83+5+4+4+3+1 -> 175 | AS19: 2 | AU19: 916.887 | AX19: =105+59+6+3+2+1+1 -> 177 | AY19: 1 | BI19: 12.825 | BJ19: 4 | BK19: 4 | BL19: 895.544 | BP19: =152+64+6+6+7+4+1 -> 240 | BQ19: 1 | BR19: 843.054 | BV19: =86+44+3+3+1+1 -> 138 | BW19: 2 | BY19: 873.185 | CB19: =35+18+9+12 -> 74 | CC19: 3 | CD19: =+BR19+BL19+BF19+AZ19+AT19+AN19+AH19+AB19+V19+P19+J19+D19+BX19 -> 4938.063 | CE19: =+BS19+BM19+BG19+BA19+AU19+AO19+AI19+AC19+W19+Q19+K19+E19+BY19 -> 1790.072 | CF19: =+BT19+BN19+BH19+BB19+AV19+AP19+AJ19+AD19+X19+R19+L19+F19+BZ19 -> 1701.804 | CG19: =+D19+F19+J19+L19+P19+R19+V19+X19+AB19+AD19+AH19+AJ19+AN19+AP19+AT19+AV19+AZ19+BB19+BF19+BH19+BR19+BT19+BN19+BL19+E19+K19+Q19+W19+AC19+AI19+AO19+AU19+BA19+BG19+BM19+BS19+G19+M19+S19+Y19+AE19+AK19+AQ19+AW19+BC19+BI19+BO19+BU19+BX19+BY19+BZ19+CA19 -> 8674.635 | CH19: =+Cierre!H14 -> 8674.65 | CI19: =+H19+N19+T19+Z19+AF19+AL19+AR19+AX19+BD19+BJ19+BV19+BP19+CB19 -> 1363 | CJ19: =+Cierre!I14 -> 1363
B20: 13 | C20: =+Bioacem!C19 -> V | D20: 795.939 | H20: =129+21+2+3+2+3 -> 160 | I20: 2 | K20: 983.861 | N20: =97+75+5+5+2+1+1 -> 186 | O20: 1 | P20: 1130.906 | T20: =121+89+7+5+4+4 -> 230 | U20: 1 | X20: 523.369 | Z20: =36+26+1+1+1 -> 65 | AA20: 2 Y 3 | AD20: 1035.311 | AF20: =88+57+1+5+1+1 -> 153 | AG20: 1 | AJ20: 550.582 | AL20: =42+4+13+6+2+1 -> 68 | AM20: 2 Y 3 | AO20: 1177.089 | AR20: =26+18+29+9+6 -> 88 | AS20: 3 | AW20: 157.865 | AX20: =15+11+1+4 -> 31 | AY20: 4 | BI20: 42.252 | BJ20: =12+1 -> 13 | BK20: 4 | BO20: 7.442 | BP20: 1 | BQ20: 4 | BU20: 1132.608 | BV20: =114+78+4+4+2+1+1 -> 204 | BW20: 4 | BX20: 1268.3 | CB20: =61+34+5+13+6+4+2 -> 125 | CC20: 3 | CD20: =+BR20+BL20+BF20+AZ20+AT20+AN20+AH20+AB20+V20+P20+J20+D20+BX20 -> 3195.145 | CE20: =+BS20+BM20+BG20+BA20+AU20+AO20+AI20+AC20+W20+Q20+K20+E20+BY20 -> 2160.95 | CF20: =+BT20+BN20+BH20+BB20+AV20+AP20+AJ20+AD20+X20+R20+L20+F20+BZ20 -> 2109.262 | CG20: =+D20+F20+J20+L20+P20+R20+V20+X20+AB20+AD20+AH20+AJ20+AN20+AP20+AT20+AV20+AZ20+BB20+BF20+BH20+BR20+BT20+BN20+BL20+E20+K20+Q20+W20+AC20+AI20+AO20+AU20+BA20+BG20+BM20+BS20+G20+M20+S20+Y20+AE20+AK20+AQ20+AW20+BC20+BI20+BO20+BU20+BX20+BY20+BZ20+CA20 -> 8805.524 | CH20: =+Cierre!H15 -> 8805.55 | CI20: =+H20+N20+T20+Z20+AF20+AL20+AR20+AX20+BD20+BJ20+BV20+BP20+CB20 -> 1324 | CJ20: =+Cierre!I15 -> 1324
B21: 14 | C21: =+Bioacem!C20 -> S | F21: 267.242 | H21: =51+13+1+1 -> 66 | I21: 2 Y 3 | K21: 1259.6 | N21: =58+41+1+13+2 -> 115 | O21: 3 | P21: 1362.848 | T21: =154+149+3+2+2+1+1+1 -> 313 | U21: 2 | X21: 984.651 | Z21: =63+84+3+2+5+2+1 -> 160 | AA21: 2 Y 3 | AD21: 559.793 | AF21: =60+34+3+2 -> 99 | AG21: 1 | AK21: 543.577 | AL21: =43+36+1+1+1 -> 82 | AM21: 4 | AN21: 1316.74 | AR21: =137+111+5+2+2+2+1 -> 260 | AS21: 1 | AU21: 856.996 | AX21: =98+82+2+1+1+1 -> 185 | AY21: 2 | BL21: 926.029 | BP21: =35+48+9+2+1+1 -> 96 | BQ21: 3 | BS21: 1109.585 | BV21: =118+88+3+2+1 -> 212 | BW21: 1 | CA21: 524.904 | CB21: =48+39+2+1+1 -> 91 | CC21: 4 | CD21: =+BR21+BL21+BF21+AZ21+AT21+AN21+AH21+AB21+V21+P21+J21+D21+BX21 -> 3605.617 | CE21: =+BS21+BM21+BG21+BA21+AU21+AO21+AI21+AC21+W21+Q21+K21+E21+BY21 -> 3226.181 | CF21: =+BT21+BN21+BH21+BB21+AV21+AP21+AJ21+AD21+X21+R21+L21+F21+BZ21 -> 1811.686 | CG21: =+D21+F21+J21+L21+P21+R21+V21+X21+AB21+AD21+AH21+AJ21+AN21+AP21+AT21+AV21+AZ21+BB21+BF21+BH21+BR21+BT21+BN21+BL21+E21+K21+Q21+W21+AC21+AI21+AO21+AU21+BA21+BG21+BM21+BS21+G21+M21+S21+Y21+AE21+AK21+AQ21+AW21+BC21+BI21+BO21+BU21+BX21+BY21+BZ21+CA21 -> 9711.965 | CH21: =+Cierre!H16 -> 9711.98 | CI21: =+H21+N21+T21+Z21+AF21+AL21+AR21+AX21+BD21+BJ21+BV21+BP21+CB21 -> 1679 | CJ21: =+Cierre!I16 -> 1679
B22: 15 | C22: =+Bioacem!C21 -> D | F22: 267.478 | H22: =37+3+1+2 -> 43 | I22: 2 Y 3 | J22: 1080.209 | N22: =115+105+2 -> 222 | O22: 1 | X22: 282.73 | Z22: =30+20+1 -> 51 | AA22: 1 | AC22: 953.107 | AF22: =83+70+2+7+1+1 -> 164 | AG22: 1 | AI22: 619.231 | AL22: =72+50+3+1 -> 126 | AM22: 1 | AT22: 882.499 | AX22: =83+66+2+4+3 -> 158 | AY22: 3 | BB22: 296.028 | BD22: =32+13+1+1 -> 47 | BE22: 2 Y 3 | BM22: 525.722 | BP22: =46+52+3+2+1 -> 104 | BQ22: 2 | BR22: 1088.962 | BV22: =107+130+3+2+1+1+1+1 -> 246 | BW22: 2 | CA22: 699.924 | CB22: =74+70+4+2+1 -> 151 | CC22: 4 | CD22: =+BR22+BL22+BF22+AZ22+AT22+AN22+AH22+AB22+V22+P22+J22+D22+BX22 -> 3051.67 | CE22: =+BS22+BM22+BG22+BA22+AU22+AO22+AI22+AC22+W22+Q22+K22+E22+BY22 -> 2098.06 | CF22: =+BT22+BN22+BH22+BB22+AV22+AP22+AJ22+AD22+X22+R22+L22+F22+BZ22 -> 846.236 | CG22: =+D22+F22+J22+L22+P22+R22+V22+X22+AB22+AD22+AH22+AJ22+AN22+AP22+AT22+AV22+AZ22+BB22+BF22+BH22+BR22+BT22+BN22+BL22+E22+K22+Q22+W22+AC22+AI22+AO22+AU22+BA22+BG22+BM22+BS22+G22+M22+S22+Y22+AE22+AK22+AQ22+AW22+BC22+BI22+BO22+BU22+BX22+BY22+BZ22+CA22 -> 6695.89 | CH22: =+Cierre!H17 -> 6695.86 | CI22: =+H22+N22+T22+Z22+AF22+AL22+AR22+AX22+BD22+BJ22+BV22+BP22+CB22 -> 1312 | CJ22: =+Cierre!I17 -> 1312
B23: 16 | C23: =+Bioacem!C22 -> L | F23: 378.295 | H23: =68+4+1+1+1+1 -> 76 | I23: 1 | M23: 137.92 | N23: =14+14+1 -> 29 | O23: 4 | W23: 1101.768 | Z23: =36+38+10+8+6 -> 98 | AA23: 3 | AD23: 578.016 | AF23: =57+24+2+1+1 -> 85 | AG23: 1 | AI23: 1015.567 | AL23: =100+66+2+6+4+3+1 -> 182 | AM23: 2 | AT23: 1637.315 | AX23: =66+35+24+8+3+3+1 -> 140 | AY23: 3 | BB23: 1270.085 | BD23: =75+38+8+2+6+3+1 -> 133 | BE23: 2 Y 3 | BM23: 740.859 | BP23: =82+61+3+3+2+2 -> 153 | BQ23: 1 | BR23: 1210.91 | BV23: =115+89+8+6+4+1+1 -> 224 | BW23: 1 | BX23: 1338.024 | CB23: =138+83+9+5+3+1+1 -> 240 | CC23: 2 | CD23: =+BR23+BL23+BF23+AZ23+AT23+AN23+AH23+AB23+V23+P23+J23+D23+BX23 -> 4186.249 | CE23: =+BS23+BM23+BG23+BA23+AU23+AO23+AI23+AC23+W23+Q23+K23+E23+BY23 -> 2858.194 | CF23: =+BT23+BN23+BH23+BB23+AV23+AP23+AJ23+AD23+X23+R23+L23+F23+BZ23 -> 2226.396 | CG23: =+D23+F23+J23+L23+P23+R23+V23+X23+AB23+AD23+AH23+AJ23+AN23+AP23+AT23+AV23+AZ23+BB23+BF23+BH23+BR23+BT23+BN23+BL23+E23+K23+Q23+W23+AC23+AI23+AO23+AU23+BA23+BG23+BM23+BS23+G23+M23+S23+Y23+AE23+AK23+AQ23+AW23+BC23+BI23+BO23+BU23+BX23+BY23+BZ23+CA23 -> 9408.759 | CH23: =+Cierre!H18 -> 9408.74 | CI23: =+H23+N23+T23+Z23+AF23+AL23+AR23+AX23+BD23+BJ23+BV23+BP23+CB23 -> 1360 | CJ23: =+Cierre!I18 -> 1360
B24: 17 | C24: =+Bioacem!C23 -> M | F24: 575.534 | H24: =79+4+6+2+1+1 -> 93 | I24: 1 | J24: 119.439 | N24: =14+14+2+1 -> 31 | O24: 4 | W24: 1117.546 | Z24: =116+83+6+5+4+2+1 -> 217 | AA24: 2 | AC24: 660.157 | AF24: =70+66+5+4+2+2+2+1 -> 152 | AG24: 1 | AJ24: 390.425 | AL24: =38+15+2+1+3+4 -> 63 | AM24: 2 Y 3 | AN24: 1307.008 | AR24: =53+32+22+8+6+5+1 -> 127 | AS24: 3 | BB24: 991.555 | BD24: =77+51+2+3+6+6 -> 145 | BE24: 1 | BM24: 1237.828 | BP24: =38+60+10+6+3+2+1 -> 120 | BQ24: 3 | BR24: 1142.81 | BV24: =131+79+2+5+4+3+1 -> 225 | BW24: 2 | BX24: 1041.826 | CB24: =138+90+9+4+3+3+2+1 -> 250 | CC24: 1 | CD24: =+BR24+BL24+BF24+AZ24+AT24+AN24+AH24+AB24+V24+P24+J24+D24+BX24 -> 3611.083 | CE24: =+BS24+BM24+BG24+BA24+AU24+AO24+AI24+AC24+W24+Q24+K24+E24+BY24 -> 3015.531 | CF24: =+BT24+BN24+BH24+BB24+AV24+AP24+AJ24+AD24+X24+R24+L24+F24+BZ24 -> 1957.514 | CG24: =+D24+F24+J24+L24+P24+R24+V24+X24+AB24+AD24+AH24+AJ24+AN24+AP24+AT24+AV24+AZ24+BB24+BF24+BH24+BR24+BT24+BN24+BL24+E24+K24+Q24+W24+AC24+AI24+AO24+AU24+BA24+BG24+BM24+BS24+G24+M24+S24+Y24+AE24+AK24+AQ24+AW24+BC24+BI24+BO24+BU24+BX24+BY24+BZ24+CA24 -> 8584.128 | CH24: =+Cierre!H19 -> 8584.15 | CI24: =+H24+N24+T24+Z24+AF24+AL24+AR24+AX24+BD24+BJ24+BV24+BP24+CB24 -> 1423 | CJ24: =+Cierre!I19 -> 1423
B25: 18 | C25: =+Bioacem!C24 -> M | D25: 1211.543 | H25: =79+13+10+5+4+1 -> 112 | I25: 3 | M25: 290.334 | N25: =36+14+1+1+1+3 -> 56 | O25: 4 | Q25: 1051.304 | T25: =83+82+7+4+3+2+1+1 -> 183 | U25: 1 | V25: 696.53 | Z25: =57+46+6+3+2+2 -> 116 | AA25: 1 | AB25: 1044.493 | AF25: =133+79+9+4+4+3+2 -> 234 | AG25: 2 | AJ25: 1106.625 | AL25: =68+46+7+1+1+4+7 -> 134 | AM25: 2 Y 3 | AN25: 458.582 | AR25: =68+61+5+1 -> 135 | AS25: 1 | BB25: 500.676 | BD25: =50+24+4+1+1+1 -> 81 | BE25: 1 | BI25: 11.935 | BJ25: 1 | BK25: 4 | BM25: 501.782 | BP25: =81+38+3+2+1 -> 125 | BQ25: 2 | BT25: 1598.953 | BV25: =80+30+5+19+7+3+2+2 -> 148 | BW25: 3 | BZ25: 334.11 | CB25: =24+15+2+4 -> 45 | CC25: 2 Y 3 | CD25: =+BR25+BL25+BF25+AZ25+AT25+AN25+AH25+AB25+V25+P25+J25+D25+BX25 -> 3411.148 | CE25: =+BS25+BM25+BG25+BA25+AU25+AO25+AI25+AC25+W25+Q25+K25+E25+BY25 -> 1553.086 | CF25: =+BT25+BN25+BH25+BB25+AV25+AP25+AJ25+AD25+X25+R25+L25+F25+BZ25 -> 3540.364 | CG25: =+D25+F25+J25+L25+P25+R25+V25+X25+AB25+AD25+AH25+AJ25+AN25+AP25+AT25+AV25+AZ25+BB25+BF25+BH25+BR25+BT25+BN25+BL25+E25+K25+Q25+W25+AC25+AI25+AO25+AU25+BA25+BG25+BM25+BS25+G25+M25+S25+Y25+AE25+AK25+AQ25+AW25+BC25+BI25+BO25+BU25+BX25+BY25+BZ25+CA25 -> 8806.867 | CH25: =+Cierre!H20 -> 8806.88 | CI25: =+H25+N25+T25+Z25+AF25+AL25+AR25+AX25+BD25+BJ25+BV25+BP25+CB25 -> 1370 | CJ25: =+Cierre!I20 -> 1370
B26: 19 | C26: =+Bioacem!C25 -> J | E26: 24.075 | H26: =6+1 -> 7 | I26: 1 | Q26: 1075.039 | T26: =96+98+4+6+7+4 -> 215 | U26: 2 | V26: 1116.052 | Z26: =166+89+5+3+7+5+2+1+1 -> 279 | AA26: 2 | AB26: 1762.339 | AF26: =49+36+29+7+4+3+3+1 -> 132 | AG26: 3 | AJ26: 387.079 | AL26: =38+13+3+1+2 -> 57 | AM26: 1 | AN26: 933.14 | AR26: =32+38+3+4+6+3 -> 86 | AS26: 2 Y 3 | AU26: 1048.027 | AX26: =69+58+6+9+2+2+1 -> 147 | AY26: 3 | BI26: 56.489 | BJ26: =8+4+1 -> 13 | BK26: 4 | BL26: 1158.579 | BP26: =144+54+12+8+7+4 -> 229 | BQ26: 1 | BR26: 287.203 | BV26: =34+14+2+1+1 -> 52 | BW26: 4 | BZ26: 753.216 | CB26: =65+37+4+3+4 -> 113 | CC26: 1 | CD26: =+BR26+BL26+BF26+AZ26+AT26+AN26+AH26+AB26+V26+P26+J26+D26+BX26 -> 5257.313 | CE26: =+BS26+BM26+BG26+BA26+AU26+AO26+AI26+AC26+W26+Q26+K26+E26+BY26 -> 2147.141 | CF26: =+BT26+BN26+BH26+BB26+AV26+AP26+AJ26+AD26+X26+R26+L26+F26+BZ26 -> 1140.295 | CG26: =+D26+F26+J26+L26+P26+R26+V26+X26+AB26+AD26+AH26+AJ26+AN26+AP26+AT26+AV26+AZ26+BB26+BF26+BH26+BR26+BT26+BN26+BL26+E26+K26+Q26+W26+AC26+AI26+AO26+AU26+BA26+BG26+BM26+BS26+G26+M26+S26+Y26+AE26+AK26+AQ26+AW26+BC26+BI26+BO26+BU26+BX26+BY26+BZ26+CA26 -> 8601.238 | CH26: =+Cierre!H21 -> 8601.27 | CI26: =+H26+N26+T26+Z26+AF26+AL26+AR26+AX26+BD26+BJ26+BV26+BP26+CB26 -> 1330 | CJ26: =+Cierre!I21 -> 1330
B27: 20 | C27: =+Bioacem!C26 -> V | Q27: 1046.085 | T27: =41+31+7+6+5+4 -> 94 | U27: 3 | W27: 992.666 | Z27: =110+78+2+2+2+1+1 -> 196 | AA27: 1 | AH27: 1292.934 | AL27: =146+62+11+6+3+2+1 -> 231 | AM27: 1 | AP27: 944.064 | AR27: =53+90+1+1+2+2 -> 149 | AS27: 2 Y 3 | AU27: 1175.54 | AX27: =123+92+4+8+2+6 -> 235 | AY27: 2 | AZ27: 1164.567 | BD27: =134+96+1+9+6+3+2+1+1 -> 253 | BE27: 2 | BI27: 179.897 | BJ27: =6+3+5+2 -> 16 | BK27: 4 | BL27: 1924.859 | BP27: =96+24+6+10+13+1+1 -> 151 | BQ27: 3 | BT27: 618.078 | BV27: =42+41+3+1 -> 87 | BW27: 2 Y 3 | BZ27: 544.527 | CB27: =41+18+15+2+2+1+1 -> 80 | CC27: 1 | CD27: =+BR27+BL27+BF27+AZ27+AT27+AN27+AH28+AB27+V27+P27+J27+D27+BX27 -> 4490.305 | CE27: =+BS27+BM27+BG27+BA27+AU27+AO27+AI28+AC27+W27+Q27+K27+E27+BY27 -> 3214.291 | CF27: =+BT27+BN27+BH27+BB27+AV27+AP27+AJ28+AD27+X27+R27+L27+F27+BZ27 -> 2106.669 | CG27: =+D27+F27+J27+L27+P27+R27+V27+X27+AB27+AD27+AH27+AJ27+AN27+AP27+AT27+AV27+AZ27+BB27+BF27+BH27+BR27+BT27+BN27+BL27+E27+K27+Q27+W27+AC27+AI27+AO27+AU27+BA27+BG27+BM27+BS27+G27+M27+S27+Y27+AE27+AK27+AQ27+AW27+BC27+BI27+BO27+BU27+BX27+BY27+BZ27+CA27 -> 9883.217 | CH27: =+Cierre!H22 -> 9883.25 | CI27: =+H27+N27+T27+Z27+AF27+AL27+AR27+AX27+BD27+BJ27+BV27+BP27+CB27 -> 1492 | CJ27: =+Cierre!I22 -> 1492
B28: 21 | C28: =+Bioacem!C27 -> S | Q28: 1145.659 | T28: =148+98+6+2+1 -> 255 | U28: 1 | AB28: 1283.937 | AF28: =145+129+3+2+1+1 -> 281 | AG28: 1 | AH28: 1400.879 | AL28: =186+88+3+4+2+1+1+1+1 -> 287 | AM28: 2 | AP28: 478.891 | AR28: =55+42+2+1+1 -> 101 | AS28: 1 | AV28: 260.582 | AX28: =29+25+4+1 -> 59 | AY28: 2 Y 3 | AZ28: 1518.965 | BD28: =87+65+11+10+4+1+1 -> 179 | BE28: 3 | BI28: 30.187 | BJ28: =2+1 -> 3 | BK28: 4 | BM28: 987.123 | BP28: =81+121+3+1+1 -> 207 | BQ28: 2 | BT28: 1045.365 | BV28: =105+55+5+2+1 -> 168 | BW28: 1 | BY28: 983.146 | CB28: =51+70+2+3+3 -> 129 | CC28: 3 | CD28: =+BR28+BL28+BF28+AZ28+AT28+AN28+AH29+AB28+V28+P28+J28+D28+BX28 -> 2802.902 | CE28: =+BS28+BM28+BG28+BA28+AU28+AO28+AI29+AC28+W28+Q28+K28+E28+BY28 -> 3115.928 | CF28: =+BT28+BN28+BH28+BB28+AV28+AP28+AJ29+AD28+X28+R28+L28+F28+BZ28 -> 2037.811 | CG28: =+D28+F28+J28+L28+P28+R28+V28+X28+AB28+AD28+AH28+AJ28+AN28+AP28+AT28+AV28+AZ28+BB28+BF28+BH28+BR28+BT28+BN28+BL28+E28+K28+Q28+W28+AC28+AI28+AO28+AU28+BA28+BG28+BM28+BS28+G28+M28+S28+Y28+AE28+AK28+AQ28+AW28+BC28+BI28+BO28+BU28+BX28+BY28+BZ28+CA28 -> 9134.734 | CH28: =+Cierre!H23 -> 9134.75 | CI28: =+H28+N28+T28+Z28+AF28+AL28+AR28+AX28+BD28+BJ28+BV28+BP28+CB28 -> 1669 | CJ28: =+Cierre!I23 -> 1669
B29: 22 | C29: =+Bioacem!C28 -> D | Q29: 727.078 | T29: =74+60+6+2+1+1+1 -> 145 | U29: 2 | V29: 1074.847 | Z29: =85+75+2+1+6+3 -> 172 | AA29: 3 | AJ29: 252.973 | AL29: =27+8+3 -> 38 | AM29: 2 Y 3 | AO29: 806.764 | AR29: =88+79+3+2+2 -> 174 | AS29: 1 | AV29: 606.987 | AX29: =73+30+2+2+1 -> 108 | AY29: 1 | AZ29: 1250.957 | BD29: =129+129+6+1 -> 265 | BE29: 1 | BL29: 1000.942 | BP29: =166+66+2 -> 234 | BQ29: 2 | BT29: 201.3 | BV29: =28+18+1 -> 47 | BW29: 1 | BY29: 333.889 | CB29: =32+27+2+1+1+1 -> 64 | CC29: 3 | CD29: =+BR29+BL29+BF29+AZ29+AT29+AN29+AH30+AB29+V29+P29+J29+D29+BX29 -> 3326.746 | CE29: =+BS29+BM29+BG29+BA29+AU29+AO29+AI30+AC29+W29+Q29+K29+E29+BY29 -> 1867.731 | CF29: =+BT29+BN29+BH29+BB29+AV29+AP29+AJ30+AD29+X29+R29+L29+F29+BZ29 -> 1593.198 | CG29: =+D29+F29+J29+L29+P29+R29+V29+X29+AB29+AD29+AH29+AJ29+AN29+AP29+AT29+AV29+AZ29+BB29+BF29+BH29+BR29+BT29+BN29+BL29+E29+K29+Q29+W29+AC29+AI29+AO29+AU29+BA29+BG29+BM29+BS29+G29+M29+S29+Y29+AE29+AK29+AQ29+AW29+BC29+BI29+BO29+BU29+BX29+BY29+BZ29+CA29 -> 6255.737 | CH29: =+Cierre!H24 -> 6255.74 | CI29: =+H29+N29+T29+Z29+AF29+AL29+AR29+AX29+BD29+BJ29+BV29+BP29+CB29 -> 1247 | CJ29: =+Cierre!I24 -> 1247
B30: 23 | C30: =+Bioacem!C29 -> L | J30: 1407.371 | N30: =146+90+6+5+5+2+1 -> 255 | O30: 2 | V30: 1292.091 | Z30: =135+70+8+7+4+3+2 -> 229 | AA30: 1 | AD30: 399.971 | AF30: =28+17+3+1+1 -> 50 | AG30: 2 Y 3 | AJ30: 784.911 | AL30: =74+31+5+1+1 -> 112 | AM30: 1 | AN30: 1738.437 | AR30: =64+34+26+9+6+3+2+1 -> 145 | AS30: 1 | AV30: 631.973 | AX30: =60+26+3+3+1 -> 93 | AY30: 1 | BI30: 120.941 | BJ30: =14+5+1+1 -> 21 | BK30: 4 | BM30: 606.03 | BP30: =41+14+7+6+4 -> 72 | BQ30: 3 | BS30: 805.5 | BV30: =96+69+4+4+3+2+2 -> 180 | BW30: 1 | BY30: 1083.804 | CB30: =98+77+3+2+7+4+3+1 -> 195 | CC30: 2 | CD30: =+BR30+BL30+BF30+AZ30+AT30+AN30+AH31+AB30+V30+P30+J30+D30+BX30 -> 4437.899 | CE30: =+BS30+BM30+BG30+BA30+AU30+AO30+AI31+AC30+W30+Q30+K30+E30+BY30 -> 2495.334 | CF30: =+BT30+BN30+BH30+BB30+AV30+AP30+AJ31+AD30+X30+R30+L30+F30+BZ30 -> 1387.06 | CG30: =+D30+F30+J30+L30+P30+R30+V30+X30+AB30+AD30+AH30+AJ30+AN30+AP30+AT30+AV30+AZ30+BB30+BF30+BH30+BR30+BT30+BN30+BL30+E30+K30+Q30+W30+AC30+AI30+AO30+AU30+BA30+BG30+BM30+BS30+G30+M30+S30+Y30+AE30+AK30+AQ30+AW30+BC30+BI30+BO30+BU30+BX30+BY30+BZ30+CA30 -> 8871.029 | CH30: =+Cierre!H25 -> 8871.07 | CI30: =+H30+N30+T30+Z30+AF30+AL30+AR30+AX30+BD30+BJ30+BV30+BP30+CB30 -> 1352 | CJ30: =+Cierre!I25 -> 1352
B31: 24 | C31: =+Bioacem!C30 -> M | P31: 1125.217 | T31: =129+53+7+6+5+2+1 -> 203 | U31: 1 | V31: 1115.783 | Z31: =43+41+1+6+3+11 -> 105 | AA31: 2 | AD31: 982.46 | AF31: =39+66+1+4+2+1+2+2 -> 117 | AG31: 1 | AJ31: 355.116 | AL31: =53+10+2+1 -> 66 | AM31: 1 | AO31: 779.473 | AR31: =87+67+10+3+3+1+1 -> 172 | AS31: 2 | AU31: 884.438 | AX31: =135+72+5+4+4+3+2+1 -> 226 | AY31: 3 | BA31: 1236.191 | BD31: =87+72+3+5+1+8+5 -> 181 | BE31: 1 | BI31: 87.427 | BJ31: =9+4+1+1 -> 15 | BK31: 4 | BN31: 387.873 | BP31: =33+14 -> 47 | BQ31: 2 Y 3 | BR31: 841.568 | BV31: =65+32+2+4+13+3+2 -> 121 | BW31: 3 | BX31: 664.446 | CB31: =40+23+6+4+3 -> 76 | CC31: 3 | CD31: =+BR31+BL31+BF31+AZ31+AT31+AN31+AH32+AB31+V31+P31+J31+D31+BX31 -> 4789.96 | CE31: =+BS31+BM31+BG31+BA31+AU31+AO31+AI32+AC31+W31+Q31+K31+E31+BY31 -> 2900.102 | CF31: =+BT31+BN31+BH31+BB31+AV31+AP31+AJ32+AD31+X31+R31+L31+F31+BZ31 -> 1370.333 | CG31: =+D31+F31+J31+L31+P31+R31+V31+X31+AB31+AD31+AH31+AJ31+AN31+AP31+AT31+AV31+AZ31+BB31+BF31+BH31+BR31+BT31+BN31+BL31+E31+K31+Q31+W31+AC31+AI31+AO31+AU31+BA31+BG31+BM31+BS31+G31+M31+S31+Y31+AE31+AK31+AQ31+AW31+BC31+BI31+BO31+BU31+BX31+BY31+BZ31+CA31 -> 8459.992 | CH31: =+Cierre!H26 -> 8460 | CI31: =+H31+N31+T31+Z31+AF31+AL31+AR31+AX31+BD31+BJ31+BV31+BP31+CB31 -> 1329 | CJ31: =+Cierre!I26 -> 1329
B32: 25 | C32: =+Bioacem!C31 -> M | K32: 1403.365 | N32: =121+78+6+7+5+4+3 -> 224 | O32: 1 | P32: 1591.555 | T32: =69+55+28+6+5+3+1+1 -> 168 | U32: 3 | AD32: 651.45 | AF32: =54+31+5+2 -> 92 | AG32: 1 | AH32: 1042.946 | AL32: =122+89+4+4+3+1 -> 223 | AM32: 1 | AO32: 1014.816 | AR32: =50+34+7+4+4+3+1 -> 103 | AS32: 3 | AV32: 398.413 | AX32: =47+22+3+2+1 -> 75 | AY32: 2 Y 3 | BA32: 942.703 | BD32: =89+64+7+5+4+3+2 -> 174 | BE32: 2 | BI32: 38.014 | BJ32: =7+1+4 -> 12 | BK32: 4 | BN32: 884.06 | BP32: =84+23+2+2+1 -> 112 | BQ32: 2 Y 3 | BR32: 1355.726 | BV32: =168+104+6+5+4+2+2 -> 291 | BW32: 2 | CD32: =+BR32+BL32+BF32+AZ32+AT32+AN32+AH33+AB32+V32+P32+J32+D32+BX32 -> 2947.281 | CE32: =+BS32+BM32+BG32+BA32+AU32+AO32+AI33+AC32+W32+Q32+K32+E32+BY32 -> 3360.884 | CF32: =+BT32+BN32+BH32+BB32+AV32+AP32+AJ33+AD32+X32+R32+L32+F32+BZ32 -> 2460.179 | CG32: =+D32+F32+J32+L32+P32+R32+V32+X32+AB32+AD32+AH32+AJ32+AN32+AP32+AT32+AV32+AZ32+BB32+BF32+BH32+BR32+BT32+BN32+BL32+E32+K32+Q32+W32+AC32+AI32+AO32+AU32+BA32+BG32+BM32+BS32+G32+M32+S32+Y32+AE32+AK32+AQ32+AW32+BC32+BI32+BO32+BU32+BX32+BY32+BZ32+CA32 -> 9323.048 | CH32: =+Cierre!H27 -> 9323.05 | CI32: =+H32+N32+T32+Z32+AF32+AL32+AR32+AX32+BD32+BJ32+BV32+BP32+CB32 -> 1474 | CJ32: =+Cierre!I27 -> 1474
B33: 26 | C33: =+Bioacem!C32 -> J | K33: 996.742 | N33: =52+49+9+7+7+2+2 -> 128 | O33: 2 | P33: 1254.262 | T33: =120+68+12+9+7+5+5+2 -> 228 | U33: 2 | AJ33: 526.256 | AL33: =47+35+1 -> 83 | AM33: 3 | AO33: 994.078 | AR33: =56+59+5+5+2+1+1 -> 129 | AS33: 1 | AV33: 1139.302 | AX33: =59+99+3+8+4+3+1 -> 177 | AY33: 2 Y 3 | BB33: 266.111 | BD33: =37+18+4+1 -> 60 | BE33: 2 Y 3 | BI33: =169.731+108.431 -> 278.162 | BJ33: =10+17+1+7+6+1 -> 42 | BK33: 4 | BN33: 476.786 | BP33: =45+20+3+1+1+1 -> 71 | BQ33: 1 | BR33: 1244.547 | BV33: =97+99+12+6+3+2+1 -> 220 | BW33: 1 | BX33: 1030.009 | CB33: =98+73+7+3+1+2+2 -> 186 | CC33: 3 | CD33: =+BR33+BL33+BF33+AZ33+AT33+AN33+AH34+AB33+V33+P33+J33+D33+BX33 -> 3528.818 | CE33: =+BS33+BM33+BG33+BA33+AU33+AO33+AI34+AC33+W33+Q33+K33+E33+BY33 -> 2850.373 | CF33: =+BT33+BN33+BH33+BB33+AV33+AP33+AJ34+AD33+X33+R33+L33+F33+BZ33 -> 1882.199 | CG33: =+D33+F33+J33+L33+P33+R33+V33+X33+AB33+AD33+AH33+AJ33+AN33+AP33+AT33+AV33+AZ33+BB33+BF33+BH33+BR33+BT33+BN33+BL33+E33+K33+Q33+W33+AC33+AI33+AO33+AU33+BA33+BG33+BM33+BS33+G33+M33+S33+Y33+AE33+AK33+AQ33+AW33+BC33+BI33+BO33+BU33+BX33+BY33+BZ33+CA33 -> 8206.255 | CH33: =+Cierre!H28 -> 8206.27 | CI33: =+H33+N33+T33+Z33+AF33+AL33+AR33+AX33+BD33+BJ33+BV33+BP33+CB33 -> 1324 | CJ33: =+Cierre!I28 -> 1324
B34: 27 | C34: =+Bioacem!C33 -> V | J34: 1645.413 | N34: =86+52+6+3+1+20+5+2 -> 175 | O34: 3 | R34: 549.372 | T34: =36+40+3+2+1+1+1 -> 84 | U34: 1 | AC34: 1031.922 | AF34: =87+67+5+4+4+2+1+1+1 -> 172 | AG34: 1 | AI34: 859.553 | AL34: =83+58+4+4+4+2+1 -> 156 | AM34: 2 | AN34: 1199.102 | AR34: =131+86+7+6+5+1+1 -> 237 | AS34: 1 | AV34: 715.141 | AX34: =56+32+4+2+1 -> 95 | AY34: 1 | BB34: 1199.563 | BD34: =68+85+6+1+3+1 -> 164 | BE34: 2 Y 3 | BI34: 251.587 | BJ34: =1+13+6+2+2+1 -> 25 | BK34: 4 | BS34: 1125.706 | BV34: =54+48+2+6+6+5+6 -> 127 | BW34: 2 | BX34: 1378.833 | CB34: =117+136+7+6+3+2+1+1 -> 273 | CC34: 2 | CD34: =+BR34+BL34+BF34+AZ34+AT34+AN34+AH35+AB34+V34+P34+J34+D34+BX34 -> 4223.348 | CE34: =+BS34+BM34+BG34+BA34+AU34+AO34+AI35+AC34+W34+Q34+K34+E34+BY34 -> 3102.401 | CF34: =+BT34+BN34+BH34+BB34+AV34+AP34+AJ35+AD34+X34+R34+L34+F34+BZ34 -> 2464.076 | CG34: =+D34+F34+J34+L34+P34+R34+V34+X34+AB34+AD34+AH34+AJ34+AN34+AP34+AT34+AV34+AZ34+BB34+BF34+BH34+BR34+BT34+BN34+BL34+E34+K34+Q34+W34+AC34+AI34+AO34+AU34+BA34+BG34+BM34+BS34+G34+M34+S34+Y34+AE34+AK34+AQ34+AW34+BC34+BI34+BO34+BU34+BX34+BY34+BZ34+CA34 -> 9956.192 | CH34: =+Cierre!H29 -> 9956.23 | CI34: =+H34+N34+T34+Z34+AF34+AL34+AR34+AX34+BD34+BJ34+BV34+BP34+CB34 -> 1508 | CJ34: =+Cierre!I29 -> 1508
B35: 28 | C35: =+Bioacem!C34 -> S | J35: 1533.712 | N35: =113+100+9+5+1+1 -> 229 | O35: 3 | R35: 754.059 | T35: =64+39+4+2+1+1 -> 111 | U35: 1 | AC35: 1248.486 | AF35: =128+107+4+2+3+1 -> 245 | AG35: 1 | AI35: 944.773 | AL35: =117+77+2+1 -> 197 | AM35: 2 | AT35: 1510.571 | AX35: =139+132+4+3+3+3+2+2+1 -> 289 | AY35: 2 | BB35: 402.307 | BD35: =42+25+2+1 -> 70 | BE35: 1 | BI35: 417.805 | BJ35: =36+17+3+2+1+4+1 -> 64 | BK35: 4 | BL35: 1574.684 | BP35: =231+59+3+1 -> 294 | BQ35: 1 | BS35: 1173.909 | BV35: =86+60+7+3+2+1+1 -> 160 | BW35: 3 | BZ35: 399.229 | CB35: =51+38+1 -> 90 | CC35: 2 Y 3 | CD35: =+BR35+BL35+BF35+AZ35+AT35+AN35+AH36+AB35+V35+P35+J35+D35+BX35 -> 4618.967 | CE35: =+BS35+BM35+BG35+BA35+AU35+AO35+AI36+AC35+W35+Q35+K35+E35+BY35 -> 2422.395 | CF35: =+BT35+BN35+BH35+BB35+AV35+AP35+AJ36+AD35+X35+R35+L35+F35+BZ35 -> 1555.595 | CG35: =+D35+F35+J35+L35+P35+R35+V35+X35+AB35+AD35+AH35+AJ35+AN35+AP35+AT35+AV35+AZ35+BB35+BF35+BH35+BR35+BT35+BN35+BL35+E35+K35+Q35+W35+AC35+AI35+AO35+AU35+BA35+BG35+BM35+BS35+G35+M35+S35+Y35+AE35+AK35+AQ35+AW35+BC35+BI35+BO35+BU35+BX35+BY35+BZ35+CA35 -> 9959.535 | CH35: =+Cierre!H30 -> 9959.54 | CI35: =+H35+N35+T35+Z35+AF35+AL35+AR35+AX35+BD35+BJ35+BV35+BP35+CB35 -> 1749 | CJ35: =+Cierre!I30 -> 1749
B36: 29 | C36: =+Bioacem!C35 -> D | CD36: =+BR36+BL36+BF36+AZ36+AT36+AN36+AH37+AB36+V36+P36+J36+D36+BX36 -> 0 | CE36: =+BS36+BM36+BG36+BA36+AU36+AO36+AI37+AC36+W36+Q36+K36+E36+BY36 -> 0 | CF36: =+BT36+BN36+BH36+BB36+AV36+AP36+AJ37+AD36+X36+R36+L36+F36+BZ36 -> 0 | CG36: =+D36+F36+J36+L36+P36+R36+V36+X36+AB36+AD36+AH36+AJ36+AN36+AP36+AT36+AV36+AZ36+BB36+BF36+BH36+BR36+BT36+BN36+BL36+E36+K36+Q36+W36+AC36+AI36+AO36+AU36+BA36+BG36+BM36+BS36+G36+M36+S36+Y36+AE36+AK36+AQ36+AW36+BC36+BI36+BO36+BU36+BX36+BY36+BZ36+CA36 -> 0 | CH36: =+Cierre!H31 -> 0 | CI36: =+H36+N36+T36+Z36+AF36+AL36+AR36+AX36+BD36+BJ36+BV36+BP36+CB36 -> 0 | CJ36: =+Cierre!I31 -> 0
B37: 30 | C37: =+Bioacem!C36 -> L | CD37: =+BR37+BL37+BF37+AZ37+AT37+AN37+AH38+AB37+V37+P37+J37+D37+BX37 -> 0 | CE37: =+BS37+BM37+BG37+BA37+AU37+AO37+AI38+AC37+W37+Q37+K37+E37+BY37 -> 0 | CF37: =+BT37+BN37+BH37+BB37+AV37+AP37+AJ38+AD37+X37+R37+L37+F37+BZ37 -> 0 | CG37: =+D37+F37+J37+L37+P37+R37+V37+X37+AB37+AD37+AH37+AJ37+AN37+AP37+AT37+AV37+AZ37+BB37+BF37+BH37+BR37+BT37+BN37+BL37+E37+K37+Q37+W37+AC37+AI37+AO37+AU37+BA37+BG37+BM37+BS37+G37+M37+S37+Y37+AE37+AK37+AQ37+AW37+BC37+BI37+BO37+BU37+BX37+BY37+BZ37+CA37 -> 0 | CH37: =+Cierre!H32 -> 0 | CI37: =+H37+N37+T37+Z37+AF37+AL37+AR37+AX37+BD37+BJ37+BV37+BP37+CB37 -> 0 | CJ37: =+Cierre!I32 -> 0
B38: 31 | C38: =+Bioacem!C37 -> M | CD38: =+BR38+BL38+BF38+AZ38+AT38+AN38+AH39+AB38+V38+P38+J38+D38+BX38 -> 9199.13 | CE38: =+BS38+BM38+BG38+BA38+AU38+AO38+AI39+AC38+W38+Q38+K38+E38+BY38 -> 5365.568 | CF38: =+BT38+BN38+BH38+BB38+AV38+AP38+AJ39+AD38+X38+R38+L38+F38+BZ38 -> 6355.717 | CG38: =+D38+F38+J38+L38+P38+R38+V38+X38+AB38+AD38+AH38+AJ38+AN38+AP38+AT38+AV38+AZ38+BB38+BF38+BH38+BR38+BT38+BN38+BL38+E38+K38+Q38+W38+AC38+AI38+AO38+AU38+BA38+BG38+BM38+BS38+G38+M38+S38+Y38+AE38+AK38+AQ38+AW38+BC38+BI38+BO38+BU38+BX38+BY38+BZ38+CA38 -> 0 | CH38: =+Cierre!H33 -> 0 | CI38: =+H38+N38+T38+Z38+AF38+AL38+AR38+AX38+BD38+BJ38+BV38+BP38+CB38 -> 0 | CJ38: =+Cierre!I33 -> 0
D39: =SUM(D8:D38) -> 6634.716 | E39: =SUM(E8:E38) -> 1665.704 | F39: 2692.1 | G39: =SUM(G8:G38) -> 0 | H39: =SUM(H8:H38) -> 1906 | J39: =SUM(J8:J38) -> 9887.427 | K39: =SUM(K8:K38) -> 5442.516 | L39: =SUM(L8:L38) -> 2944.496 | M39: =SUM(M8:M38) -> 638.646 | N39: =SUM(N8:N38) -> 2791 | P39: =SUM(P8:P38) -> 9635.357 | Q39: =SUM(Q8:Q38) -> 8052.734 | R39: =SUM(R8:R38) -> 3595.439 | S39: =SUM(S8:S38) -> 231.871 | T39: =SUM(T8:T38) -> 3590 | V39: =SUM(V8:V38) -> 13892.698 | W39: =SUM(W8:W38) -> 6257.884 | X39: =SUM(X8:X38) -> 1790.75 | Y39: =SUM(Y8:Y38) -> 0 | Z39: =SUM(Z8:Z38) -> 3430 | AB39: =SUM(AB8:AB38) -> 5892.924 | AC39: =SUM(AC8:AC38) -> 7618.856 | AD39: =SUM(AD8:AD38) -> 5251.667 | AE39: =SUM(AE8:AE38) -> 0 | AF39: =SUM(AF8:AF38) -> 3203 | AH39: =SUM(AH8:AH38) -> 9199.13 | AI39: =SUM(AI8:AI38) -> 5365.568 | AJ39: =SUM(AJ8:AJ38) -> 6355.717 | AK39: =SUM(AK8:AK38) -> 773.565 | AL39: =SUM(AL8:AL38) -> 3774 | AN39: =SUM(AN8:AN38) -> 10313.02 | AO39: =SUM(AO8:AO38) -> 6437.706 | AP39: =SUM(AP8:AP38) -> 1965.952 | AQ39: =SUM(AQ8:AQ38) -> 0 | AR39: =SUM(AR8:AR38) -> 2497 | AT39: =SUM(AT8:AT38) -> 4758.124 | AU39: =SUM(AU8:AU38) -> 7006.703 | AV39: =SUM(AV8:AV38) -> 5021.584 | AW39: =SUM(AW8:AW38) -> 157.865 | AX39: =SUM(AX8:AX38) -> 2753 | AZ39: =SUM(AZ8:AZ38) -> 7737.922 | BA39: =SUM(BA8:BA38) -> 3973.3 | BB39: =SUM(BB8:BB38) -> 5502.187 | BC39: =SUM(BC8:BC38) -> 437.425 | BD39: =SUM(BD8:BD38) -> 2912 | BF39: =SUM(BF8:BF38) -> 0 | BG39: =SUM(BG8:BG38) -> 0 | BH39: =SUM(BH8:BH38) -> 0 | BI39: =SUM(BI8:BI38) -> 2257.691 | BJ39: =SUM(BJ8:BJ38) -> 344 | BL39: =SUM(BL8:BL38) -> 9381.994 | BM39: =SUM(BM8:BM38) -> 5776.634 | BN39: =SUM(BN8:BN38) -> 4529.442 | BO39: =SUM(BO8:BO38) -> 1027.929 | BP39: =SUM(BP8:BP38) -> 3134 | BR39: =SUM(BR8:BR38) -> 10372.826 | BS39: =SUM(BS8:BS38) -> 7135.131 | BT39: =SUM(BT8:BT38) -> 7092.075 | BU39: =SUM(BU8:BU38) -> 1132.608 | BV39: =SUM(BV8:BV38) -> 4079 | BX39: =SUM(BX8:BX38) -> 11107.205 | BY39: =SUM(BY8:BY38) -> 4942.767 | BZ39: =SUM(BZ8:BZ38) -> 3421.06 | CA39: =SUM(CA8:CA38) -> 1913.769 | CB39: =SUM(CB8:CB38) -> 3630 | CD39: =SUM(CD8:CD38) -> 116719.54 | CE39: =SUM(CE8:CE38) -> 75041.071 | CF39: =SUM(CF8:CF38) -> 58006.701 | CG39: =SUM(CG8:CG38) -> 238711.2 | CI39: =SUM(CI8:CI38) -> 38043
B40: TOTAL | D40: =IFERROR(AVERAGE(D8:D38),0) -> 947.81657 | E40: =IFERROR(AVERAGE(E8:E38),0) -> 555.23467 | F40: =IFERROR(AVERAGE(F8:F38),0) -> 522.57687 | G40: =IFERROR(AVERAGE(G8:G38),0) -> 0 | H40: =AVERAGE(H8:H38) -> 105.88889 | J40: =IFERROR(AVERAGE(J8:J38),0) -> 1098.603 | K40: =IFERROR(AVERAGE(K8:K38),0) -> 1088.5032 | L40: =IFERROR(AVERAGE(L8:L38),0) -> 588.8992 | M40: =IFERROR(AVERAGE(M8:M38),0) -> 212.882 | N40: =AVERAGE(N8:N38) -> 126.86364 | P40: =IFERROR(AVERAGE(P8:P38),0) -> 1070.5952 | Q40: =IFERROR(AVERAGE(Q8:Q38),0) -> 894.74822 | R40: =IFERROR(AVERAGE(R8:R38),0) -> 719.0878 | S40: =IFERROR(AVERAGE(S8:S38),0) -> 231.871 | T40: =AVERAGE(T8:T38) -> 149.58333 | V40: =IFERROR(AVERAGE(V8:V38),0) -> 1157.7248 | W40: =IFERROR(AVERAGE(W8:W38),0) -> 893.98343 | X40: =IFERROR(AVERAGE(X8:X38),0) -> 596.91667 | Y40: =IFERROR(AVERAGE(Y8:Y38),0) -> 0 | Z40: =AVERAGE(Z8:Z38) -> 155.90909 | AB40: =IFERROR(AVERAGE(AB8:AB38),0) -> 1178.5848 | AC40: =IFERROR(AVERAGE(AC8:AC38),0) -> 846.53956 | AD40: =IFERROR(AVERAGE(AD8:AD38),0) -> 656.45838 | AE40: =IFERROR(AVERAGE(AE8:AE38),0) -> 0 | AF40: =AVERAGE(AF8:AF38) -> 145.59091 | AH40: =IFERROR(AVERAGE(AH8:AH38),0) -> 1149.8913 | AI40: =IFERROR(AVERAGE(AI8:AI38),0) -> 894.26133 | AJ40: =IFERROR(AVERAGE(AJ8:AJ38),0) -> 577.79245 | AK40: =IFERROR(AVERAGE(AK8:AK38),0) -> 386.7825 | AL40: =AVERAGE(AL8:AL38) -> 139.77778 | AN40: =IFERROR(AVERAGE(AN8:AN38),0) -> 1145.8911 | AO40: =IFERROR(AVERAGE(AO8:AO38),0) -> 919.67229 | AP40: =IFERROR(AVERAGE(AP8:AP38),0) -> 655.31733 | AQ40: =IFERROR(AVERAGE(AQ8:AQ38),0) -> 0 | AR40: =AVERAGE(AR8:AR38) -> 131.42105 | AT40: =IFERROR(AVERAGE(AT8:AT38),0) -> 1189.531 | AU40: =IFERROR(AVERAGE(AU8:AU38),0) -> 875.83788 | AV40: =IFERROR(AVERAGE(AV8:AV38),0) -> 627.698 | AW40: =IFERROR(AVERAGE(AW8:AW38),0) -> 157.865 | AX40: =AVERAGE(AX8:AX38) -> 131.09524 | AZ40: =IFERROR(AVERAGE(AZ8:AZ38),0) -> 1105.4174 | BA40: =IFERROR(AVERAGE(BA8:BA38),0) -> 993.325 | BB40: =IFERROR(AVERAGE(BB8:BB38),0) -> 687.77337 | BC40: =IFERROR(AVERAGE(BC8:BC38),0) -> 145.80833 | BD40: =AVERAGE(BD8:BD38) -> 132.36364 | BF40: =IFERROR(AVERAGE(BF8:BF38),0) -> 0 | BG40: =IFERROR(AVERAGE(BG8:BG38),0) -> 0 | BH40: =IFERROR(AVERAGE(BH8:BH38),0) -> 0 | BI40: =IFERROR(AVERAGE(BI8:BI38),0) -> 132.80535 | BJ40: =AVERAGE(BJ8:BJ38) -> 20.235294 | BL40: =IFERROR(AVERAGE(BL8:BL38),0) -> 1042.4438 | BM40: =IFERROR(AVERAGE(BM8:BM38),0) -> 825.23343 | BN40: =IFERROR(AVERAGE(BN8:BN38),0) -> 566.18025 | BO40: =IFERROR(AVERAGE(BO8:BO38),0) -> 513.9645 | BP40: =AVERAGE(BP8:BP38) -> 120.53846 | BR40: =IFERROR(AVERAGE(BR8:BR38),0) -> 1037.2826 | BS40: =IFERROR(AVERAGE(BS8:BS38),0) -> 1019.3044 | BT40: =IFERROR(AVERAGE(BT8:BT38),0) -> 709.2075 | BU40: =IFERROR(AVERAGE(BU8:BU38),0) -> 1132.608 | BV40: =AVERAGE(BV8:BV38) -> 145.67857 | BX40: =IFERROR(AVERAGE(BX8:BX38),0) -> 1110.7205 | BY40: =IFERROR(AVERAGE(BY8:BY38),0) -> 823.7945 | BZ40: =IFERROR(AVERAGE(BZ8:BZ38),0) -> 488.72286 | CA40: =IFERROR(AVERAGE(CA8:CA38),0) -> 637.923 | CB40: =AVERAGE(CB8:CB38) -> 139.61538
D41: =IFERROR(AVERAGE(D8:F38),0) -> 693.39083 | H41: =(+D39+F39+E39)/H39 -> 5.7673242 | J41: =IFERROR(AVERAGE(J8:L38),0) -> 961.81258 | N41: =(+J39+L39+K39)/N39 -> 6.5476313 | P41: =IFERROR(AVERAGE(P8:R38),0) -> 925.37087 | T41: =(+P39+R39+Q39)/T39 -> 5.9285599 | V41: =IFERROR(AVERAGE(V8:X38),0) -> 997.33327 | Z41: =(+V39+X39+W39)/Z39 -> 6.3968898 | AB41: =IFERROR(AVERAGE(AB8:AD38),0) -> 852.88395 | AF41: =(+AB39+AD39+AC39)/AF39 -> 5.8580852 | AH41: =IFERROR(AVERAGE(AH8:AJ38),0) -> 836.8166 | AL41: =(+AH39+AJ39+AI39)/AL39 -> 5.5433002 | AN41: =IFERROR(AVERAGE(AN8:AP38),0) -> 985.08832 | AR41: =(+AN39+AP39+AO39)/AR39 -> 7.495666 | AT41: =IFERROR(AVERAGE(AT8:AV38),0) -> 839.32055 | AX41: =(+AT39+AV39+AU39)/AX39 -> 6.0974976 | AZ41: =IFERROR(AVERAGE(AZ8:BB38),0) -> 905.96889 | BD41: =(+AZ39+BB39+BA39)/BD39 -> 5.9111981 | BF41: =IFERROR(AVERAGE(BF8:BH38),0) -> 0 | BJ41: =(+BF39+BH39+BG39)/BJ39 -> 0 | BL41: =IFERROR(AVERAGE(BL8:BN38),0) -> 820.33625 | BP41: =(+BL39+BN39+BM39)/BP39 -> 6.28209 | BR41: =IFERROR(AVERAGE(BR8:BT38),0) -> 911.1123 | BV41: =(+BR39+BT39+BS39)/BV39 -> 6.0308978 | BX41: =IFERROR(AVERAGE(BX8:BZ38),0) -> 846.56661 | CB41: =(+BX39+BZ39+BY39)/CB39 -> 5.3639207
F44: Galones | H44: Clientes | J44: Prom Total | K44: Prom T1 T2 | L44: Prom T3 | M44: Prom T4
D45: =+D6 -> SAMUEL MORENO/SANTIAGO LEON | F45: =+D39+E39+F39 -> 10992.52 | H45: =+H39 -> 1906 | J45: =+F45/H45 -> 5.7673242 | K45: =AVERAGE(D40:E40) -> 751.52562 | L45: =+F40 -> 522.57687 | M45: =+G40 -> 0 | N45: =+J45*3000 -> 17301.973
D46: =+J6 -> YEISON FLOREZ | F46: =+J39+K39+L39 -> 18274.439 | H46: =+N39 -> 2791 | J46: =+F46/H46 -> 6.5476313 | K46: =AVERAGE(J40:K40) -> 1093.5531 | L46: =+L40 -> 588.8992 | M46: =+M40 -> 212.882 | N46: =+J46*3000 -> 19642.894 | P46: =+N46+O46 -> 19642.894 | R46: TURNO 2 | S46: TURNO 3 | T46: TURNO 4
D47: =+P6 -> JHONATAN PADILLA | F47: =+P39+Q39+R39 -> 21283.53 | H47: =+T39 -> 3590 | J47: =+F47/H47 -> 5.9285599 | K47: =AVERAGE(P40:Q40) -> 982.67172 | L47: =+R40 -> 719.0878 | M47: =+S40 -> 231.871 | N47: =+J47*3000 -> 17785.68 | O47: =+N47 -> 17785.68 | P47: =+N47+O47 -> 35571.359 | R47: =+E39+K39+Q39+W39+AC39+AI39+AO39+AU39+BA39+BG39+BM39+BS39+BY39 -> 69675.503 | S47: =+F39+L39+R39+X39+AD39+AJ39+AP39+AV39+BB39+BH39+BN39+BT39+BZ39 -> 50162.469 | T47: =+G39+M39+S39+Y39+AE39+AK39+AQ39+AW39+BC39+BI39+BO39+BU39++CA39 -> 8571.369
D48: =+V6 -> MARIA CAROLINA MEJIA | F48: =+V39+X39+W39 -> 21941.332 | H48: =+Z39 -> 3430 | J48: =+F48/H48 -> 6.3968898 | K48: =AVERAGE(V40:W40) -> 1025.8541 | L48: =+X40 -> 596.91667 | M48: =+Y40 -> 0 | N48: =+J48*3000 -> 19190.669 | R48: =+E40+K40+Q40+W40+AC40+AI40+AO40+AU40+BA40+BG40+BM40+BS40+BY40 -> 10630.438 | S48: =+F40+L40+R40+X40+AD40+AJ40+AP40+AV40+BB40+BH40+BN40+BT40+BZ40 -> 7396.6307 | T48: =+G40+M40+S40+Y40+AE40+AK40+AQ40+AW40+BC40+BI40+BO40+BU40+CA40 -> 3552.5097
D49: =+AB6 -> SANDRA YEPEZ | F49: =+AB39+AC39+AD39 -> 18763.447 | H49: =+T39 -> 3590 | J49: =+F49/H49 -> 5.2265869 | K49: =AVERAGE(AB40:AC40) -> 1012.5622 | L49: =+AD40 -> 656.45838 | M49: =+AE40 -> 0 | N49: =+J49*3000 -> 15679.761 | P49: =+N49+O49 -> 15679.761
D50: =+AH6 -> LEONARDO SERPA | F50: =+AH39+AI39+AJ39 -> 20920.415 | H50: =+AL39 -> 3774 | J50: =+F50/H50 -> 5.5433002 | K50: =AVERAGE(AH40:AI40) -> 1022.0763 | L50: =+AJ40 -> 577.79245 | M50: =+AK40 -> 386.7825 | N50: =+J50*3000 -> 16629.901 | O50: =+N50 -> 16629.901 | P50: =+N50+O50 -> 33259.801
D51: =+AN6 -> YADIRA CRUZ | F51: =+AN39+AO39+AP39 -> 18716.678 | H51: =+AR39 -> 2497 | J51: =+F51/H51 -> 7.495666 | K51: =AVERAGE(AN40:AO40) -> 1032.7817 | L51: =+AP40 -> 655.31733 | M51: =+AR40 -> 131.42105 | N51: =+J51*3000 -> 22486.998 | P51: =+N51+O51 -> 22486.998
D52: =+AT6 -> MARIBEL GAMEZ | F52: =+AT39+AU39+AV39 -> 16786.411 | H52: =+AX39 -> 2753 | J52: =+F52/H52 -> 6.0974976 | K52: =AVERAGE(AT40:AU40) -> 1032.6844 | L52: =+AV40 -> 627.698 | M52: =+AW40 -> 157.865 | N52: =+J52*3000 -> 18292.493 | P52: =+N52+O52 -> 18292.493
D53: =+AZ6 -> ANGELA HERREÑO | F53: =+AZ39+BA39+BB39 -> 17213.409 | H53: =+BD39 -> 2912 | J53: =+F53/H53 -> 5.9111981 | K53: =AVERAGE(AZ40:BA40) -> 1049.3712 | L53: =+BB40 -> 687.77337 | M53: =+BC40 -> 145.80833 | N53: =+J53*3000 -> 17733.594 | P53: =+N53+O53 -> 17733.594
D54: =+BF6 -> LIZETH ORJUELA | F54: =+BF39+BG39+BH39 -> 0 | H54: =+BJ39 -> 344 | J54: =+F54/H54 -> 0 | K54: =AVERAGE(BF40:BG40) -> 0 | L54: =+BH40+F40+L40++R40+X40+AD40+AJ40+AP40+AV40+BB40+BN40+BT40+BZ40 -> 7396.6307 | M54: =+BI40 -> 132.80535 | N54: =+J54*3000 -> 0 | P54: =+N54+O54 -> 0
D55: =+BL6 -> ANGIE RUIZ/CAMILO SANCHEZ | F55: =+BL39+BM39+BN39 -> 19688.07 | H55: =+BP39 -> 3134 | J55: =+F55/H55 -> 6.28209 | K55: =AVERAGE(BL40:BM40) -> 933.8386 | L55: =+BN40 -> 566.18025 | M55: =+BO40 -> 513.9645 | N55: =+J55*3000 -> 18846.27 | P55: =+N55+O55 -> 18846.27
D56: =+BR6 -> JOSE DUARTE | F56: =+BR39+BS39+BT39 -> 24600.032 | H56: =+BV39 -> 4079 | J56: =+F56/H56 -> 6.0308978 | K56: =AVERAGE(BR40:BS40) -> 1028.2935 | L56: =+BT40 -> 709.2075 | M56: =+BU40 -> 1132.608 | N56: =+J56*3000 -> 18092.693 | O56: =+N56 -> 18092.693 | P56: =+N56+O56 -> 36185.387
D57: =+BX6 -> VALENTINA COSSIO /DANIEL ARGEL | F57: =+BX39+BY39+BZ39 -> 19471.032 | H57: =+CB39 -> 3630 | J57: =+F57/H57 -> 5.3639207 | K57: =AVERAGE(BX40:BY40) -> 967.2575 | L57: =+BZ40 -> 488.72286 | M57: =+CA40 -> 637.923 | N57: =+J57*3000 -> 16091.762 | P57: =+N57+O57 -> 16091.762
F58: =SUM(F45:F56) -> 209180.28 | H58: =SUM(H45:H56) -> 34800 | J58: =+F58/H58 -> 6.0109277 | K58: =+AVERAGE(K45:K56) -> 913.76771 | L58: =+AVERAGE(L45:L56) -> 1192.0449 | M58: =+AVERAGE(M45:M56) -> 253.83398 | P58: =SUM(P45:P57) -> 233790.32 | Q58: 62802.587
BW68: 7
BW27620: 4

Sheet Presupuesto
B5: 2026
C6: ENE | D6: FEB | E6: MAR | F6: ABR | G6: MAY | H6: JUN | I6: JUL | J6: AGO | K6: SEP | L6: OCT | M6: NOV | N6: DIC
B7: Ventas | C7: 241755.22 | D7: =+'G. Corriente'!E38+Bioacem!E38+'G. Extra'!E38 -> 238711.71 | N7: =+[2]Cierre!H58 -> 0
B8: Compra | C8: 248400 | D8: =+'G. Corriente'!F38+Bioacem!F38+'G. Extra'!F38 -> 240300 | N8: =+[2]Facturas!F93 -> 0
B9: Rumbo | C9: 23699.247 | D9: =+Cierre!L35+Cierre!P35 -> 23619.75 | N9: =+[2]Cierre!L59 -> 0
B10: Clientes Propios | C10: 8321.3859 | D10: =+Cierre!T35 -> 10327.538 | N10: =+[2]Cierre!T59 -> 0
B11: Clientes Paso | C11: 209734.59 | D11: =+D7-D9-D10 -> 204764.42 | N11: =+N7-N9-N10 -> 0
B12: Presupuesto 25 | C12: 220944 | D12: =+D13+D14+D15 -> 238464
B13: Presupuesto CTE | C13: 103407 | D13: 110924
B14: Presupuesto ACPM | C14: 108332 | D14: 117867
B15: Presupuesto EXTRA | C15: 9205 | D15: 9673
B16: Cumplimiento | C16: =+C8/C12 -> 1.1242668 | D16: =+D8/D12 -> 1.0076993
B17: % Rumbo | C17: =+C9/C7 -> 0.098029931 | D17: =+D9/D7 -> 0.098946757
B18: % Clientes Propios | C18: =+C10/C7 -> 0.034420708 | D18: =+D10/D7 -> 0.043263644
B19: % Clientes Paso | C19: =+C11/C7 -> 0.86754936 | D19: =+D11/D7 -> 0.8577896
B20: PRESUPUESTO POR PRODUCTO
B21: % CTE | C21: 1.1198468 | D21: =+'G. Corriente'!F38/Presupuesto!D13 -> 0.94298799
B22: % BIOACEM | C22: 1.0966289 | D22: =+Bioacem!F38/Presupuesto!D14 -> 1.0469427
B23: % EXTRA | C23: 1.4991852 | D23: =+'G. Extra'!F38/Presupuesto!D15 -> 1.2715807
B24: MIX PRODUCTOS
B25: %VENTAS CTE | C25: 0.46086889 | D25: =+'G. Corriente'!E38/Presupuesto!D7 -> 0.44118028
B26: %VENTAS BIOACEM | C26: 0.48613287 | D26: =+Bioacem!E38/Presupuesto!D7 -> 0.50998893
B27: %VENTAS EXTRA | C27: 0.052998235 | D27: =+'G. Extra'!E38/Presupuesto!D7 -> 0.048830784

Sheet Sicom
B3: EDS JAP S.A.S.
B4: EDS LA PORTADA
B5: INFORME SICOM
K6: =-0.4*D10/1000 -> -41.84
C8: INVENTARIO INICIAL | D8: COMPRAS | E8: VENTAS | F8: FALTANTES | G8: EVAPORACION | H8: INVENTARIO FINAL | I8: INVENTARIO FINAL
B9: ACPM | C9: =+Bioacem!D7 -> 12651.427 | D9: =+Bioacem!F38 -> 123400 | E9: =-Bioacem!E38 -> -121740.33 | F9: =IF((SUM(C9:E9)=I9),0,H9-I9) -> -480.903 | G9: 0 | H9: =+C9+D9+E9 -> 14311.097 | I9: =+Bioacem!H34 -> 14792 | K9: negativo ganancia
B10: CORRIENTE | C10: =+'G. Corriente'!D7 -> 7703.17 | D10: =+'G. Corriente'!F38 -> 104600 | E10: =-'G. Corriente'!E38 -> -105314.9 | F10: =IF((SUM(C10:E10)=I10),0,H10-I10+G10) -> 26.47 | G10: =-0.4*D10/1000 -> -41.84 | H10: =+C10+D10+E10 -> 6988.27 | I10: =+'G. Corriente'!H34 -> 6919.96 | K10: positivo perdida
B11: EXTRA | C11: =+'G. Extra'!D7 -> 2194.99 | D11: =+'G. Extra'!F38 -> 12300 | E11: =-'G. Extra'!E38 -> -11656.48 | F11: =IF((SUM(C11:E11)=I11),0,H11-I11+G11) -> 16.15 | G11: =-0.4*D11/1000 -> -4.92 | H11: =+C11+D11+E11 -> 2838.51 | I11: =+'G. Extra'!H34 -> 2817.44
C12: =SUM(C9:C11) -> 22549.587 | D12: =SUM(D9:D11) -> 240300 | E12: =SUM(E9:E11) -> -238711.71 | F12: =SUM(F9:F11) -> -438.283 | G12: =SUM(G9:G11) -> -46.76 | H12: =SUM(H9:H11) -> 24137.877 | I12: =SUM(I9:I11) -> 24529.4
F16: =+F10-G10 -> 68.31
